Workbook

Sheet Hoja1
B1: Rubro | C1: Artículos | D1: Proveedor | E1: Habitual | G1: Moneda | H1: Unidad
B2: Embalaje | C2: Lunares 30mm (Blanco) | D2: Mix-57 | E2: si | G2: ARS | H2: kg
B3: Embalaje | C3: Lunares 30mm (Negro) | D3: Mix-57 | E3: si | G3: USD | H3: unidad
B4: Embalaje | C4: Lunares 30mm (Azul) | D4: Mix-57 | E4: si | H4: par
B5: Embalaje | C5: Lunares 30mm (Naranja) | D5: Mix-57 | E5: si | H5: bolsa
B6: Embalaje | C6: Lunares 15mm (Blanco) | D6: Mix-57 | E6: si | H6: rollo
B7: Embalaje | C7: Lunares 15mm (Negro) | D7: Mix-57 | E7: si | H7: m3
B8: Embalaje | C8: Lunares 15mm (Azul) | D8: Mix-57 | E8: si | H8: litro
B9: Embalaje | C9: Etiquetas DK 2205 (Fleje) | D9: Mix-57 | E9: si | H9: m
B10: Embalaje | C10: Etiquetas DK 1226 (Estandar) | D10: Mix-57 | E10: si | H10: bidón
B11: Embalaje | C11: Etiquetas Dobles 50x29 (embalaje) | D11: Mix-57 | E11: si
B12: Embalaje | C12: Etiquetas 30mm cuadrado (Verde) | D12: Mix-57 | E12: si
B13: Pintura | C13: Pinceles | D13: Coiro | E13: si
B14: Soldadura | C14: Tobera MB25 (Herrería) | D14: Diprov | E14: si
B15: Soldadura | C15: Difusor de Gas (Herrería) | D15: Diprov | E15: si
B16: Soldadura | C16: Repuesto roscado caudalímetro (Herrería) | D16: Diprov | E16: si
B17: Soldadura | C17: TUBO M6 0.9mm (Herrería) | D17: Diprov | E17: si
B18: Soldadura | C18: Lente máscara de soldar | D18: Diprov | E18: si
B19: Farmacia | C19: Curitas | D19: Farmacia | E19: si
B20: Farmacia | C20: Jabón neutro | D20: Farmacia | E20: si
B21: Farmacia | C21: Agua oxigenada | D21: Farmacia | E21: si
B22: Farmacia | C22: Alcohol | D22: Farmacia | E22: si
... B37: Lubricantes | C37: Lubricantes Aerosol | D37: Fercol | E37: si
B38: Lubricantes | C38: Limpia contactos
B39: Lubricantes | C39: Aceite DRAFOS MNL (Base SMR)
B40: Soldadura | C40: Pasta Antiadherente (Herrería) | D40: Diprov | E40: si
B41: Pintura | C41: Aerosol Negro Semi-mate | D41: Pinturería Giannoni | E41: si
B42: Pintura | C42: Aeroso Blanco Semi-mate | D42: Pinturería Giannoni | E42: si
B43: Herramientas | C43: Disco Sensitiva 350 mm | D43: Wurth | E43: si
B44: Herramientas | C44: Tijera corta chapa | D44: Coiro | E44: si
B45: Herramientas | C45: Hoja de Sierra P/Serrucho L2450mm | D45: Alpamet | E45: si
B46: Lubricantes | C46: Agua Destilada
B47: EPP | C47: Anteojos Seguridad | D47: Tech Safe | E47: si
B48: EPP | C48: Faja Lumbar TALLE S | D48: Tech Safe | E48: si
B49: EPP | C49: Faja Lumbar TALLE M | D49: Tech Safe | E49: si
B50: EPP | C50: Faja Lumbar TALLE L | D50: Tech Safe | E50: si
B51: EPP | C51: Faja Lumbar TALLE XL | D51: Tech Safe | E51: si
B52: EPP | C52: Faja Lumbar TALLE XXL | D52: Tech Safe | E52: si
B53: EPP | C53: Guantes Dyne 5 | D53: Roguant | E53: si
B54: EPP | C54: Guantes Poli (Tactil) 8# | D54: Roguant | E54: si
B55: EPP | C55: Guantes Poli (Tactil) 10# | D55: Tech Safe | E55: si
B56: EPP | C56: Guantes Dyne 5 | D56: Tech Safe | E56: no
B57: EPP | C57: Guantes Poli (Tactil) 8# | D57: Tech Safe | E57: no
B58: EPP | C58: Guantes Poli (Tactil) 10# | D58: Tech Safe | E58: no
... B66: Soldadura | C66: Alambre de Soldadura 0,9 mm | D66: Roberto Gustavo Q. | E66: si
B67: Embalaje | C67: Gancho P/Zuncho Crique
B68: Embalaje | C68: Funda de Cuero | D68: Diprin | E68: si
B69: Materia Prima | C69: Cerrojo 210 | D69: Prive | E69: si
B70: Embalaje | C70: Eslinga Violeta 5 mts x 1000kg | D70: Diprin | E70: si
B71: Embalaje | C71: Eslinga Violeta 3 mts x 1000kg | D71: Diprin | E71: si
B72: Embalaje | C72: Eslinga Amarillo 4 mts x 3000kg | D72: Diprin | E72: si
B73: Embalaje | C73: Eslinga Roja 4 mts x 5000kg | D73: Diprin | E73: si
B74: Embalaje | C74: Stretch 10 cm | D74: Mad Packaging | E74: si
B75: Embalaje | C75: Stretch 10 cm Negro | D75: Mad Packaging | E75: si
B76: Embalaje | C76: Stretch 10 cm Rojo | D76: Mad Packaging | E76: si
B77: Embalaje | C77: Stretch 50 cm C/Mango | D77: Mad Packaging | E77: si
B78: Soldadura | C78: Tubo de Gas (Atal) | D78: Roberto Gustavo Q. | E78: si
B79: Soldadura | C79: Tubo de Oxígeno | D79: Roberto Gustavo Q. | E79: si
B80: Combustible | C80: Gas Oil
B81: Combustible | C81: Gas Oil Premium
B82: Embalaje | C82: Zuncho Verde 19mm | D82: Formaco | E82: si
B83: Embalaje | C83: Telgopor 50x50x450 | D83: Frío Acero | E83: si
B84: Embalaje | C84: Telgopor 50x50x600 | D84: Frío Acero | E84: si
B85: Embalaje | C85: Bolsas Tubos x 100 mic | D85: Greenfilm | E85: si
B86: Embalaje | C86: Bolsas Tubos x 80 mic | D86: Greenfilm | E86: si
B87: Embalaje | C87: Bolsas Tubos x 100 mic | D87: Plásticos Aloha | E87: no
B88: Embalaje | C88: Bolsas Tubos x 80 mic | D88: Plásticos Aloha | E88: no
B89: Materia Prima | C89: Bisagras 20x80 | D89: Metalúrgica Diego | E89: si
B90: Embalaje | C90: Bolsas de Arpillera 100 x 60 | D90: Franco Damario | E90: si
B91: Embalaje | C91: Bolsas de Arpillera 80 x 60 | D91: Franco Damario | E91: si
B92: Embalaje | C92: Tacos 1 1/2" x 3" x 1130mm | D92: Aserradero Alonso | E92: si
B93: Embalaje | C93: Tacos 2" x 2 1/2" x 640mm | D93: Aserradero Alonso | E93: si
... B131: Limpieza | C131: Tacho de basura | D131: Imperio de la Limpieza | E131: si
B132: Reventa | C132: Tuerca Flange Zinc. 1/4" | D132: Distribuidora Tubulón
B133: Reventa | C133: Tuerca Flange Zinc. 3/8" | D133: Distribuidora Tubulón
B134: EPP | C134: Camisa Grafa | D134: Aníbal Roncoroni
B135: EPP | C135: Pantalón cargo Grafa | D135: Aníbal Roncoroni
B136: EPP | C136: Zapato Ombú prusiano | D136: Aníbal Roncoroni
B137: EPP | C137: Pantalón cargo ombú | D137: Tech Safe
B138: Reventa | C138: Varilla Roscada Zinc. 1/4" | D138: Dusvar
B139: Reventa | C139: Varilla Roscada Zinc. 3/8" | D139: Dusvar
B140: Reventa | C140: Varilla Roscada Zinc. 5/16" | D140: Dusvar
B141: Reventa | C141: Arandela Plana Zinc. 1/4" | D141: Disur
B142: Reventa | C142: Arandela Plana Zinc. 5/16" | D142: Disur
B143: Reventa | C143: Tor. Cab. Re. 1/4" | D143: Disur
... B154: Materia Prima | C154: GALVA 1220 X 2440 3,2 | D154: Pacheco Chapas
B155: Librería | C155: Resmas
B156: Librería | C156: Toner Laser HP 105
B157: Librería | C157: Toner 217 AC
B158: Librería | C158: Toner 510 A
B159: Embalaje | C159: Tacos 1 1/2" x 4" x 1100mm
B160: Embalaje | C160: Clavos 4"
B161: Materia Prima | C161: Cadena Calibrada
B162: Librería | C162: Artículos de librería - Varios
B163: Materia Prima | C163: PLANCHUELA 1 X 1/2 X 3/16 | D163: Casanova
B164: Materia Prima | C164: ANGULO 1" 1/4 X 1/8 x kg | D164: Casanova
B165: Materia Prima | C165: HIERRO T 1" 1/4 X 1/8 | D165: Casanova
B166: Pintura | C166: Pintura Amarillo 04 - 1 l | D166: Pinturería Giannoni
B167: Reventa | C167: Tor. Traba 3/8"
B168: Reventa | C168: Arandela Plana Zinc. 3/8"
...

Sheet Historial de compras
A1: Fecha | B1: Mes | C1: Artículo | D1: Rubro | E1: Proveedor | F1: Cantidad | G1: Unidad | H1: Precio Unitario ARS | I1: Precio Unitario USD | J1: DTO | K1: Moneda | L1: IVA | M1: Subtotal ARS | N1: TOTAL ARS | O1: TOTAL USD | P1: TC BNA | Q1: Observaciones
A2: 46154 | B2: =MONTH(Tabla2[[#This Row],[Fecha]]) -> 5 | C2: Stretch 10 cm | D2: =IFERROR(_xlfn.XLOOKUP(Tabla2[[#This Row],[Artículo]],Tabla1[Artículos],Tabla1[Rubro]),"") -> Embalaje | E2: Mad Packaging | F2: 185 | G2: kg | H2: 4528 | I2: =Tabla2[[#This Row],[Precio Unitario ARS]]/Tabla2[[#This Row],[TC BNA]] -> 3.2227758 | J2: 0 | K2: ARS | L2: 0.21 | M2: =(Tabla2[[#This Row],[Precio Unitario ARS]]-(Tabla2[[#This Row],[Precio Unitario ARS]]*Tabla2[[#This Row],[DTO]]))*Tabla2[[#This Row],[Cantidad]] -> 837680 | N2: =Tabla2[[#This Row],[Subtotal ARS]]+(Tabla2[[#This Row],[Subtotal ARS]]*Tabla2[[#This Row],[IVA]]) -> 1013592.8 | O2: =Tabla2[[#This Row],[TOTAL ARS]]/Tabla2[[#This Row],[TC BNA]] -> 721.41836 | P2: =_xlfn.XLOOKUP(A2,'TC_BNA xlsx'!A:A,'TC_BNA xlsx'!C:C,"No encontrado") -> 1405
A3: 46162 | B3: =MONTH(Tabla2[[#This Row],[Fecha]]) -> 5 | C3: Resmas | D3: =IFERROR(_xlfn.XLOOKUP(Tabla2[[#This Row],[Artículo]],Tabla1[Artículos],Tabla1[Rubro]),"") -> Librería | E3: Zicari Mariana Elena | F3: 10 | G3: unidad | H3: 5900 | I3: =Tabla2[[#This Row],[Precio Unitario ARS]]/Tabla2[[#This Row],[TC BNA]] -> 4.1549296 | J3: 0 | K3: ARS | L3: 0.21 | M3: =(Tabla2[[#This Row],[Precio Unitario ARS]]-(Tabla2[[#This Row],[Precio Unitario ARS]]*Tabla2[[#This Row],[DTO]]))*Tabla2[[#This Row],[Cantidad]] -> 59000 | N3: =Tabla2[[#This Row],[Subtotal ARS]]+(Tabla2[[#This Row],[Subtotal ARS]]*Tabla2[[#This Row],[IVA]]) -> 71390 | O3: =Tabla2[[#This Row],[TOTAL ARS]]/Tabla2[[#This Row],[TC BNA]] -> 50.274648 | P3: =_xlfn.XLOOKUP(A3,'TC_BNA xlsx'!A:A,'TC_BNA xlsx'!C:C,"No encontrado") -> 1420
A4: 46162 | B4: =MONTH(Tabla2[[#This Row],[Fecha]]) -> 5 | C4: Toner Laser HP 105 | D4: =IFERROR(_xlfn.XLOOKUP(Tabla2[[#This Row],[Artículo]],Tabla1[Artículos],Tabla1[Rubro]),"") -> Librería | E4: Zicari Mariana Elena | F4: 4 | G4: unidad | H4: 15225 | I4: =Tabla2[[#This Row],[Precio Unitario ARS]]/Tabla2[[#This Row],[TC BNA]] -> 10.721831 | J4: 0.15 | K4: ARS | L4: 0.21 | M4: =(Tabla2[[#This Row],[Precio Unitario ARS]]-(Tabla2[[#This Row],[Precio Unitario ARS]]*Tabla2[[#This Row],[DTO]]))*Tabla2[[#This Row],[Cantidad]] -> 51765 | N4: =Tabla2[[#This Row],[Subtotal ARS]]+(Tabla2[[#This Row],[Subtotal ARS]]*Tabla2[[#This Row],[IVA]]) -> 62635.65 | O4: =Tabla2[[#This Row],[TOTAL ARS]]/Tabla2[[#This Row],[TC BNA]] -> 44.109613 | P4: =_xlfn.XLOOKUP(A4,'TC_BNA xlsx'!A:A,'TC_BNA xlsx'!C:C,"No encontrado") -> 1420
A5: 46163 | B5: =MONTH(Tabla2[[#This Row],[Fecha]]) -> 5 | C5: Tuerca Flange Zinc. 1/4" | D5: =IFERROR(_xlfn.XLOOKUP(Tabla2[[#This Row],[Artículo]],Tabla1[Artículos],Tabla1[Rubro]),"") -> Reventa | E5: Distribuidora Tubulón | F5: 100800 | G5: unidad | H5: 18.78376 | I5: =Tabla2[[#This Row],[Precio Unitario ARS]]/Tabla2[[#This Row],[TC BNA]] -> 0.013321816 | J5: 0.1538 | K5: ARS | L5: 0.21 | M5: =(Tabla2[[#This Row],[Precio Unitario ARS]]-(Tabla2[[#This Row],[Precio Unitario ARS]]*Tabla2[[#This Row],[DTO]]))*Tabla2[[#This Row],[Cantidad]] -> 1602197.6 | N5: =Tabla2[[#This Row],[Subtotal ARS]]+(Tabla2[[#This Row],[Subtotal ARS]]*Tabla2[[#This Row],[IVA]]) -> 1938659.1 | O5: =Tabla2[[#This Row],[TOTAL ARS]]/Tabla2[[#This Row],[TC BNA]] -> 1374.9356 | P5: =_xlfn.XLOOKUP(A5,'TC_BNA xlsx'!A:A,'TC_BNA xlsx'!C:C,"No encontrado") -> 1410
A6: 46163 | B6: =MONTH(Tabla2[[#This Row],[Fecha]]) -> 5 | C6: Tuerca Flange Zinc. 3/8" | D6: =IFERROR(_xlfn.XLOOKUP(Tabla2[[#This Row],[Artículo]],Tabla1[Artículos],Tabla1[Rubro]),"") -> Reventa | E6: Distribuidora Tubulón | F6: 30800 | G6: unidad | H6: 38.91368 | I6: =Tabla2[[#This Row],[Precio Unitario ARS]]/Tabla2[[#This Row],[TC BNA]] -> 0.027598355 | J6: 0.1538 | K6: ARS | L6: 0.21 | M6: =(Tabla2[[#This Row],[Precio Unitario ARS]]-(Tabla2[[#This Row],[Precio Unitario ARS]]*Tabla2[[#This Row],[DTO]]))*Tabla2[[#This Row],[Cantidad]] -> 1014205.7 | N6: =Tabla2[[#This Row],[Subtotal ARS]]+(Tabla2[[#This Row],[Subtotal ARS]]*Tabla2[[#This Row],[IVA]]) -> 1227188.9 | O6: =Tabla2[[#This Row],[TOTAL ARS]]/Tabla2[[#This Row],[TC BNA]] -> 870.34672 | P6: =_xlfn.XLOOKUP(A6,'TC_BNA xlsx'!A:A,'TC_BNA xlsx'!C:C,"No encontrado") -> 1410
A7: 46163 | B7: =MONTH(Tabla2[[#This Row],[Fecha]]) -> 5 | C7: Tubo de Gas (Atal) | D7: =IFERROR(_xlfn.XLOOKUP(Tabla2[[#This Row],[Artículo]],Tabla1[Artículos],Tabla1[Rubro]),"") -> Soldadura | E7: Roberto Gustavo Q. | F7: 30 | G7: m3 | H7: 17500 | I7: =Tabla2[[#This Row],[Precio Unitario ARS]]/Tabla2[[#This Row],[TC BNA]] -> 12.411348 | J7: 0 | K7: ARS | M7: =(Tabla2[[#This Row],[Precio Unitario ARS]]-(Tabla2[[#This Row],[Precio Unitario ARS]]*Tabla2[[#This Row],[DTO]]))*Tabla2[[#This Row],[Cantidad]] -> 525000 | N7: =Tabla2[[#This Row],[Subtotal ARS]]+(Tabla2[[#This Row],[Subtotal ARS]]*Tabla2[[#This Row],[IVA]]) -> 525000 | O7: =Tabla2[[#This Row],[TOTAL ARS]]/Tabla2[[#This Row],[TC BNA]] -> 372.34043 | P7: =_xlfn.XLOOKUP(A7,'TC_BNA xlsx'!A:A,'TC_BNA xlsx'!C:C,"No encontrado") -> 1410
A8: 46163 | B8: =MONTH(Tabla2[[#This Row],[Fecha]]) -> 5 | C8: Alambre de Soldadura 0,9 mm | D8: =IFERROR(_xlfn.XLOOKUP(Tabla2[[#This Row],[Artículo]],Tabla1[Artículos],Tabla1[Rubro]),"") -> Soldadura | E8: Roberto Gustavo Q. | F8: 1 | G8: rollo | H8: 80000 | I8: =Tabla2[[#This Row],[Precio Unitario ARS]]/Tabla2[[#This Row],[TC BNA]] -> 56.737589 | J8: 0 | K8: ARS | M8: =(Tabla2[[#This Row],[Precio Unitario ARS]]-(Tabla2[[#This Row],[Precio Unitario ARS]]*Tabla2[[#This Row],[DTO]]))*Tabla2[[#This Row],[Cantidad]] -> 80000 | N8: =Tabla2[[#This Row],[Subtotal ARS]]+(Tabla2[[#This Row],[Subtotal ARS]]*Tabla2[[#This Row],[IVA]]) -> 80000 | O8: =Tabla2[[#This Row],[TOTAL ARS]]/Tabla2[[#This Row],[TC BNA]] -> 56.737589 | P8: =_xlfn.XLOOKUP(A8,'TC_BNA xlsx'!A:A,'TC_BNA xlsx'!C:C,"No encontrado") -> 1410
A9: 46164 | B9: =MONTH(Tabla2[[#This Row],[Fecha]]) -> 5 | C9: Papel higiénico Industrial | D9: =IFERROR(_xlfn.XLOOKUP(Tabla2[[#This Row],[Artículo]],Tabla1[Artículos],Tabla1[Rubro]),"") -> Limpieza | E9: Esdevi - Valeria | F9: 8 | G9: bolsa | H9: 7300 | I9: =Tabla2[[#This Row],[Precio Unitario ARS]]/Tabla2[[#This Row],[TC BNA]] -> 5.122807 | J9: 0 | K9: ARS | M9: =(Tabla2[[#This Row],[Precio Unitario ARS]]-(Tabla2[[#This Row],[Precio Unitario ARS]]*Tabla2[[#This Row],[DTO]]))*Tabla2[[#This Row],[Cantidad]] -> 58400 | N9: =Tabla2[[#This Row],[Subtotal ARS]]+(Tabla2[[#This Row],[Subtotal ARS]]*Tabla2[[#This Row],[IVA]]) -> 58400 | O9: =Tabla2[[#This Row],[TOTAL ARS]]/Tabla2[[#This Row],[TC BNA]] -> 40.982456 | P9: =_xlfn.XLOOKUP(A9,'TC_BNA xlsx'!A:A,'TC_BNA xlsx'!C:C,"No encontrado") -> 1425
A10: 46164 | B10: =MONTH(Tabla2[[#This Row],[Fecha]]) -> 5 | C10: Dispénser de rollo de cocina | D10: =IFERROR(_xlfn.XLOOKUP(Tabla2[[#This Row],[Artículo]],Tabla1[Artículos],Tabla1[Rubro]),"") -> Limpieza | E10: Esdevi - Valeria | F10: 7 | G10: bolsa | H10: 9900 | I10: =Tabla2[[#This Row],[Precio Unitario ARS]]/Tabla2[[#This Row],[TC BNA]] -> 6.9473684 | J10: 0 | K10: ARS | M10: =(Tabla2[[#This Row],[Precio Unitario ARS]]-(Tabla2[[#This Row],[Precio Unitario ARS]]*Tabla2[[#This Row],[DTO]]))*Tabla2[[#This Row],[Cantidad]] -> 69300 | N10: =Tabla2[[#This Row],[Subtotal ARS]]+(Tabla2[[#This Row],[Subtotal ARS]]*Tabla2[[#This Row],[IVA]]) -> 69300 | O10: =Tabla2[[#This Row],[TOTAL ARS]]/Tabla2[[#This Row],[TC BNA]] -> 48.631579 | P10: =_xlfn.XLOOKUP(A10,'TC_BNA xlsx'!A:A,'TC_BNA xlsx'!C:C,"No encontrado") -> 1425
A11: 46164 | B11: =MONTH(Tabla2[[#This Row],[Fecha]]) -> 5 | C11: Guantes Poli (Tactil) 8# | D11: =IFERROR(_xlfn.XLOOKUP(Tabla2[[#This Row],[Artículo]],Tabla1[Artículos],Tabla1[Rubro]),"") -> EPP | E11: Tech Safe | F11: 24 | G11: par | H11: 600 | I11: =Tabla2[[#This Row],[Precio Unitario ARS]]/Tabla2[[#This Row],[TC BNA]] -> 0.42105263 | J11: 0 | K11: ARS | L11: 0.21 | M11: =(Tabla2[[#This Row],[Precio Unitario ARS]]-(Tabla2[[#This Row],[Precio Unitario ARS]]*Tabla2[[#This Row],[DTO]]))*Tabla2[[#This Row],[Cantidad]] -> 14400 | N11: =Tabla2[[#This Row],[Subtotal ARS]]+(Tabla2[[#This Row],[Subtotal ARS]]*Tabla2[[#This Row],[IVA]]) -> 17424 | O11: =Tabla2[[#This Row],[TOTAL ARS]]/Tabla2[[#This Row],[TC BNA]] -> 12.227368 | P11: =_xlfn.XLOOKUP(A11,'TC_BNA xlsx'!A:A,'TC_BNA xlsx'!C:C,"No encontrado") -> 1425
A12: 46164 | B12: =MONTH(Tabla2[[#This Row],[Fecha]]) -> 5 | C12: Guantes Poli (Tactil) 10# | D12: =IFERROR(_xlfn.XLOOKUP(Tabla2[[#This Row],[Artículo]],Tabla1[Artículos],Tabla1[Rubro]),"") -> EPP | E12: Tech Safe | F12: 24 | G12: par | H12: 600 | I12: =Tabla2[[#This Row],[Precio Unitario ARS]]/Tabla2[[#This Row],[TC BNA]] -> 0.42105263 | J12: 0 | K12: ARS | L12: 0.21 | M12: =(Tabla2[[#This Row],[Precio Unitario ARS]]-(Tabla2[[#This Row],[Precio Unitario ARS]]*Tabla2[[#This Row],[DTO]]))*Tabla2[[#This Row],[Cantidad]] -> 14400 | N12: =Tabla2[[#This Row],[Subtotal ARS]]+(Tabla2[[#This Row],[Subtotal ARS]]*Tabla2[[#This Row],[IVA]]) -> 17424 | O12: =Tabla2[[#This Row],[TOTAL ARS]]/Tabla2[[#This Row],[TC BNA]] -> 12.227368 | P12: =_xlfn.XLOOKUP(A12,'TC_BNA xlsx'!A:A,'TC_BNA xlsx'!C:C,"No encontrado") -> 1425
A13: 46164 | B13: =MONTH(Tabla2[[#This Row],[Fecha]]) -> 5 | C13: Guantes Dyne 5 | D13: =IFERROR(_xlfn.XLOOKUP(Tabla2[[#This Row],[Artículo]],Tabla1[Artículos],Tabla1[Rubro]),"") -> EPP | E13: Tech Safe | F13: 12 | G13: par | H13: 4295 | I13: =Tabla2[[#This Row],[Precio Unitario ARS]]/Tabla2[[#This Row],[TC BNA]] -> 3.0140351 | J13: 0 | K13: ARS | L13: 0.21 | M13: =(Tabla2[[#This Row],[Precio Unitario ARS]]-(Tabla2[[#This Row],[Precio Unitario ARS]]*Tabla2[[#This Row],[DTO]]))*Tabla2[[#This Row],[Cantidad]] -> 51540 | N13: =Tabla2[[#This Row],[Subtotal ARS]]+(Tabla2[[#This Row],[Subtotal ARS]]*Tabla2[[#This Row],[IVA]]) -> 62363.4 | O13: =Tabla2[[#This Row],[TOTAL ARS]]/Tabla2[[#This Row],[TC BNA]] -> 43.763789 | P13: =_xlfn.XLOOKUP(A13,'TC_BNA xlsx'!A:A,'TC_BNA xlsx'!C:C,"No encontrado") -> 1425
A14: 46168 | B14: =MONTH(Tabla2[[#This Row],[Fecha]]) -> 5 | C14: Arandela Plana Zinc. 1/4" | D14: =IFERROR(_xlfn.XLOOKUP(Tabla2[[#This Row],[Artículo]],Tabla1[Artículos],Tabla1[Rubro]),"") -> Reventa | E14: Disur | F14: 63.5 | G14: kg | H14: 4800 | I14: =Tabla2[[#This Row],[Precio Unitario ARS]]/Tabla2[[#This Row],[TC BNA]] -> 3.3566434 | J14: 0 | K14: ARS | L14: 0.21 | M14: =(Tabla2[[#This Row],[Precio Unitario ARS]]-(Tabla2[[#This Row],[Precio Unitario ARS]]*Tabla2[[#This Row],[DTO]]))*Tabla2[[#This Row],[Cantidad]] -> 304800 | N14: =Tabla2[[#This Row],[Subtotal ARS]]+(Tabla2[[#This Row],[Subtotal ARS]]*Tabla2[[#This Row],[IVA]]) -> 368808 | O14: =Tabla2[[#This Row],[TOTAL ARS]]/Tabla2[[#This Row],[TC BNA]] -> 257.90769 | P14: =_xlfn.XLOOKUP(A14,'TC_BNA xlsx'!A:A,'TC_BNA xlsx'!C:C,"No encontrado") -> 1430
A15: 46168 | B15: =MONTH(Tabla2[[#This Row],[Fecha]]) -> 5 | C15: Arandela Plana Zinc. 3/8" | D15: =IFERROR(_xlfn.XLOOKUP(Tabla2[[#This Row],[Artículo]],Tabla1[Artículos],Tabla1[Rubro]),"") -> Reventa | E15: Disur | F15: 50 | G15: kg | H15: 4185 | I15: =Tabla2[[#This Row],[Precio Unitario ARS]]/Tabla2[[#This Row],[TC BNA]] -> 2.9265734 | J15: 0 | K15: ARS | L15: 0.21 | M15: =(Tabla2[[#This Row],[Precio Unitario ARS]]-(Tabla2[[#This Row],[Precio Unitario ARS]]*Tabla2[[#This Row],[DTO]]))*Tabla2[[#This Row],[Cantidad]] -> 209250 | N15: =Tabla2[[#This Row],[Subtotal ARS]]+(Tabla2[[#This Row],[Subtotal ARS]]*Tabla2[[#This Row],[IVA]]) -> 253192.5 | O15: =Tabla2[[#This Row],[TOTAL ARS]]/Tabla2[[#This Row],[TC BNA]] -> 177.05769 | P15: =_xlfn.XLOOKUP(A15,'TC_BNA xlsx'!A:A,'TC_BNA xlsx'!C:C,"No encontrado") -> 1430
A16: 46168 | B16: =MONTH(Tabla2[[#This Row],[Fecha]]) -> 5 | C16: Arandela Plana Zinc. 5/16" | D16: =IFERROR(_xlfn.XLOOKUP(Tabla2[[#This Row],[Artículo]],Tabla1[Artículos],Tabla1[Rubro]),"") -> Reventa | E16: Disur | F16: 35 | G16: kg | H16: 4890 | I16: =Tabla2[[#This Row],[Precio Unitario ARS]]/Tabla2[[#This Row],[TC BNA]] -> 3.4195804 | J16: 0 | K16: ARS | L16: 0.21 | M16: =(Tabla2[[#This Row],[Precio Unitario ARS]]-(Tabla2[[#This Row],[Precio Unitario ARS]]*Tabla2[[#This Row],[DTO]]))*Tabla2[[#This Row],[Cantidad]] -> 171150 | N16: =Tabla2[[#This Row],[Subtotal ARS]]+(Tabla2[[#This Row],[Subtotal ARS]]*Tabla2[[#This Row],[IVA]]) -> 207091.5 | O16: =Tabla2[[#This Row],[TOTAL ARS]]/Tabla2[[#This Row],[TC BNA]] -> 144.81923 | P16: =_xlfn.XLOOKUP(A16,'TC_BNA xlsx'!A:A,'TC_BNA xlsx'!C:C,"No encontrado") -> 1430
A17: 46168 | B17: =MONTH(Tabla2[[#This Row],[Fecha]]) -> 5 | C17: Tor. Cab. Re. 1/4" | D17: =IFERROR(_xlfn.XLOOKUP(Tabla2[[#This Row],[Artículo]],Tabla1[Artículos],Tabla1[Rubro]),"") -> Reventa | E17: Disur | F17: 10000 | G17: unidad | H17: 29.2 | I17: =Tabla2[[#This Row],[Precio Unitario ARS]]/Tabla2[[#This Row],[TC BNA]] -> 0.02041958 | J17: 0 | K17: ARS | L17: 0.21 | M17: =(Tabla2[[#This Row],[Precio Unitario ARS]]-(Tabla2[[#This Row],[Precio Unitario ARS]]*Tabla2[[#This Row],[DTO]]))*Tabla2[[#This Row],[Cantidad]] -> 292000 | N17: =Tabla2[[#This Row],[Subtotal ARS]]+(Tabla2[[#This Row],[Subtotal ARS]]*Tabla2[[#This Row],[IVA]]) -> 353320 | O17: =Tabla2[[#This Row],[TOTAL ARS]]/Tabla2[[#This Row],[TC BNA]] -> 247.07692 | P17: =_xlfn.XLOOKUP(A17,'TC_BNA xlsx'!A:A,'TC_BNA xlsx'!C:C,"No encontrado") -> 1430
A18: 46168 | B18: =MONTH(Tabla2[[#This Row],[Fecha]]) -> 5 | C18: Tor. Traba 1/4" | D18: =IFERROR(_xlfn.XLOOKUP(Tabla2[[#This Row],[Artículo]],Tabla1[Artículos],Tabla1[Rubro]),"") -> Reventa | E18: Disur | F18: 60000 | G18: unidad | H18: 27.97 | I18: =Tabla2[[#This Row],[Precio Unitario ARS]]/Tabla2[[#This Row],[TC BNA]] -> 0.019559441 | J18: 0 | K18: ARS | L18: 0.21 | M18: =(Tabla2[[#This Row],[Precio Unitario ARS]]-(Tabla2[[#This Row],[Precio Unitario ARS]]*Tabla2[[#This Row],[DTO]]))*Tabla2[[#This Row],[Cantidad]] -> 1678200 | N18: =Tabla2[[#This Row],[Subtotal ARS]]+(Tabla2[[#This Row],[Subtotal ARS]]*Tabla2[[#This Row],[IVA]]) -> 2030622 | O18: =Tabla2[[#This Row],[TOTAL ARS]]/Tabla2[[#This Row],[TC BNA]] -> 1420.0154 | P18: =_xlfn.XLOOKUP(A18,'TC_BNA xlsx'!A:A,'TC_BNA xlsx'!C:C,"No encontrado") -> 1430
A19: 46168 | B19: =MONTH(Tabla2[[#This Row],[Fecha]]) -> 5 | C19: Tuerca Zinc. 1/4" | D19: =IFERROR(_xlfn.XLOOKUP(Tabla2[[#This Row],[Artículo]],Tabla1[Artículos],Tabla1[Rubro]),"") -> Reventa | E19: Disur | F19: 20000 | G19: unidad | H19: 12.5 | I19: =Tabla2[[#This Row],[Precio Unitario ARS]]/Tabla2[[#This Row],[TC BNA]] -> 0.0087412587 | J19: 0 | K19: ARS | L19: 0.21 | M19: =(Tabla2[[#This Row],[Precio Unitario ARS]]-(Tabla2[[#This Row],[Precio Unitario ARS]]*Tabla2[[#This Row],[DTO]]))*Tabla2[[#This Row],[Cantidad]] -> 250000 | N19: =Tabla2[[#This Row],[Subtotal ARS]]+(Tabla2[[#This Row],[Subtotal ARS]]*Tabla2[[#This Row],[IVA]]) -> 302500 | O19: =Tabla2[[#This Row],[TOTAL ARS]]/Tabla2[[#This Row],[TC BNA]] -> 211.53846 | P19: =_xlfn.XLOOKUP(A19,'TC_BNA xlsx'!A:A,'TC_BNA xlsx'!C:C,"No encontrado") -> 1430
A20: 46168 | B20: =MONTH(Tabla2[[#This Row],[Fecha]]) -> 5 | C20: Tuerca Zinc. 3/8" | D20: =IFERROR(_xlfn.XLOOKUP(Tabla2[[#This Row],[Artículo]],Tabla1[Artículos],Tabla1[Rubro]),"") -> Reventa | E20: Disur | F20: 6800 | G20: unidad | H20: 26 | I20: =Tabla2[[#This Row],[Precio Unitario ARS]]/Tabla2[[#This Row],[TC BNA]] -> 0.018181818 | J20: 0 | K20: ARS | L20: 0.21 | M20: =(Tabla2[[#This Row],[Precio Unitario ARS]]-(Tabla2[[#This Row],[Precio Unitario ARS]]*Tabla2[[#This Row],[DTO]]))*Tabla2[[#This Row],[Cantidad]] -> 176800 | N20: =Tabla2[[#This Row],[Subtotal ARS]]+(Tabla2[[#This Row],[Subtotal ARS]]*Tabla2[[#This Row],[IVA]]) -> 213928 | O20: =Tabla2[[#This Row],[TOTAL ARS]]/Tabla2[[#This Row],[TC BNA]] -> 149.6 | P20: =_xlfn.XLOOKUP(A20,'TC_BNA xlsx'!A:A,'TC_BNA xlsx'!C:C,"No encontrado") -> 1430
A21: 46168 | B21: =MONTH(Tabla2[[#This Row],[Fecha]]) -> 5 | C21: Tuerca Zinc. 5/16" | D21: =IFERROR(_xlfn.XLOOKUP(Tabla2[[#This Row],[Artículo]],Tabla1[Artículos],Tabla1[Rubro]),"") -> Reventa | E21: Disur | F21: 6000 | G21: unidad | H21: 18.6 | I21: =Tabla2[[#This Row],[Precio Unitario ARS]]/Tabla2[[#This Row],[TC BNA]] -> 0.013006993 | J21: 0 | K21: ARS | L21: 0.21 | M21: =(Tabla2[[#This Row],[Precio Unitario ARS]]-(Tabla2[[#This Row],[Precio Unitario ARS]]*Tabla2[[#This Row],[DTO]]))*Tabla2[[#This Row],[Cantidad]] -> 111600 | N21: =Tabla2[[#This Row],[Subtotal ARS]]+(Tabla2[[#This Row],[Subtotal ARS]]*Tabla2[[#This Row],[IVA]]) -> 135036 | O21: =Tabla2[[#This Row],[TOTAL ARS]]/Tabla2[[#This Row],[TC BNA]] -> 94.430769 | P21: =_xlfn.XLOOKUP(A21,'TC_BNA xlsx'!A:A,'TC_BNA xlsx'!C:C,"No encontrado") -> 1430
A22: 46168 | B22: =MONTH(Tabla2[[#This Row],[Fecha]]) -> 5 | C22: Lysoform | D22: =IFERROR(_xlfn.XLOOKUP(Tabla2[[#This Row],[Artículo]],Tabla1[Artículos],Tabla1[Rubro]),"") -> Limpieza | E22: Imperio de la Limpieza | F22: 10 | G22: unidad | H22: 3619.83 | I22: =Tabla2[[#This Row],[Precio Unitario ARS]]/Tabla2[[#This Row],[TC BNA]] -> 2.5313497 | J22: 0 | K22: ARS | L22: 0.21 | M22: =(Tabla2[[#This Row],[Precio Unitario ARS]]-(Tabla2[[#This Row],[Precio Unitario ARS]]*Tabla2[[#This Row],[DTO]]))*Tabla2[[#This Row],[Cantidad]] -> 36198.3 | N22: =Tabla2[[#This Row],[Subtotal ARS]]+(Tabla2[[#This Row],[Subtotal ARS]]*Tabla2[[#This Row],[IVA]]) -> 43799.943 | O22: =Tabla2[[#This Row],[TOTAL ARS]]/Tabla2[[#This Row],[TC BNA]] -> 30.629331 | P22: =_xlfn.XLOOKUP(A22,'TC_BNA xlsx'!A:A,'TC_BNA xlsx'!C:C,"No encontrado") -> 1430
A23: 46168 | B23: =MONTH(Tabla2[[#This Row],[Fecha]]) -> 5 | C23: Bolsas 50x70 | D23: =IFERROR(_xlfn.XLOOKUP(Tabla2[[#This Row],[Artículo]],Tabla1[Artículos],Tabla1[Rubro]),"") -> Limpieza | E23: Imperio de la Limpieza | F23: 130 | G23: unidad | H23: =611.57/10 -> 61.157 | I23: =Tabla2[[#This Row],[Precio Unitario ARS]]/Tabla2[[#This Row],[TC BNA]] -> 0.042767133 | J23: 0 | K23: ARS | L23: 0.21 | M23: =(Tabla2[[#This Row],[Precio Unitario ARS]]-(Tabla2[[#This Row],[Precio Unitario ARS]]*Tabla2[[#This Row],[DTO]]))*Tabla2[[#This Row],[Cantidad]] -> 7950.41 | N23: =Tabla2[[#This Row],[Subtotal ARS]]+(Tabla2[[#This Row],[Subtotal ARS]]*Tabla2[[#This Row],[IVA]]) -> 9619.9961 | O23: =Tabla2[[#This Row],[TOTAL ARS]]/Tabla2[[#This Row],[TC BNA]] -> 6.72727 | P23: =_xlfn.XLOOKUP(A23,'TC_BNA xlsx'!A:A,'TC_BNA xlsx'!C:C,"No encontrado") -> 1430
A24: 46168 | B24: =MONTH(Tabla2[[#This Row],[Fecha]]) -> 5 | C24: Bolsas 80x110 | D24: =IFERROR(_xlfn.XLOOKUP(Tabla2[[#This Row],[Artículo]],Tabla1[Artículos],Tabla1[Rubro]),"") -> Limpieza | E24: Imperio de la Limpieza | F24: 110 | G24: unidad | H24: =1876.03/10 -> 187.603 | I24: =Tabla2[[#This Row],[Precio Unitario ARS]]/Tabla2[[#This Row],[TC BNA]] -> 0.13119091 | J24: 0 | K24: ARS | L24: 0.21 | M24: =(Tabla2[[#This Row],[Precio Unitario ARS]]-(Tabla2[[#This Row],[Precio Unitario ARS]]*Tabla2[[#This Row],[DTO]]))*Tabla2[[#This Row],[Cantidad]] -> 20636.33 | N24: =Tabla2[[#This Row],[Subtotal ARS]]+(Tabla2[[#This Row],[Subtotal ARS]]*Tabla2[[#This Row],[IVA]]) -> 24969.959 | O24: =Tabla2[[#This Row],[TOTAL ARS]]/Tabla2[[#This Row],[TC BNA]] -> 17.46151 | P24: =_xlfn.XLOOKUP(A24,'TC_BNA xlsx'!A:A,'TC_BNA xlsx'!C:C,"No encontrado") -> 1430
A25: 46168 | B25: =MONTH(Tabla2[[#This Row],[Fecha]]) -> 5 | C25: Esponjas | D25: =IFERROR(_xlfn.XLOOKUP(Tabla2[[#This Row],[Artículo]],Tabla1[Artículos],Tabla1[Rubro]),"") -> Limpieza | E25: Imperio de la Limpieza | F25: 6 | G25: unidad | H25: 520.66 | I25: =Tabla2[[#This Row],[Precio Unitario ARS]]/Tabla2[[#This Row],[TC BNA]] -> 0.3640979 | J25: 0 | K25: ARS | L25: 0.21 | M25: =(Tabla2[[#This Row],[Precio Unitario ARS]]-(Tabla2[[#This Row],[Precio Unitario ARS]]*Tabla2[[#This Row],[DTO]]))*Tabla2[[#This Row],[Cantidad]] -> 3123.96 | N25: =Tabla2[[#This Row],[Subtotal ARS]]+(Tabla2[[#This Row],[Subtotal ARS]]*Tabla2[[#This Row],[IVA]]) -> 3779.9916 | O25: =Tabla2[[#This Row],[TOTAL ARS]]/Tabla2[[#This Row],[TC BNA]] -> 2.6433508 | P25: =_xlfn.XLOOKUP(A25,'TC_BNA xlsx'!A:A,'TC_BNA xlsx'!C:C,"No encontrado") -> 1430
A26: 46168 | B26: =MONTH(Tabla2[[#This Row],[Fecha]]) -> 5 | C26: Desodorante p/piso Lavanda | D26: =IFERROR(_xlfn.XLOOKUP(Tabla2[[#This Row],[Artículo]],Tabla1[Artículos],Tabla1[Rubro]),"") -> Limpieza | E26: Imperio de la Limpieza | F26: 5 | G26: litro | H26: =2809.91/5 -> 561.982 | I26: =Tabla2[[#This Row],[Precio Unitario ARS]]/Tabla2[[#This Row],[TC BNA]] -> 0.39299441 | J26: 0 | K26: ARS | L26: 0.21 | M26: =(Tabla2[[#This Row],[Precio Unitario ARS]]-(Tabla2[[#This Row],[Precio Unitario ARS]]*Tabla2[[#This Row],[DTO]]))*Tabla2[[#This Row],[Cantidad]] -> 2809.91 | N26: =Tabla2[[#This Row],[Subtotal ARS]]+(Tabla2[[#This Row],[Subtotal ARS]]*Tabla2[[#This Row],[IVA]]) -> 3399.9911 | O26: =Tabla2[[#This Row],[TOTAL ARS]]/Tabla2[[#This Row],[TC BNA]] -> 2.3776162 | P26: =_xlfn.XLOOKUP(A26,'TC_BNA xlsx'!A:A,'TC_BNA xlsx'!C:C,"No encontrado") -> 1430
A27: 46168 | B27: =MONTH(Tabla2[[#This Row],[Fecha]]) -> 5 | C27: Guantes de limpieza (Talle L) | D27: =IFERROR(_xlfn.XLOOKUP(Tabla2[[#This Row],[Artículo]],Tabla1[Artículos],Tabla1[Rubro]),"") -> Limpieza | E27: Imperio de la Limpieza | F27: 1 | G27: unidad | H27: 2917.35 | I27: =Tabla2[[#This Row],[Precio Unitario ARS]]/Tabla2[[#This Row],[TC BNA]] -> 2.0401049 | J27: 0 | K27: ARS | L27: 0.21 | M27: =(Tabla2[[#This Row],[Precio Unitario ARS]]-(Tabla2[[#This Row],[Precio Unitario ARS]]*Tabla2[[#This Row],[DTO]]))*Tabla2[[#This Row],[Cantidad]] -> 2917.35 | N27: =Tabla2[[#This Row],[Subtotal ARS]]+(Tabla2[[#This Row],[Subtotal ARS]]*Tabla2[[#This Row],[IVA]]) -> 3529.9935 | O27: =Tabla2[[#This Row],[TOTAL ARS]]/Tabla2[[#This Row],[TC BNA]] -> 2.4685269 | P27: =_xlfn.XLOOKUP(A27,'TC_BNA xlsx'!A:A,'TC_BNA xlsx'!C:C,"No encontrado") -> 1430
A28: 46168 | B28: =MONTH(Tabla2[[#This Row],[Fecha]]) -> 5 | C28: Jabón líquido | D28: =IFERROR(_xlfn.XLOOKUP(Tabla2[[#This Row],[Artículo]],Tabla1[Artículos],Tabla1[Rubro]),"") -> Limpieza | E28: Imperio de la Limpieza | F28: 5 | G28: litro | H28: =8462.8/5 -> 1692.56 | I28: =Tabla2[[#This Row],[Precio Unitario ARS]]/Tabla2[[#This Row],[TC BNA]] -> 1.1836084 | J28: 0 | K28: ARS | L28: 0.21 | M28: =(Tabla2[[#This Row],[Precio Unitario ARS]]-(Tabla2[[#This Row],[Precio Unitario ARS]]*Tabla2[[#This Row],[DTO]]))*Tabla2[[#This Row],[Cantidad]] -> 8462.8 | N28: =Tabla2[[#This Row],[Subtotal ARS]]+(Tabla2[[#This Row],[Subtotal ARS]]*Tabla2[[#This Row],[IVA]]) -> 10239.988 | O28: =Tabla2[[#This Row],[TOTAL ARS]]/Tabla2[[#This Row],[TC BNA]] -> 7.1608308 | P28: =_xlfn.XLOOKUP(A28,'TC_BNA xlsx'!A:A,'TC_BNA xlsx'!C:C,"No encontrado") -> 1430
A29: 46168 | B29: =MONTH(Tabla2[[#This Row],[Fecha]]) -> 5 | C29: Detergente | D29: =IFERROR(_xlfn.XLOOKUP(Tabla2[[#This Row],[Artículo]],Tabla1[Artículos],Tabla1[Rubro]),"") -> Limpieza | E29: Imperio de la Limpieza | F29: 5 | G29: litro | H29: =8239.66/5 -> 1647.932 | I29: =Tabla2[[#This Row],[Precio Unitario ARS]]/Tabla2[[#This Row],[TC BNA]] -> 1.1524 | J29: 0 | K29: ARS | L29: 0.21 | M29: =(Tabla2[[#This Row],[Precio Unitario ARS]]-(Tabla2[[#This Row],[Precio Unitario ARS]]*Tabla2[[#This Row],[DTO]]))*Tabla2[[#This Row],[Cantidad]] -> 8239.66 | N29: =Tabla2[[#This Row],[Subtotal ARS]]+(Tabla2[[#This Row],[Subtotal ARS]]*Tabla2[[#This Row],[IVA]]) -> 9969.9886 | O29: =Tabla2[[#This Row],[TOTAL ARS]]/Tabla2[[#This Row],[TC BNA]] -> 6.97202 | P29: =_xlfn.XLOOKUP(A29,'TC_BNA xlsx'!A:A,'TC_BNA xlsx'!C:C,"No encontrado") -> 1430
A30: 46168 | B30: =MONTH(Tabla2[[#This Row],[Fecha]]) -> 5 | C30: Rejilla | D30: =IFERROR(_xlfn.XLOOKUP(Tabla2[[#This Row],[Artículo]],Tabla1[Artículos],Tabla1[Rubro]),"") -> Limpieza | E30: Imperio de la Limpieza | F30: 2 | G30: unidad | H30: 710.74 | I30: =Tabla2[[#This Row],[Precio Unitario ARS]]/Tabla2[[#This Row],[TC BNA]] -> 0.49702098 | J30: 0 | K30: ARS | L30: 0.21 | M30: =(Tabla2[[#This Row],[Precio Unitario ARS]]-(Tabla2[[#This Row],[Precio Unitario ARS]]*Tabla2[[#This Row],[DTO]]))*Tabla2[[#This Row],[Cantidad]] -> 1421.48 | N30: =Tabla2[[#This Row],[Subtotal ARS]]+(Tabla2[[#This Row],[Subtotal ARS]]*Tabla2[[#This Row],[IVA]]) -> 1719.9908 | O30: =Tabla2[[#This Row],[TOTAL ARS]]/Tabla2[[#This Row],[TC BNA]] -> 1.2027908 | P30: =_xlfn.XLOOKUP(A30,'TC_BNA xlsx'!A:A,'TC_BNA xlsx'!C:C,"No encontrado") -> 1430
A31: 46168 | B31: =MONTH(Tabla2[[#This Row],[Fecha]]) -> 5 | C31: Trapo de piso | D31: =IFERROR(_xlfn.XLOOKUP(Tabla2[[#This Row],[Artículo]],Tabla1[Artículos],Tabla1[Rubro]),"") -> Limpieza | E31: Imperio de la Limpieza | F31: 4 | G31: unidad | H31: 1661.15 | I31: =Tabla2[[#This Row],[Precio Unitario ARS]]/Tabla2[[#This Row],[TC BNA]] -> 1.1616434 | J31: 0 | K31: ARS | L31: 0.21 | M31: =(Tabla2[[#This Row],[Precio Unitario ARS]]-(Tabla2[[#This Row],[Precio Unitario ARS]]*Tabla2[[#This Row],[DTO]]))*Tabla2[[#This Row],[Cantidad]] -> 6644.6 | N31: =Tabla2[[#This Row],[Subtotal ARS]]+(Tabla2[[#This Row],[Subtotal ARS]]*Tabla2[[#This Row],[IVA]]) -> 8039.966 | O31: =Tabla2[[#This Row],[TOTAL ARS]]/Tabla2[[#This Row],[TC BNA]] -> 5.6223538 | P31: =_xlfn.XLOOKUP(A31,'TC_BNA xlsx'!A:A,'TC_BNA xlsx'!C:C,"No encontrado") -> 1430
A32: 46168 | B32: =MONTH(Tabla2[[#This Row],[Fecha]]) -> 5 | C32: Saphirus | D32: =IFERROR(_xlfn.XLOOKUP(Tabla2[[#This Row],[Artículo]],Tabla1[Artículos],Tabla1[Rubro]),"") -> Limpieza | E32: Imperio de la Limpieza | F32: 7 | G32: unidad | H32: 4818.18 | I32: =Tabla2[[#This Row],[Precio Unitario ARS]]/Tabla2[[#This Row],[TC BNA]] -> 3.3693566 | J32: 0 | K32: ARS | L32: 0.21 | M32: =(Tabla2[[#This Row],[Precio Unitario ARS]]-(Tabla2[[#This Row],[Precio Unitario ARS]]*Tabla2[[#This Row],[DTO]]))*Tabla2[[#This Row],[Cantidad]] -> 33727.26 | N32: =Tabla2[[#This Row],[Subtotal ARS]]+(Tabla2[[#This Row],[Subtotal ARS]]*Tabla2[[#This Row],[IVA]]) -> 40809.985 | O32: =Tabla2[[#This Row],[TOTAL ARS]]/Tabla2[[#This Row],[TC BNA]] -> 28.538451 | P32: =_xlfn.XLOOKUP(A32,'TC_BNA xlsx'!A:A,'TC_BNA xlsx'!C:C,"No encontrado") -> 1430
A33: 46168 | B33: =MONTH(Tabla2[[#This Row],[Fecha]]) -> 5 | C33: Esponja tipo patito | D33: =IFERROR(_xlfn.XLOOKUP(Tabla2[[#This Row],[Artículo]],Tabla1[Artículos],Tabla1[Rubro]),"") -> Limpieza | E33: Imperio de la Limpieza | F33: 2 | G33: unidad | H33: 719 | I33: =Tabla2[[#This Row],[Precio Unitario ARS]]/Tabla2[[#This Row],[TC BNA]] -> 0.5027972 | J33: 0 | K33: ARS | L33: 0.21 | M33: =(Tabla2[[#This Row],[Precio Unitario ARS]]-(Tabla2[[#This Row],[Precio Unitario ARS]]*Tabla2[[#This Row],[DTO]]))*Tabla2[[#This Row],[Cantidad]] -> 1438 | N33: =Tabla2[[#This Row],[Subtotal ARS]]+(Tabla2[[#This Row],[Subtotal ARS]]*Tabla2[[#This Row],[IVA]]) -> 1739.98 | O33: =Tabla2[[#This Row],[TOTAL ARS]]/Tabla2[[#This Row],[TC BNA]] -> 1.2167692 | P33: =_xlfn.XLOOKUP(A33,'TC_BNA xlsx'!A:A,'TC_BNA xlsx'!C:C,"No encontrado") -> 1430
A34: 46169 | B34: =MONTH(Tabla2[[#This Row],[Fecha]]) -> 5 | C34: EU-250 | D34: =IFERROR(_xlfn.XLOOKUP(Tabla2[[#This Row],[Artículo]],Tabla1[Artículos],Tabla1[Rubro]),"") -> Servicio | E34: MTZ | F34: 726 | G34: unidad | H34: 517 | I34: =Tabla2[[#This Row],[Precio Unitario ARS]]/Tabla2[[#This Row],[TC BNA]] -> 0.36153846 | J34: 0 | K34: ARS | M34: =(Tabla2[[#This Row],[Precio Unitario ARS]]-(Tabla2[[#This Row],[Precio Unitario ARS]]*Tabla2[[#This Row],[DTO]]))*Tabla2[[#This Row],[Cantidad]] -> 375342 | N34: =Tabla2[[#This Row],[Subtotal ARS]]+(Tabla2[[#This Row],[Subtotal ARS]]*Tabla2[[#This Row],[IVA]]) -> 375342 | O34: =Tabla2[[#This Row],[TOTAL ARS]]/Tabla2[[#This Row],[TC BNA]] -> 262.47692 | P34: =_xlfn.XLOOKUP(A34,'TC_BNA xlsx'!A:A,'TC_BNA xlsx'!C:C,"No encontrado") -> 1430
A35: 46169 | B35: =MONTH(Tabla2[[#This Row],[Fecha]]) -> 5 | C35: EU-300 | D35: =IFERROR(_xlfn.XLOOKUP(Tabla2[[#This Row],[Artículo]],Tabla1[Artículos],Tabla1[Rubro]),"") -> Servicio | E35: MTZ | F35: 1800 | G35: unidad | H35: 620 | I35: =Tabla2[[#This Row],[Precio Unitario ARS]]/Tabla2[[#This Row],[TC BNA]] -> 0.43356643 | J35: 0 | K35: ARS | M35: =(Tabla2[[#This Row],[Precio Unitario ARS]]-(Tabla2[[#This Row],[Precio Unitario ARS]]*Tabla2[[#This Row],[DTO]]))*Tabla2[[#This Row],[Cantidad]] -> 1116000 | N35: =Tabla2[[#This Row],[Subtotal ARS]]+(Tabla2[[#This Row],[Subtotal ARS]]*Tabla2[[#This Row],[IVA]]) -> 1116000 | O35: =Tabla2[[#This Row],[TOTAL ARS]]/Tabla2[[#This Row],[TC BNA]] -> 780.41958 | P35: =_xlfn.XLOOKUP(A35,'TC_BNA xlsx'!A:A,'TC_BNA xlsx'!C:C,"No encontrado") -> 1430
A36: 46170 | B36: =MONTH(Tabla2[[#This Row],[Fecha]]) -> 5 | C36: Pallets | D36: =IFERROR(_xlfn.XLOOKUP(Tabla2[[#This Row],[Artículo]],Tabla1[Artículos],Tabla1[Rubro]),"") -> Embalaje | E36: Pallets Buenos Aires | F36: 20 | G36: unidad | H36: 6500 | I36: =Tabla2[[#This Row],[Precio Unitario ARS]]/Tabla2[[#This Row],[TC BNA]] -> 4.5454545 | J36: 0 | K36: ARS | L36: 0.21 | M36: =(Tabla2[[#This Row],[Precio Unitario ARS]]-(Tabla2[[#This Row],[Precio Unitario ARS]]*Tabla2[[#This Row],[DTO]]))*Tabla2[[#This Row],[Cantidad]] -> 130000 | N36: =Tabla2[[#This Row],[Subtotal ARS]]+(Tabla2[[#This Row],[Subtotal ARS]]*Tabla2[[#This Row],[IVA]]) -> 157300 | O36: =Tabla2[[#This Row],[TOTAL ARS]]/Tabla2[[#This Row],[TC BNA]] -> 110 | P36: =_xlfn.XLOOKUP(A36,'TC_BNA xlsx'!A:A,'TC_BNA xlsx'!C:C,"No encontrado") -> 1430
A37: 46170 | B37: =MONTH(Tabla2[[#This Row],[Fecha]]) -> 5 | C37: Stretch 10 cm | D37: =IFERROR(_xlfn.XLOOKUP(Tabla2[[#This Row],[Artículo]],Tabla1[Artículos],Tabla1[Rubro]),"") -> Embalaje | E37: Mad Packaging | F37: 187 | G37: kg | H37: 4592 | I37: =Tabla2[[#This Row],[Precio Unitario ARS]]/Tabla2[[#This Row],[TC BNA]] -> 3.2111888 | J37: 0 | K37: ARS | L37: 0.21 | M37: =(Tabla2[[#This Row],[Precio Unitario ARS]]-(Tabla2[[#This Row],[Precio Unitario ARS]]*Tabla2[[#This Row],[DTO]]))*Tabla2[[#This Row],[Cantidad]] -> 858704 | N37: =Tabla2[[#This Row],[Subtotal ARS]]+(Tabla2[[#This Row],[Subtotal ARS]]*Tabla2[[#This Row],[IVA]]) -> 1039031.8 | O37: =Tabla2[[#This Row],[TOTAL ARS]]/Tabla2[[#This Row],[TC BNA]] -> 726.59569 | P37: =_xlfn.XLOOKUP(A37,'TC_BNA xlsx'!A:A,'TC_BNA xlsx'!C:C,"No encontrado") -> 1430 | Q37: Tomaron TC 1435
A38: 46170 | B38: =MONTH(Tabla2[[#This Row],[Fecha]]) -> 5 | C38: Stretch 50 cm C/Mango | D38: =IFERROR(_xlfn.XLOOKUP(Tabla2[[#This Row],[Artículo]],Tabla1[Artículos],Tabla1[Rubro]),"") -> Embalaje | E38: Mad Packaging | F38: 31 | G38: kg | H38: 4547.6 | I38: =Tabla2[[#This Row],[Precio Unitario ARS]]/Tabla2[[#This Row],[TC BNA]] -> 3.1801399 | J38: 0 | K38: ARS | L38: 0.21 | M38: =(Tabla2[[#This Row],[Precio Unitario ARS]]-(Tabla2[[#This Row],[Precio Unitario ARS]]*Tabla2[[#This Row],[DTO]]))*Tabla2[[#This Row],[Cantidad]] -> 140975.6 | N38: =Tabla2[[#This Row],[Subtotal ARS]]+(Tabla2[[#This Row],[Subtotal ARS]]*Tabla2[[#This Row],[IVA]]) -> 170580.48 | O38: =Tabla2[[#This Row],[TOTAL ARS]]/Tabla2[[#This Row],[TC BNA]] -> 119.28705 | P38: =_xlfn.XLOOKUP(A38,'TC_BNA xlsx'!A:A,'TC_BNA xlsx'!C:C,"No encontrado") -> 1430
A39: 46170 | B39: =MONTH(Tabla2[[#This Row],[Fecha]]) -> 5 | C39: Precintos 450 x 10 | D39: =IFERROR(_xlfn.XLOOKUP(Tabla2[[#This Row],[Artículo]],Tabla1[Artículos],Tabla1[Rubro]),"") -> Embalaje | E39: Adamat | F39: 20 | G39: bolsa | H39: 22056.94 | I39: =Tabla2[[#This Row],[Precio Unitario ARS]]/Tabla2[[#This Row],[TC BNA]] -> 15.424434 | J39: 0.4 | K39: ARS | L39: 0.21 | M39: =(Tabla2[[#This Row],[Precio Unitario ARS]]-(Tabla2[[#This Row],[Precio Unitario ARS]]*Tabla2[[#This Row],[DTO]]))*Tabla2[[#This Row],[Cantidad]] -> 264683.28 | N39: =Tabla2[[#This Row],[Subtotal ARS]]+(Tabla2[[#This Row],[Subtotal ARS]]*Tabla2[[#This Row],[IVA]]) -> 320266.77 | O39: =Tabla2[[#This Row],[TOTAL ARS]]/Tabla2[[#This Row],[TC BNA]] -> 223.96278 | P39: =_xlfn.XLOOKUP(A39,'TC_BNA xlsx'!A:A,'TC_BNA xlsx'!C:C,"No encontrado") -> 1430
A40: 46170 | B40: =MONTH(Tabla2[[#This Row],[Fecha]]) -> 5 | C40: Casco S/Arnes Blanco | D40: =IFERROR(_xlfn.XLOOKUP(Tabla2[[#This Row],[Artículo]],Tabla1[Artículos],Tabla1[Rubro]),"") -> EPP | E40: Roguant | F40: 2 | G40: unidad | H40: =2.77*1430 -> 3961.1 | I40: =Tabla2[[#This Row],[Precio Unitario ARS]]/Tabla2[[#This Row],[TC BNA]] -> 2.77 | J40: 0 | K40: ARS | L40: 0.21 | M40: =(Tabla2[[#This Row],[Precio Unitario ARS]]-(Tabla2[[#This Row],[Precio Unitario ARS]]*Tabla2[[#This Row],[DTO]]))*Tabla2[[#This Row],[Cantidad]] -> 7922.2 | N40: =Tabla2[[#This Row],[Subtotal ARS]]+(Tabla2[[#This Row],[Subtotal ARS]]*Tabla2[[#This Row],[IVA]]) -> 9585.862 | O40: =Tabla2[[#This Row],[TOTAL ARS]]/Tabla2[[#This Row],[TC BNA]] -> 6.7034 | P40: =_xlfn.XLOOKUP(A40,'TC_BNA xlsx'!A:A,'TC_BNA xlsx'!C:C,"No encontrado") -> 1430
A41: 46170 | B41: =MONTH(Tabla2[[#This Row],[Fecha]]) -> 5 | C41: Arnes P/Casco | D41: =IFERROR(_xlfn.XLOOKUP(Tabla2[[#This Row],[Artículo]],Tabla1[Artículos],Tabla1[Rubro]),"") -> EPP | E41: Roguant | F41: 2 | G41: unidad | H41: =4.41*1430 -> 6306.3 | I41: =Tabla2[[#This Row],[Precio Unitario ARS]]/Tabla2[[#This Row],[TC BNA]] -> 4.41 | J41: 0 | K41: ARS | L41: 0.21 | M41: =(Tabla2[[#This Row],[Precio Unitario ARS]]-(Tabla2[[#This Row],[Precio Unitario ARS]]*Tabla2[[#This Row],[DTO]]))*Tabla2[[#This Row],[Cantidad]] -> 12612.6 | N41: =Tabla2[[#This Row],[Subtotal ARS]]+(Tabla2[[#This Row],[Subtotal ARS]]*Tabla2[[#This Row],[IVA]]) -> 15261.246 | O41: =Tabla2[[#This Row],[TOTAL ARS]]/Tabla2[[#This Row],[TC BNA]] -> 10.6722 | P41: =_xlfn.XLOOKUP(A41,'TC_BNA xlsx'!A:A,'TC_BNA xlsx'!C:C,"No encontrado") -> 1430
A42: 46171 | B42: =MONTH(Tabla2[[#This Row],[Fecha]]) -> 5 | C42: Tubo de Gas (Atal) | D42: =IFERROR(_xlfn.XLOOKUP(Tabla2[[#This Row],[Artículo]],Tabla1[Artículos],Tabla1[Rubro]),"") -> Soldadura | E42: Roberto Gustavo Q. | F42: 10 | G42: m3 | H42: 17500 | I42: =Tabla2[[#This Row],[Precio Unitario ARS]]/Tabla2[[#This Row],[TC BNA]] -> 12.237762 | J42: 0 | K42: ARS | M42: =(Tabla2[[#This Row],[Precio Unitario ARS]]-(Tabla2[[#This Row],[Precio Unitario ARS]]*Tabla2[[#This Row],[DTO]]))*Tabla2[[#This Row],[Cantidad]] -> 175000 | N42: =Tabla2[[#This Row],[Subtotal ARS]]+(Tabla2[[#This Row],[Subtotal ARS]]*Tabla2[[#This Row],[IVA]]) -> 175000 | O42: =Tabla2[[#This Row],[TOTAL ARS]]/Tabla2[[#This Row],[TC BNA]] -> 122.37762 | P42: =_xlfn.XLOOKUP(A42,'TC_BNA xlsx'!A:A,'TC_BNA xlsx'!C:C,"No encontrado") -> 1430
A43: 46171 | B43: =MONTH(Tabla2[[#This Row],[Fecha]]) -> 5 | C43: Alambre de Soldadura 0,9 mm | D43: =IFERROR(_xlfn.XLOOKUP(Tabla2[[#This Row],[Artículo]],Tabla1[Artículos],Tabla1[Rubro]),"") -> Soldadura | E43: Roberto Gustavo Q. | F43: 2 | G43: rollo | H43: 80000 | I43: =Tabla2[[#This Row],[Precio Unitario ARS]]/Tabla2[[#This Row],[TC BNA]] -> 55.944056 | J43: 0 | K43: ARS | M43: =(Tabla2[[#This Row],[Precio Unitario ARS]]-(Tabla2[[#This Row],[Precio Unitario ARS]]*Tabla2[[#This Row],[DTO]]))*Tabla2[[#This Row],[Cantidad]] -> 160000 | N43: =Tabla2[[#This Row],[Subtotal ARS]]+(Tabla2[[#This Row],[Subtotal ARS]]*Tabla2[[#This Row],[IVA]]) -> 160000 | O43: =Tabla2[[#This Row],[TOTAL ARS]]/Tabla2[[#This Row],[TC BNA]] -> 111.88811 | P43: =_xlfn.XLOOKUP(A43,'TC_BNA xlsx'!A:A,'TC_BNA xlsx'!C:C,"No encontrado") -> 1430
A44: 46174 | B44: =MONTH(Tabla2[[#This Row],[Fecha]]) -> 6 | C44: EU-250 | D44: =IFERROR(_xlfn.XLOOKUP(Tabla2[[#This Row],[Artículo]],Tabla1[Artículos],Tabla1[Rubro]),"") -> Servicio | E44: MTZ | F44: 726 | G44: unidad | H44: 517 | I44: =Tabla2[[#This Row],[Precio Unitario ARS]]/Tabla2[[#This Row],[TC BNA]] -> 0.35778547 | J44: 0 | K44: ARS | M44: =(Tabla2[[#This Row],[Precio Unitario ARS]]-(Tabla2[[#This Row],[Precio Unitario ARS]]*Tabla2[[#This Row],[DTO]]))*Tabla2[[#This Row],[Cantidad]] -> 375342 | N44: =Tabla2[[#This Row],[Subtotal ARS]]+(Tabla2[[#This Row],[Subtotal ARS]]*Tabla2[[#This Row],[IVA]]) -> 375342 | O44: =Tabla2[[#This Row],[TOTAL ARS]]/Tabla2[[#This Row],[TC BNA]] -> 259.75225 | P44: =_xlfn.XLOOKUP(A44,'TC_BNA xlsx'!A:A,'TC_BNA xlsx'!C:C,"No encontrado") -> 1445 | Q44: NC
A45: 46175 | B45: =MONTH(Tabla2[[#This Row],[Fecha]]) -> 6 | C45: Tubo de Oxígeno | D45: =IFERROR(_xlfn.XLOOKUP(Tabla2[[#This Row],[Artículo]],Tabla1[Artículos],Tabla1[Rubro]),"") -> Soldadura | E45: Roberto Gustavo Q. | F45: 30 | G45: m3 | H45: 4500 | I45: =Tabla2[[#This Row],[Precio Unitario ARS]]/Tabla2[[#This Row],[TC BNA]] -> 3.1034483 | J45: 0 | K45: ARS | M45: =(Tabla2[[#This Row],[Precio Unitario ARS]]-(Tabla2[[#This Row],[Precio Unitario ARS]]*Tabla2[[#This Row],[DTO]]))*Tabla2[[#This Row],[Cantidad]] -> 135000 | N45: =Tabla2[[#This Row],[Subtotal ARS]]+(Tabla2[[#This Row],[Subtotal ARS]]*Tabla2[[#This Row],[IVA]]) -> 135000 | O45: =Tabla2[[#This Row],[TOTAL ARS]]/Tabla2[[#This Row],[TC BNA]] -> 93.103448 | P45: =_xlfn.XLOOKUP(A45,'TC_BNA xlsx'!A:A,'TC_BNA xlsx'!C:C,"No encontrado") -> 1450
A46: 46175 | B46: =MONTH(Tabla2[[#This Row],[Fecha]]) -> 6 | C46: Guantes Dyne 5 | D46: =IFERROR(_xlfn.XLOOKUP(Tabla2[[#This Row],[Artículo]],Tabla1[Artículos],Tabla1[Rubro]),"") -> EPP | E46: Roguant | F46: 24 | G46: par | H46: =2.9*1430 -> 4147 | I46: =Tabla2[[#This Row],[Precio Unitario ARS]]/Tabla2[[#This Row],[TC BNA]] -> 2.86 | J46: 0 | K46: ARS | L46: 0.21 | M46: =(Tabla2[[#This Row],[Precio Unitario ARS]]-(Tabla2[[#This Row],[Precio Unitario ARS]]*Tabla2[[#This Row],[DTO]]))*Tabla2[[#This Row],[Cantidad]] -> 99528 | N46: =Tabla2[[#This Row],[Subtotal ARS]]+(Tabla2[[#This Row],[Subtotal ARS]]*Tabla2[[#This Row],[IVA]]) -> 120428.88 | O46: =Tabla2[[#This Row],[TOTAL ARS]]/Tabla2[[#This Row],[TC BNA]] -> 83.0544 | P46: =_xlfn.XLOOKUP(A46,'TC_BNA xlsx'!A:A,'TC_BNA xlsx'!C:C,"No encontrado") -> 1450
A47: 46176 | B47: =MONTH(Tabla2[[#This Row],[Fecha]]) -> 6 | C47: Guantes Poli (Tactil) 8# | D47: =IFERROR(_xlfn.XLOOKUP(Tabla2[[#This Row],[Artículo]],Tabla1[Artículos],Tabla1[Rubro]),"") -> EPP | E47: Tech Safe | F47: 24 | G47: par | H47: 637 | I47: =Tabla2[[#This Row],[Precio Unitario ARS]]/Tabla2[[#This Row],[TC BNA]] -> 0.43630137 | J47: 0 | K47: ARS | L47: 0.21 | M47: =(Tabla2[[#This Row],[Precio Unitario ARS]]-(Tabla2[[#This Row],[Precio Unitario ARS]]*Tabla2[[#This Row],[DTO]]))*Tabla2[[#This Row],[Cantidad]] -> 15288 | N47: =Tabla2[[#This Row],[Subtotal ARS]]+(Tabla2[[#This Row],[Subtotal ARS]]*Tabla2[[#This Row],[IVA]]) -> 18498.48 | O47: =Tabla2[[#This Row],[TOTAL ARS]]/Tabla2[[#This Row],[TC BNA]] -> 12.670192 | P47: =_xlfn.XLOOKUP(A47,'TC_BNA xlsx'!A:A,'TC_BNA xlsx'!C:C,"No encontrado") -> 1460
A48: 46176 | B48: =MONTH(Tabla2[[#This Row],[Fecha]]) -> 6 | C48: Guantes Poli (Tactil) 10# | D48: =IFERROR(_xlfn.XLOOKUP(Tabla2[[#This Row],[Artículo]],Tabla1[Artículos],Tabla1[Rubro]),"") -> EPP | E48: Tech Safe | F48: 24 | G48: par | H48: 637 | I48: =Tabla2[[#This Row],[Precio Unitario ARS]]/Tabla2[[#This Row],[TC BNA]] -> 0.43630137 | J48: 0 | K48: ARS | L48: 0.21 | M48: =(Tabla2[[#This Row],[Precio Unitario ARS]]-(Tabla2[[#This Row],[Precio Unitario ARS]]*Tabla2[[#This Row],[DTO]]))*Tabla2[[#This Row],[Cantidad]] -> 15288 | N48: =Tabla2[[#This Row],[Subtotal ARS]]+(Tabla2[[#This Row],[Subtotal ARS]]*Tabla2[[#This Row],[IVA]]) -> 18498.48 | O48: =Tabla2[[#This Row],[TOTAL ARS]]/Tabla2[[#This Row],[TC BNA]] -> 12.670192 | P48: =_xlfn.XLOOKUP(A48,'TC_BNA xlsx'!A:A,'TC_BNA xlsx'!C:C,"No encontrado") -> 1460
A49: 46176 | B49: =MONTH(Tabla2[[#This Row],[Fecha]]) -> 6 | C49: Tacos 1 1/2" x 4" x 1100mm | D49: =IFERROR(_xlfn.XLOOKUP(Tabla2[[#This Row],[Artículo]],Tabla1[Artículos],Tabla1[Rubro]),"") -> Embalaje | E49: Aserradero Alonso | F49: 400 | G49: unidad | H49: 1659.6636 | I49: =Tabla2[[#This Row],[Precio Unitario ARS]]/Tabla2[[#This Row],[TC BNA]] -> 1.1367559 | J49: 0.1 | K49: ARS | L49: 0.21 | M49: =(Tabla2[[#This Row],[Precio Unitario ARS]]-(Tabla2[[#This Row],[Precio Unitario ARS]]*Tabla2[[#This Row],[DTO]]))*Tabla2[[#This Row],[Cantidad]] -> 597478.9 | N49: =Tabla2[[#This Row],[Subtotal ARS]]+(Tabla2[[#This Row],[Subtotal ARS]]*Tabla2[[#This Row],[IVA]]) -> 722949.46 | O49: =Tabla2[[#This Row],[TOTAL ARS]]/Tabla2[[#This Row],[TC BNA]] -> 495.17087 | P49: =_xlfn.XLOOKUP(A49,'TC_BNA xlsx'!A:A,'TC_BNA xlsx'!C:C,"No encontrado") -> 1460 | Q49: Para Guillón
A50: 46176 | B50: =MONTH(Tabla2[[#This Row],[Fecha]]) -> 6 | C50: Sierra | D50: =IFERROR(_xlfn.XLOOKUP(Tabla2[[#This Row],[Artículo]],Tabla1[Artículos],Tabla1[Rubro]),"") -> Herramientas | E50: Alpamet | F50: 2 | G50: unidad | H50: 28000 | I50: =Tabla2[[#This Row],[Precio Unitario ARS]]/Tabla2[[#This Row],[TC BNA]] -> 19.178082 | J50: 0.1 | K50: ARS | L50: 0.21 | M50: =(Tabla2[[#This Row],[Precio Unitario ARS]]-(Tabla2[[#This Row],[Precio Unitario ARS]]*Tabla2[[#This Row],[DTO]]))*Tabla2[[#This Row],[Cantidad]] -> 50400 | N50: =Tabla2[[#This Row],[Subtotal ARS]]+(Tabla2[[#This Row],[Subtotal ARS]]*Tabla2[[#This Row],[IVA]]) -> 60984 | O50: =Tabla2[[#This Row],[TOTAL ARS]]/Tabla2[[#This Row],[TC BNA]] -> 41.769863 | P50: =_xlfn.XLOOKUP(A50,'TC_BNA xlsx'!A:A,'TC_BNA xlsx'!C:C,"No encontrado") -> 1460
A51: 46176 | B51: =MONTH(Tabla2[[#This Row],[Fecha]]) -> 6 | C51: Hoja de Sierra P/Serrucho L2450mm | D51: =IFERROR(_xlfn.XLOOKUP(Tabla2[[#This Row],[Artículo]],Tabla1[Artículos],Tabla1[Rubro]),"") -> Herramientas | E51: Alpamet | F51: 1 | G51: unidad | H51: 59500 | I51: =Tabla2[[#This Row],[Precio Unitario ARS]]/Tabla2[[#This Row],[TC BNA]] -> 40.753425 | J51: 0 | K51: ARS | L51: 0.21 | M51: =(Tabla2[[#This Row],[Precio Unitario ARS]]-(Tabla2[[#This Row],[Precio Unitario ARS]]*Tabla2[[#This Row],[DTO]]))*Tabla2[[#This Row],[Cantidad]] -> 59500 | N51: =Tabla2[[#This Row],[Subtotal ARS]]+(Tabla2[[#This Row],[Subtotal ARS]]*Tabla2[[#This Row],[IVA]]) -> 71995 | O51: =Tabla2[[#This Row],[TOTAL ARS]]/Tabla2[[#This Row],[TC BNA]] -> 49.311644 | P51: =_xlfn.XLOOKUP(A51,'TC_BNA xlsx'!A:A,'TC_BNA xlsx'!C:C,"No encontrado") -> 1460
A52: 46178 | B52: =MONTH(Tabla2[[#This Row],[Fecha]]) -> 6 | C52: Cadena Calibrada | D52: =IFERROR(_xlfn.XLOOKUP(Tabla2[[#This Row],[Artículo]],Tabla1[Artículos],Tabla1[Rubro]),"") -> Materia Prima | E52: Metrochain | F52: 400 | G52: m | H52: 2170 | I52: =Tabla2[[#This Row],[Precio Unitario ARS]]/Tabla2[[#This Row],[TC BNA]] -> 1.4863014 | J52: 0 | K52: ARS | L52: 0.21 | M52: =(Tabla2[[#This Row],[Precio Unitario ARS]]-(Tabla2[[#This Row],[Precio Unitario ARS]]*Tabla2[[#This Row],[DTO]]))*Tabla2[[#This Row],[Cantidad]] -> 868000 | N52: =Tabla2[[#This Row],[Subtotal ARS]]+(Tabla2[[#This Row],[Subtotal ARS]]*Tabla2[[#This Row],[IVA]]) -> 1050280 | O52: =Tabla2[[#This Row],[TOTAL ARS]]/Tabla2[[#This Row],[TC BNA]] -> 719.36986 | P52: =_xlfn.XLOOKUP(A52,'TC_BNA xlsx'!A:A,'TC_BNA xlsx'!C:C,"No encontrado") -> 1460
A53: 46178 | B53: =MONTH(Tabla2[[#This Row],[Fecha]]) -> 6 | C53: Tacos 1 1/2" x 3" x 1130mm | D53: =IFERROR(_xlfn.XLOOKUP(Tabla2[[#This Row],[Artículo]],Tabla1[Artículos],Tabla1[Rubro]),"") -> Embalaje | E53: Aserradero Alonso | F53: 300 | G53: unidad | H53: 1151.7875 | I53: =Tabla2[[#This Row],[Precio Unitario ARS]]/Tabla2[[#This Row],[TC BNA]] -> 0.78889555 | J53: 0.1 | K53: ARS | L53: 0.21 | M53: =(Tabla2[[#This Row],[Precio Unitario ARS]]-(Tabla2[[#This Row],[Precio Unitario ARS]]*Tabla2[[#This Row],[DTO]]))*Tabla2[[#This Row],[Cantidad]] -> 310982.62 | N53: =Tabla2[[#This Row],[Subtotal ARS]]+(Tabla2[[#This Row],[Subtotal ARS]]*Tabla2[[#This Row],[IVA]]) -> 376288.98 | O53: =Tabla2[[#This Row],[TOTAL ARS]]/Tabla2[[#This Row],[TC BNA]] -> 257.73218 | P53: =_xlfn.XLOOKUP(A53,'TC_BNA xlsx'!A:A,'TC_BNA xlsx'!C:C,"No encontrado") -> 1460
A54: 46178 | B54: =MONTH(Tabla2[[#This Row],[Fecha]]) -> 6 | C54: Tacos 2" x 2 1/2" x 640mm | D54: =IFERROR(_xlfn.XLOOKUP(Tabla2[[#This Row],[Artículo]],Tabla1[Artículos],Tabla1[Rubro]),"") -> Embalaje | E54: Aserradero Alonso | F54: 200 | G54: unidad | H54: 814.519 | I54: =Tabla2[[#This Row],[Precio Unitario ARS]]/Tabla2[[#This Row],[TC BNA]] -> 0.55788973 | J54: 0.1 | K54: ARS | L54: 0.21 | M54: =(Tabla2[[#This Row],[Precio Unitario ARS]]-(Tabla2[[#This Row],[Precio Unitario ARS]]*Tabla2[[#This Row],[DTO]]))*Tabla2[[#This Row],[Cantidad]] -> 146613.42 | N54: =Tabla2[[#This Row],[Subtotal ARS]]+(Tabla2[[#This Row],[Subtotal ARS]]*Tabla2[[#This Row],[IVA]]) -> 177402.24 | O54: =Tabla2[[#This Row],[TOTAL ARS]]/Tabla2[[#This Row],[TC BNA]] -> 121.50838 | P54: =_xlfn.XLOOKUP(A54,'TC_BNA xlsx'!A:A,'TC_BNA xlsx'!C:C,"No encontrado") -> 1460
A55: 46178 | B55: =MONTH(Tabla2[[#This Row],[Fecha]]) -> 6 | C55: Varilla Roscada Zinc. 1/4" | D55: =IFERROR(_xlfn.XLOOKUP(Tabla2[[#This Row],[Artículo]],Tabla1[Artículos],Tabla1[Rubro]),"") -> Reventa | E55: Dusvar | F55: 1000 | G55: unidad | H55: 450 | I55: =Tabla2[[#This Row],[Precio Unitario ARS]]/Tabla2[[#This Row],[TC BNA]] -> 0.30821918 | J55: 0 | K55: ARS | L55: 0.21 | M55: =(Tabla2[[#This Row],[Precio Unitario ARS]]-(Tabla2[[#This Row],[Precio Unitario ARS]]*Tabla2[[#This Row],[DTO]]))*Tabla2[[#This Row],[Cantidad]] -> 450000 | N55: =Tabla2[[#This Row],[Subtotal ARS]]+(Tabla2[[#This Row],[Subtotal ARS]]*Tabla2[[#This Row],[IVA]]) -> 544500 | O55: =Tabla2[[#This Row],[TOTAL ARS]]/Tabla2[[#This Row],[TC BNA]] -> 372.94521 | P55: =_xlfn.XLOOKUP(A55,'TC_BNA xlsx'!A:A,'TC_BNA xlsx'!C:C,"No encontrado") -> 1460
A56: 46178 | B56: =MONTH(Tabla2[[#This Row],[Fecha]]) -> 6 | C56: Varilla Roscada Zinc. 5/16" | D56: =IFERROR(_xlfn.XLOOKUP(Tabla2[[#This Row],[Artículo]],Tabla1[Artículos],Tabla1[Rubro]),"") -> Reventa | E56: Dusvar | F56: 1500 | G56: unidad | H56: 717 | I56: =Tabla2[[#This Row],[Precio Unitario ARS]]/Tabla2[[#This Row],[TC BNA]] -> 0.49109589 | J56: 0 | K56: ARS | L56: 0.21 | M56: =(Tabla2[[#This Row],[Precio Unitario ARS]]-(Tabla2[[#This Row],[Precio Unitario ARS]]*Tabla2[[#This Row],[DTO]]))*Tabla2[[#This Row],[Cantidad]] -> 1075500 | N56: =Tabla2[[#This Row],[Subtotal ARS]]+(Tabla2[[#This Row],[Subtotal ARS]]*Tabla2[[#This Row],[IVA]]) -> 1301355 | O56: =Tabla2[[#This Row],[TOTAL ARS]]/Tabla2[[#This Row],[TC BNA]] -> 891.33904 | P56: =_xlfn.XLOOKUP(A56,'TC_BNA xlsx'!A:A,'TC_BNA xlsx'!C:C,"No encontrado") -> 1460
A57: 46181 | B57: =MONTH(Tabla2[[#This Row],[Fecha]]) -> 6 | C57: Lente máscara de soldar | D57: =IFERROR(_xlfn.XLOOKUP(Tabla2[[#This Row],[Artículo]],Tabla1[Artículos],Tabla1[Rubro]),"") -> Soldadura | E57: Diprov | F57: 7 | G57: unidad | H57: 3212 | I57: =Tabla2[[#This Row],[Precio Unitario ARS]]/Tabla2[[#This Row],[TC BNA]] -> 2.1924915 | J57: 0 | K57: ARS | L57: 0.21 | M57: =(Tabla2[[#This Row],[Precio Unitario ARS]]-(Tabla2[[#This Row],[Precio Unitario ARS]]*Tabla2[[#This Row],[DTO]]))*Tabla2[[#This Row],[Cantidad]] -> 22484 | N57: =Tabla2[[#This Row],[Subtotal ARS]]+(Tabla2[[#This Row],[Subtotal ARS]]*Tabla2[[#This Row],[IVA]]) -> 27205.64 | O57: =Tabla2[[#This Row],[TOTAL ARS]]/Tabla2[[#This Row],[TC BNA]] -> 18.570403 | P57: =_xlfn.XLOOKUP(A57,'TC_BNA xlsx'!A:A,'TC_BNA xlsx'!C:C,"No encontrado") -> 1465
A58: 46181 | B58: =MONTH(Tabla2[[#This Row],[Fecha]]) -> 6 | C58: Tuerca Flange Zinc. 1/4" | D58: =IFERROR(_xlfn.XLOOKUP(Tabla2[[#This Row],[Artículo]],Tabla1[Artículos],Tabla1[Rubro]),"") -> Reventa | E58: Distribuidora Tubulón | F58: 100800 | G58: unidad | H58: 19.37902 | I58: =Tabla2[[#This Row],[Precio Unitario ARS]]/Tabla2[[#This Row],[TC BNA]] -> 0.013228 | J58: 0.1538 | K58: ARS | L58: 0.21 | M58: =(Tabla2[[#This Row],[Precio Unitario ARS]]-(Tabla2[[#This Row],[Precio Unitario ARS]]*Tabla2[[#This Row],[DTO]]))*Tabla2[[#This Row],[Cantidad]] -> 1652971.5 | N58: =Tabla2[[#This Row],[Subtotal ARS]]+(Tabla2[[#This Row],[Subtotal ARS]]*Tabla2[[#This Row],[IVA]]) -> 2000095.5 | O58: =Tabla2[[#This Row],[TOTAL ARS]]/Tabla2[[#This Row],[TC BNA]] -> 1365.2529 | P58: =_xlfn.XLOOKUP(A58,'TC_BNA xlsx'!A:A,'TC_BNA xlsx'!C:C,"No encontrado") -> 1465
A59: 46182 | B59: =MONTH(Tabla2[[#This Row],[Fecha]]) -> 6 | C59: Precintos 450 x 10 | D59: =IFERROR(_xlfn.XLOOKUP(Tabla2[[#This Row],[Artículo]],Tabla1[Artículos],Tabla1[Rubro]),"") -> Embalaje | E59: Adamat | F59: 12 | G59: bolsa | H59: 22056.94 | I59: =Tabla2[[#This Row],[Precio Unitario ARS]]/Tabla2[[#This Row],[TC BNA]] -> 15.107493 | J59: 0.4 | K59: ARS | L59: 0.21 | M59: =(Tabla2[[#This Row],[Precio Unitario ARS]]-(Tabla2[[#This Row],[Precio Unitario ARS]]*Tabla2[[#This Row],[DTO]]))*Tabla2[[#This Row],[Cantidad]] -> 158809.97 | N59: =Tabla2[[#This Row],[Subtotal ARS]]+(Tabla2[[#This Row],[Subtotal ARS]]*Tabla2[[#This Row],[IVA]]) -> 192160.06 | O59: =Tabla2[[#This Row],[TOTAL ARS]]/Tabla2[[#This Row],[TC BNA]] -> 131.61648 | P59: =_xlfn.XLOOKUP(A59,'TC_BNA xlsx'!A:A,'TC_BNA xlsx'!C:C,"No encontrado") -> 1460
A60: 46182 | B60: =MONTH(Tabla2[[#This Row],[Fecha]]) -> 6 | C60: Precintos 500 x 10 | D60: =IFERROR(_xlfn.XLOOKUP(Tabla2[[#This Row],[Artículo]],Tabla1[Artículos],Tabla1[Rubro]),"") -> Embalaje | E60: Adamat | F60: 5 | G60: bolsa | H60: 27888.08 | I60: =Tabla2[[#This Row],[Precio Unitario ARS]]/Tabla2[[#This Row],[TC BNA]] -> 19.101425 | J60: 0.4 | K60: ARS | L60: 0.21 | M60: =(Tabla2[[#This Row],[Precio Unitario ARS]]-(Tabla2[[#This Row],[Precio Unitario ARS]]*Tabla2[[#This Row],[DTO]]))*Tabla2[[#This Row],[Cantidad]] -> 83664.24 | N60: =Tabla2[[#This Row],[Subtotal ARS]]+(Tabla2[[#This Row],[Subtotal ARS]]*Tabla2[[#This Row],[IVA]]) -> 101233.73 | O60: =Tabla2[[#This Row],[TOTAL ARS]]/Tabla2[[#This Row],[TC BNA]] -> 69.338172 | P60: =_xlfn.XLOOKUP(A60,'TC_BNA xlsx'!A:A,'TC_BNA xlsx'!C:C,"No encontrado") -> 1460
A61: 46182 | B61: =MONTH(Tabla2[[#This Row],[Fecha]]) -> 6 | C61: Precintos 450 x 10 | D61: =IFERROR(_xlfn.XLOOKUP(Tabla2[[#This Row],[Artículo]],Tabla1[Artículos],Tabla1[Rubro]),"") -> Embalaje | E61: Adamat | F61: 8 | G61: bolsa | H61: 22056.94 | I61: =Tabla2[[#This Row],[Precio Unitario ARS]]/Tabla2[[#This Row],[TC BNA]] -> 15.107493 | J61: 0.4 | K61: ARS | L61: 0.21 | M61: =(Tabla2[[#This Row],[Precio Unitario ARS]]-(Tabla2[[#This Row],[Precio Unitario ARS]]*Tabla2[[#This Row],[DTO]]))*Tabla2[[#This Row],[Cantidad]] -> 105873.31 | N61: =Tabla2[[#This Row],[Subtotal ARS]]+(Tabla2[[#This Row],[Subtotal ARS]]*Tabla2[[#This Row],[IVA]]) -> 128106.71 | O61: =Tabla2[[#This Row],[TOTAL ARS]]/Tabla2[[#This Row],[TC BNA]] -> 87.74432 | P61: =_xlfn.XLOOKUP(A61,'TC_BNA xlsx'!A:A,'TC_BNA xlsx'!C:C,"No encontrado") -> 1460
... A72: 46184 | B72: =MONTH(Tabla2[[#This Row],[Fecha]]) -> 6 | C72: Bolsas Tubos x 100 mic | D72: =IFERROR(_xlfn.XLOOKUP(Tabla2[[#This Row],[Artículo]],Tabla1[Artículos],Tabla1[Rubro]),"") -> Embalaje | E72: Greenfilm | F72: 2 | G72: rollo | H72: 256000 | I72: =Tabla2[[#This Row],[Precio Unitario ARS]]/Tabla2[[#This Row],[TC BNA]] -> 176.55172 | J72: 0 | K72: ARS | L72: 0.21 | M72: =(Tabla2[[#This Row],[Precio Unitario ARS]]-(Tabla2[[#This Row],[Precio Unitario ARS]]*Tabla2[[#This Row],[DTO]]))*Tabla2[[#This Row],[Cantidad]] -> 512000 | N72: =Tabla2[[#This Row],[Subtotal ARS]]+(Tabla2[[#This Row],[Subtotal ARS]]*Tabla2[[#This Row],[IVA]]) -> 619520 | O72: =Tabla2[[#This Row],[TOTAL ARS]]/Tabla2[[#This Row],[TC BNA]] -> 427.25517 | P72: =_xlfn.XLOOKUP(A72,'TC_BNA xlsx'!A:A,'TC_BNA xlsx'!C:C,"No encontrado") -> 1450
A73: 46184 | B73: =MONTH(Tabla2[[#This Row],[Fecha]]) -> 6 | C73: Guantes Dyne 5 | D73: =IFERROR(_xlfn.XLOOKUP(Tabla2[[#This Row],[Artículo]],Tabla1[Artículos],Tabla1[Rubro]),"") -> EPP | E73: Roguant | F73: 24 | G73: par | H73: =2.9*1455 -> 4219.5 | I73: =Tabla2[[#This Row],[Precio Unitario ARS]]/Tabla2[[#This Row],[TC BNA]] -> 2.91 | J73: 0 | K73: ARS | L73: 0.21 | M73: =(Tabla2[[#This Row],[Precio Unitario ARS]]-(Tabla2[[#This Row],[Precio Unitario ARS]]*Tabla2[[#This Row],[DTO]]))*Tabla2[[#This Row],[Cantidad]] -> 101268 | N73: =Tabla2[[#This Row],[Subtotal ARS]]+(Tabla2[[#This Row],[Subtotal ARS]]*Tabla2[[#This Row],[IVA]]) -> 122534.28 | O73: =Tabla2[[#This Row],[TOTAL ARS]]/Tabla2[[#This Row],[TC BNA]] -> 84.5064 | P73: =_xlfn.XLOOKUP(A73,'TC_BNA xlsx'!A:A,'TC_BNA xlsx'!C:C,"No encontrado") -> 1450 | Q73: Tomaron TC 1455
A74: 46184 | B74: =MONTH(Tabla2[[#This Row],[Fecha]]) -> 6 | C74: GALVA 1220 X 2440 3,2 | D74: =IFERROR(_xlfn.XLOOKUP(Tabla2[[#This Row],[Artículo]],Tabla1[Artículos],Tabla1[Rubro]),"") -> Materia Prima | E74: Pacheco Chapas | F74: 5164 | G74: kg | H74: 1882.77 | I74: =Tabla2[[#This Row],[Precio Unitario ARS]]/Tabla2[[#This Row],[TC BNA]] -> 1.2984621 | J74: 0 | K74: ARS | L74: 0.21 | M74: =(Tabla2[[#This Row],[Precio Unitario ARS]]-(Tabla2[[#This Row],[Precio Unitario ARS]]*Tabla2[[#This Row],[DTO]]))*Tabla2[[#This Row],[Cantidad]] -> 9722624.3 | N74: =Tabla2[[#This Row],[Subtotal ARS]]+(Tabla2[[#This Row],[Subtotal ARS]]*Tabla2[[#This Row],[IVA]]) -> 11764375 | O74: =Tabla2[[#This Row],[TOTAL ARS]]/Tabla2[[#This Row],[TC BNA]] -> 8113.3623 | P74: =_xlfn.XLOOKUP(A74,'TC_BNA xlsx'!A:A,'TC_BNA xlsx'!C:C,"No encontrado") -> 1450 | Q74: Tomaron TC 1455
A75: 46184 | B75: =MONTH(Tabla2[[#This Row],[Fecha]]) -> 6 | C75: Varilla Roscada Zinc. 1/4" | D75: =IFERROR(_xlfn.XLOOKUP(Tabla2[[#This Row],[Artículo]],Tabla1[Artículos],Tabla1[Rubro]),"") -> Reventa | E75: Dusvar | F75: 1000 | G75: unidad | H75: 450 | I75: =Tabla2[[#This Row],[Precio Unitario ARS]]/Tabla2[[#This Row],[TC BNA]] -> 0.31034483 | J75: 0 | K75: ARS | L75: 0.21 | M75: =(Tabla2[[#This Row],[Precio Unitario ARS]]-(Tabla2[[#This Row],[Precio Unitario ARS]]*Tabla2[[#This Row],[DTO]]))*Tabla2[[#This Row],[Cantidad]] -> 450000 | N75: =Tabla2[[#This Row],[Subtotal ARS]]+(Tabla2[[#This Row],[Subtotal ARS]]*Tabla2[[#This Row],[IVA]]) -> 544500 | O75: =Tabla2[[#This Row],[TOTAL ARS]]/Tabla2[[#This Row],[TC BNA]] -> 375.51724 | P75: =_xlfn.XLOOKUP(A75,'TC_BNA xlsx'!A:A,'TC_BNA xlsx'!C:C,"No encontrado") -> 1450
A76: 46184 | B76: =MONTH(Tabla2[[#This Row],[Fecha]]) -> 6 | C76: Varilla Roscada Zinc. 3/8" | D76: =IFERROR(_xlfn.XLOOKUP(Tabla2[[#This Row],[Artículo]],Tabla1[Artículos],Tabla1[Rubro]),"") -> Reventa | E76: Dusvar | F76: 1500 | G76: unidad | H76: 998 | I76: =Tabla2[[#This Row],[Precio Unitario ARS]]/Tabla2[[#This Row],[TC BNA]] -> 0.68827586 | J76: 0 | K76: ARS | L76: 0.21 | M76: =(Tabla2[[#This Row],[Precio Unitario ARS]]-(Tabla2[[#This Row],[Precio Unitario ARS]]*Tabla2[[#This Row],[DTO]]))*Tabla2[[#This Row],[Cantidad]] -> 1497000 | N76: =Tabla2[[#This Row],[Subtotal ARS]]+(Tabla2[[#This Row],[Subtotal ARS]]*Tabla2[[#This Row],[IVA]]) -> 1811370 | O76: =Tabla2[[#This Row],[TOTAL ARS]]/Tabla2[[#This Row],[TC BNA]] -> 1249.2207 | P76: =_xlfn.XLOOKUP(A76,'TC_BNA xlsx'!A:A,'TC_BNA xlsx'!C:C,"No encontrado") -> 1450
A77: 46184 | B77: =MONTH(Tabla2[[#This Row],[Fecha]]) -> 6 | C77: Varilla Roscada Zinc. 5/16" | D77: =IFERROR(_xlfn.XLOOKUP(Tabla2[[#This Row],[Artículo]],Tabla1[Artículos],Tabla1[Rubro]),"") -> Reventa | E77: Dusvar | F77: 750 | G77: unidad | H77: 717 | I77: =Tabla2[[#This Row],[Precio Unitario ARS]]/Tabla2[[#This Row],[TC BNA]] -> 0.49448276 | J77: 0 | K77: ARS | L77: 0.21 | M77: =(Tabla2[[#This Row],[Precio Unitario ARS]]-(Tabla2[[#This Row],[Precio Unitario ARS]]*Tabla2[[#This Row],[DTO]]))*Tabla2[[#This Row],[Cantidad]] -> 537750 | N77: =Tabla2[[#This Row],[Subtotal ARS]]+(Tabla2[[#This Row],[Subtotal ARS]]*Tabla2[[#This Row],[IVA]]) -> 650677.5 | O77: =Tabla2[[#This Row],[TOTAL ARS]]/Tabla2[[#This Row],[TC BNA]] -> 448.7431 | P77: =_xlfn.XLOOKUP(A77,'TC_BNA xlsx'!A:A,'TC_BNA xlsx'!C:C,"No encontrado") -> 1450
A78: 46184 | B78: =MONTH(Tabla2[[#This Row],[Fecha]]) -> 6 | C78: ANGULO 1" 1/4 X 1/8 x kg | D78: =IFERROR(_xlfn.XLOOKUP(Tabla2[[#This Row],[Artículo]],Tabla1[Artículos],Tabla1[Rubro]),"") -> Materia Prima | E78: Casanova | F78: 5 | G78: kg | H78: 1718.69 | I78: =Tabla2[[#This Row],[Precio Unitario ARS]]/Tabla2[[#This Row],[TC BNA]] -> 1.1853034 | J78: 0 | K78: ARS | L78: 0.21 | M78: =(Tabla2[[#This Row],[Precio Unitario ARS]]-(Tabla2[[#This Row],[Precio Unitario ARS]]*Tabla2[[#This Row],[DTO]]))*Tabla2[[#This Row],[Cantidad]] -> 8593.45 | N78: =Tabla2[[#This Row],[Subtotal ARS]]+(Tabla2[[#This Row],[Subtotal ARS]]*Tabla2[[#This Row],[IVA]]) -> 10398.075 | O78: =Tabla2[[#This Row],[TOTAL ARS]]/Tabla2[[#This Row],[TC BNA]] -> 7.1710859 | P78: =_xlfn.XLOOKUP(A78,'TC_BNA xlsx'!A:A,'TC_BNA xlsx'!C:C,"No encontrado") -> 1450
A79: 46184 | B79: =MONTH(Tabla2[[#This Row],[Fecha]]) -> 6 | C79: PLANCHUELA 1 X 1/2 X 3/16 | D79: =IFERROR(_xlfn.XLOOKUP(Tabla2[[#This Row],[Artículo]],Tabla1[Artículos],Tabla1[Rubro]),"") -> Materia Prima | E79: Casanova | F79: 3 | G79: kg | H79: 1748.9 | I79: =Tabla2[[#This Row],[Precio Unitario ARS]]/Tabla2[[#This Row],[TC BNA]] -> 1.2061379 | J79: 0 | K79: ARS | L79: 0.21 | M79: =(Tabla2[[#This Row],[Precio Unitario ARS]]-(Tabla2[[#This Row],[Precio Unitario ARS]]*Tabla2[[#This Row],[DTO]]))*Tabla2[[#This Row],[Cantidad]] -> 5246.7 | N79: =Tabla2[[#This Row],[Subtotal ARS]]+(Tabla2[[#This Row],[Subtotal ARS]]*Tabla2[[#This Row],[IVA]]) -> 6348.507 | O79: =Tabla2[[#This Row],[TOTAL ARS]]/Tabla2[[#This Row],[TC BNA]] -> 4.3782807 | P79: =_xlfn.XLOOKUP(A79,'TC_BNA xlsx'!A:A,'TC_BNA xlsx'!C:C,"No encontrado") -> 1450
A80: 46184 | B80: =MONTH(Tabla2[[#This Row],[Fecha]]) -> 6 | C80: HIERRO T 1" 1/4 X 1/8 | D80: =IFERROR(_xlfn.XLOOKUP(Tabla2[[#This Row],[Artículo]],Tabla1[Artículos],Tabla1[Rubro]),"") -> Materia Prima | E80: Casanova | F80: 14 | G80: kg | H80: 2357.02 | I80: =Tabla2[[#This Row],[Precio Unitario ARS]]/Tabla2[[#This Row],[TC BNA]] -> 1.625531 | J80: 0 | K80: ARS | L80: 0.21 | M80: =(Tabla2[[#This Row],[Precio Unitario ARS]]-(Tabla2[[#This Row],[Precio Unitario ARS]]*Tabla2[[#This Row],[DTO]]))*Tabla2[[#This Row],[Cantidad]] -> 32998.28 | N80: =Tabla2[[#This Row],[Subtotal ARS]]+(Tabla2[[#This Row],[Subtotal ARS]]*Tabla2[[#This Row],[IVA]]) -> 39927.919 | O80: =Tabla2[[#This Row],[TOTAL ARS]]/Tabla2[[#This Row],[TC BNA]] -> 27.536496 | P80: =_xlfn.XLOOKUP(A80,'TC_BNA xlsx'!A:A,'TC_BNA xlsx'!C:C,"No encontrado") -> 1450
A81: 46185 | B81: =MONTH(Tabla2[[#This Row],[Fecha]]) -> 6 | C81: Telgopor 50x50x450 | D81: =IFERROR(_xlfn.XLOOKUP(Tabla2[[#This Row],[Artículo]],Tabla1[Artículos],Tabla1[Rubro]),"") -> Embalaje | E81: Frío Acero | F81: 400 | G81: unidad | H81: 186.38 | I81: =Tabla2[[#This Row],[Precio Unitario ARS]]/Tabla2[[#This Row],[TC BNA]] -> 0.12853793 | J81: 0 | K81: ARS | L81: 0.21 | M81: =(Tabla2[[#This Row],[Precio Unitario ARS]]-(Tabla2[[#This Row],[Precio Unitario ARS]]*Tabla2[[#This Row],[DTO]]))*Tabla2[[#This Row],[Cantidad]] -> 74552 | N81: =Tabla2[[#This Row],[Subtotal ARS]]+(Tabla2[[#This Row],[Subtotal ARS]]*Tabla2[[#This Row],[IVA]]) -> 90207.92 | O81: =Tabla2[[#This Row],[TOTAL ARS]]/Tabla2[[#This Row],[TC BNA]] -> 62.212359 | P81: =_xlfn.XLOOKUP(A81,'TC_BNA xlsx'!A:A,'TC_BNA xlsx'!C:C,"No encontrado") -> 1450
A82: 46185 | B82: =MONTH(Tabla2[[#This Row],[Fecha]]) -> 6 | C82: Telgopor 50x50x600 | D82: =IFERROR(_xlfn.XLOOKUP(Tabla2[[#This Row],[Artículo]],Tabla1[Artículos],Tabla1[Rubro]),"") -> Embalaje | E82: Frío Acero | F82: 196 | G82: unidad | H82: 266.25 | I82: =Tabla2[[#This Row],[Precio Unitario ARS]]/Tabla2[[#This Row],[TC BNA]] -> 0.18362069 | J82: 0 | K82: ARS | L82: 0.21 | M82: =(Tabla2[[#This Row],[Precio Unitario ARS]]-(Tabla2[[#This Row],[Precio Unitario ARS]]*Tabla2[[#This Row],[DTO]]))*Tabla2[[#This Row],[Cantidad]] -> 52185 | N82: =Tabla2[[#This Row],[Subtotal ARS]]+(Tabla2[[#This Row],[Subtotal ARS]]*Tabla2[[#This Row],[IVA]]) -> 63143.85 | O82: =Tabla2[[#This Row],[TOTAL ARS]]/Tabla2[[#This Row],[TC BNA]] -> 43.547483 | P82: =_xlfn.XLOOKUP(A82,'TC_BNA xlsx'!A:A,'TC_BNA xlsx'!C:C,"No encontrado") -> 1450
A83: 46185 | B83: =MONTH(Tabla2[[#This Row],[Fecha]]) -> 6 | C83: Disco de Corte 115 mm | D83: =IFERROR(_xlfn.XLOOKUP(Tabla2[[#This Row],[Artículo]],Tabla1[Artículos],Tabla1[Rubro]),"") -> Herramientas | E83: Wurth | F83: 75 | G83: unidad | H83: 1201 | I83: =Tabla2[[#This Row],[Precio Unitario ARS]]/Tabla2[[#This Row],[TC BNA]] -> 0.82827586 | J83: 0 | K83: ARS | L83: 0.21 | M83: =(Tabla2[[#This Row],[Precio Unitario ARS]]-(Tabla2[[#This Row],[Precio Unitario ARS]]*Tabla2[[#This Row],[DTO]]))*Tabla2[[#This Row],[Cantidad]] -> 90075 | N83: =Tabla2[[#This Row],[Subtotal ARS]]+(Tabla2[[#This Row],[Subtotal ARS]]*Tabla2[[#This Row],[IVA]]) -> 108990.75 | O83: =Tabla2[[#This Row],[TOTAL ARS]]/Tabla2[[#This Row],[TC BNA]] -> 75.166034 | P83: =_xlfn.XLOOKUP(A83,'TC_BNA xlsx'!A:A,'TC_BNA xlsx'!C:C,"No encontrado") -> 1450
A84: 46185 | B84: =MONTH(Tabla2[[#This Row],[Fecha]]) -> 6 | C84: Costo de envío + seguro | D84: =IFERROR(_xlfn.XLOOKUP(Tabla2[[#This Row],[Artículo]],Tabla1[Artículos],Tabla1[Rubro]),"") -> Envío | E84: Wurth | F84: 1 | H84: =11154.98+1441.2 -> 12596.18 | I84: =Tabla2[[#This Row],[Precio Unitario ARS]]/Tabla2[[#This Row],[TC BNA]] -> 8.6870207 | J84: 0 | K84: ARS | L84: 0.21 | M84: =(Tabla2[[#This Row],[Precio Unitario ARS]]-(Tabla2[[#This Row],[Precio Unitario ARS]]*Tabla2[[#This Row],[DTO]]))*Tabla2[[#This Row],[Cantidad]] -> 12596.18 | N84: =Tabla2[[#This Row],[Subtotal ARS]]+(Tabla2[[#This Row],[Subtotal ARS]]*Tabla2[[#This Row],[IVA]]) -> 15241.378 | O84: =Tabla2[[#This Row],[TOTAL ARS]]/Tabla2[[#This Row],[TC BNA]] -> 10.511295 | P84: =_xlfn.XLOOKUP(A84,'TC_BNA xlsx'!A:A,'TC_BNA xlsx'!C:C,"No encontrado") -> 1450
A85: 46189 | B85: =MONTH(Tabla2[[#This Row],[Fecha]]) -> 6 | C85: Pintura Amarillo 04 - 1 l | D85: =IFERROR(_xlfn.XLOOKUP(Tabla2[[#This Row],[Artículo]],Tabla1[Artículos],Tabla1[Rubro]),"") -> Pintura | E85: Pinturería Giannoni | F85: 1 | G85: litro | H85: 21309.08 | I85: =Tabla2[[#This Row],[Precio Unitario ARS]]/Tabla2[[#This Row],[TC BNA]] -> 14.645416 | J85: 0 | K85: ARS | L85: 0.21 | M85: =(Tabla2[[#This Row],[Precio Unitario ARS]]-(Tabla2[[#This Row],[Precio Unitario ARS]]*Tabla2[[#This Row],[DTO]]))*Tabla2[[#This Row],[Cantidad]] -> 21309.08 | N85: =Tabla2[[#This Row],[Subtotal ARS]]+(Tabla2[[#This Row],[Subtotal ARS]]*Tabla2[[#This Row],[IVA]]) -> 25783.987 | O85: =Tabla2[[#This Row],[TOTAL ARS]]/Tabla2[[#This Row],[TC BNA]] -> 17.720953 | P85: =_xlfn.XLOOKUP(A85,'TC_BNA xlsx'!A:A,'TC_BNA xlsx'!C:C,"No encontrado") -> 1455
A86: 46189 | B86: =MONTH(Tabla2[[#This Row],[Fecha]]) -> 6 | C86: Tacos 1 1/2" x 3" x 1130mm | D86: =IFERROR(_xlfn.XLOOKUP(Tabla2[[#This Row],[Artículo]],Tabla1[Artículos],Tabla1[Rubro]),"") -> Embalaje | E86: Aserradero Alonso | F86: 300 | G86: unidad | H86: 1151.7875 | I86: =Tabla2[[#This Row],[Precio Unitario ARS]]/Tabla2[[#This Row],[TC BNA]] -> 0.79160654 | J86: 0.1 | K86: ARS | L86: 0.21 | M86: =(Tabla2[[#This Row],[Precio Unitario ARS]]-(Tabla2[[#This Row],[Precio Unitario ARS]]*Tabla2[[#This Row],[DTO]]))*Tabla2[[#This Row],[Cantidad]] -> 310982.63 | N86: =Tabla2[[#This Row],[Subtotal ARS]]+(Tabla2[[#This Row],[Subtotal ARS]]*Tabla2[[#This Row],[IVA]]) -> 376288.98 | O86: =Tabla2[[#This Row],[TOTAL ARS]]/Tabla2[[#This Row],[TC BNA]] -> 258.61786 | P86: =_xlfn.XLOOKUP(A86,'TC_BNA xlsx'!A:A,'TC_BNA xlsx'!C:C,"No encontrado") -> 1455
A87: 46189 | B87: =MONTH(Tabla2[[#This Row],[Fecha]]) -> 6 | C87: Tacos 2" x 2 1/2" x 640mm | D87: =IFERROR(_xlfn.XLOOKUP(Tabla2[[#This Row],[Artículo]],Tabla1[Artículos],Tabla1[Rubro]),"") -> Embalaje | E87: Aserradero Alonso | F87: 200 | G87: unidad | H87: 814.51901 | I87: =Tabla2[[#This Row],[Precio Unitario ARS]]/Tabla2[[#This Row],[TC BNA]] -> 0.55980688 | J87: 0.1 | K87: ARS | L87: 0.21 | M87: =(Tabla2[[#This Row],[Precio Unitario ARS]]-(Tabla2[[#This Row],[Precio Unitario ARS]]*Tabla2[[#This Row],[DTO]]))*Tabla2[[#This Row],[Cantidad]] -> 146613.42 | N87: =Tabla2[[#This Row],[Subtotal ARS]]+(Tabla2[[#This Row],[Subtotal ARS]]*Tabla2[[#This Row],[IVA]]) -> 177402.24 | O87: =Tabla2[[#This Row],[TOTAL ARS]]/Tabla2[[#This Row],[TC BNA]] -> 121.92594 | P87: =_xlfn.XLOOKUP(A87,'TC_BNA xlsx'!A:A,'TC_BNA xlsx'!C:C,"No encontrado") -> 1455
A88: 46190 | B88: =MONTH(Tabla2[[#This Row],[Fecha]]) -> 6 | C88: Papel higiénico Industrial | D88: =IFERROR(_xlfn.XLOOKUP(Tabla2[[#This Row],[Artículo]],Tabla1[Artículos],Tabla1[Rubro]),"") -> Limpieza | E88: Esdevi - Valeria | F88: 8 | G88: bolsa | H88: 7300 | I88: =Tabla2[[#This Row],[Precio Unitario ARS]]/Tabla2[[#This Row],[TC BNA]] -> 5 | J88: 0 | K88: ARS | L88: 0 | M88: =(Tabla2[[#This Row],[Precio Unitario ARS]]-(Tabla2[[#This Row],[Precio Unitario ARS]]*Tabla2[[#This Row],[DTO]]))*Tabla2[[#This Row],[Cantidad]] -> 58400 | N88: =Tabla2[[#This Row],[Subtotal ARS]]+(Tabla2[[#This Row],[Subtotal ARS]]*Tabla2[[#This Row],[IVA]]) -> 58400 | O88: =Tabla2[[#This Row],[TOTAL ARS]]/Tabla2[[#This Row],[TC BNA]] -> 40 | P88: =_xlfn.XLOOKUP(A88,'TC_BNA xlsx'!A:A,'TC_BNA xlsx'!C:C,"No encontrado") -> 1460
A89: 46190 | B89: =MONTH(Tabla2[[#This Row],[Fecha]]) -> 6 | C89: Dispénser de rollo de cocina | D89: =IFERROR(_xlfn.XLOOKUP(Tabla2[[#This Row],[Artículo]],Tabla1[Artículos],Tabla1[Rubro]),"") -> Limpieza | E89: Esdevi - Valeria | F89: 10 | G89: bolsa | H89: 9900 | I89: =Tabla2[[#This Row],[Precio Unitario ARS]]/Tabla2[[#This Row],[TC BNA]] -> 6.7808219 | J89: 0 | K89: ARS | L89: 0 | M89: =(Tabla2[[#This Row],[Precio Unitario ARS]]-(Tabla2[[#This Row],[Precio Unitario ARS]]*Tabla2[[#This Row],[DTO]]))*Tabla2[[#This Row],[Cantidad]] -> 99000 | N89: =Tabla2[[#This Row],[Subtotal ARS]]+(Tabla2[[#This Row],[Subtotal ARS]]*Tabla2[[#This Row],[IVA]]) -> 99000 | O89: =Tabla2[[#This Row],[TOTAL ARS]]/Tabla2[[#This Row],[TC BNA]] -> 67.808219 | P89: =_xlfn.XLOOKUP(A89,'TC_BNA xlsx'!A:A,'TC_BNA xlsx'!C:C,"No encontrado") -> 1460
A90: 46190 | B90: =MONTH(Tabla2[[#This Row],[Fecha]]) -> 6 | C90: Grampa Olmar 19 | D90: =IFERROR(_xlfn.XLOOKUP(Tabla2[[#This Row],[Artículo]],Tabla1[Artículos],Tabla1[Rubro]),"") -> Reventa | E90: Metalúrgica Santa Fe | F90: 1500 | G90: unidad | H90: 737 | I90: =Tabla2[[#This Row],[Precio Unitario ARS]]/Tabla2[[#This Row],[TC BNA]] -> 0.50479452 | J90: 0.2875 | K90: ARS | L90: 0.21 | M90: =(Tabla2[[#This Row],[Precio Unitario ARS]]-(Tabla2[[#This Row],[Precio Unitario ARS]]*Tabla2[[#This Row],[DTO]]))*Tabla2[[#This Row],[Cantidad]] -> 787668.75 | N90: =Tabla2[[#This Row],[Subtotal ARS]]+(Tabla2[[#This Row],[Subtotal ARS]]*Tabla2[[#This Row],[IVA]]) -> 953079.19 | O90: =Tabla2[[#This Row],[TOTAL ARS]]/Tabla2[[#This Row],[TC BNA]] -> 652.79396 | P90: =_xlfn.XLOOKUP(A90,'TC_BNA xlsx'!A:A,'TC_BNA xlsx'!C:C,"No encontrado") -> 1460
A91: 46190 | B91: =MONTH(Tabla2[[#This Row],[Fecha]]) -> 6 | C91: Grampa Olmar 26 | D91: =IFERROR(_xlfn.XLOOKUP(Tabla2[[#This Row],[Artículo]],Tabla1[Artículos],Tabla1[Rubro]),"") -> Reventa | E91: Metalúrgica Santa Fe | F91: 300 | G91: unidad | H91: 791 | I91: =Tabla2[[#This Row],[Precio Unitario ARS]]/Tabla2[[#This Row],[TC BNA]] -> 0.54178082 | J91: 0.2875 | K91: ARS | L91: 0.21 | M91: =(Tabla2[[#This Row],[Precio Unitario ARS]]-(Tabla2[[#This Row],[Precio Unitario ARS]]*Tabla2[[#This Row],[DTO]]))*Tabla2[[#This Row],[Cantidad]] -> 169076.25 | N91: =Tabla2[[#This Row],[Subtotal ARS]]+(Tabla2[[#This Row],[Subtotal ARS]]*Tabla2[[#This Row],[IVA]]) -> 204582.26 | O91: =Tabla2[[#This Row],[TOTAL ARS]]/Tabla2[[#This Row],[TC BNA]] -> 140.12484 | P91: =_xlfn.XLOOKUP(A91,'TC_BNA xlsx'!A:A,'TC_BNA xlsx'!C:C,"No encontrado") -> 1460
A92: 46190 | B92: =MONTH(Tabla2[[#This Row],[Fecha]]) -> 6 | C92: Grampa Chaveta 19 (3/4") | D92: =IFERROR(_xlfn.XLOOKUP(Tabla2[[#This Row],[Artículo]],Tabla1[Artículos],Tabla1[Rubro]),"") -> Reventa | E92: Metalúrgica Santa Fe | F92: 500 | G92: unidad | H92: 710 | I92: =Tabla2[[#This Row],[Precio Unitario ARS]]/Tabla2[[#This Row],[TC BNA]] -> 0.48630137 | J92: 0.2875 | K92: ARS | L92: 0.21 | M92: =(Tabla2[[#This Row],[Precio Unitario ARS]]-(Tabla2[[#This Row],[Precio Unitario ARS]]*Tabla2[[#This Row],[DTO]]))*Tabla2[[#This Row],[Cantidad]] -> 252937.5 | N92: =Tabla2[[#This Row],[Subtotal ARS]]+(Tabla2[[#This Row],[Subtotal ARS]]*Tabla2[[#This Row],[IVA]]) -> 306054.38 | O92: =Tabla2[[#This Row],[TOTAL ARS]]/Tabla2[[#This Row],[TC BNA]] -> 209.62628 | P92: =_xlfn.XLOOKUP(A92,'TC_BNA xlsx'!A:A,'TC_BNA xlsx'!C:C,"No encontrado") -> 1460
A93: 46190 | B93: =MONTH(Tabla2[[#This Row],[Fecha]]) -> 6 | C93: Grampa Media Omega 3/4" | D93: =IFERROR(_xlfn.XLOOKUP(Tabla2[[#This Row],[Artículo]],Tabla1[Artículos],Tabla1[Rubro]),"") -> Reventa | E93: Metalúrgica Santa Fe | F93: 100 | G93: unidad | H93: 130 | I93: =Tabla2[[#This Row],[Precio Unitario ARS]]/Tabla2[[#This Row],[TC BNA]] -> 0.089041096 | J93: 0.2875 | K93: ARS | L93: 0.21 | M93: =(Tabla2[[#This Row],[Precio Unitario ARS]]-(Tabla2[[#This Row],[Precio Unitario ARS]]*Tabla2[[#This Row],[DTO]]))*Tabla2[[#This Row],[Cantidad]] -> 9262.5 | N93: =Tabla2[[#This Row],[Subtotal ARS]]+(Tabla2[[#This Row],[Subtotal ARS]]*Tabla2[[#This Row],[IVA]]) -> 11207.625 | O93: =Tabla2[[#This Row],[TOTAL ARS]]/Tabla2[[#This Row],[TC BNA]] -> 7.6764555 | P93: =_xlfn.XLOOKUP(A93,'TC_BNA xlsx'!A:A,'TC_BNA xlsx'!C:C,"No encontrado") -> 1460
A94: 46190 | B94: =MONTH(Tabla2[[#This Row],[Fecha]]) -> 6 | C94: Grampa Omega 3/4" | D94: =IFERROR(_xlfn.XLOOKUP(Tabla2[[#This Row],[Artículo]],Tabla1[Artículos],Tabla1[Rubro]),"") -> Reventa | E94: Metalúrgica Santa Fe | F94: 3000 | G94: unidad | H94: 130 | I94: =Tabla2[[#This Row],[Precio Unitario ARS]]/Tabla2[[#This Row],[TC BNA]] -> 0.089041096 | J94: 0.2875 | K94: ARS | L94: 0.21 | M94: =(Tabla2[[#This Row],[Precio Unitario ARS]]-(Tabla2[[#This Row],[Precio Unitario ARS]]*Tabla2[[#This Row],[DTO]]))*Tabla2[[#This Row],[Cantidad]] -> 277875 | N94: =Tabla2[[#This Row],[Subtotal ARS]]+(Tabla2[[#This Row],[Subtotal ARS]]*Tabla2[[#This Row],[IVA]]) -> 336228.75 | O94: =Tabla2[[#This Row],[TOTAL ARS]]/Tabla2[[#This Row],[TC BNA]] -> 230.29366 | P94: =_xlfn.XLOOKUP(A94,'TC_BNA xlsx'!A:A,'TC_BNA xlsx'!C:C,"No encontrado") -> 1460
A95: 46190 | B95: =MONTH(Tabla2[[#This Row],[Fecha]]) -> 6 | C95: Grampa Omega 1" | D95: =IFERROR(_xlfn.XLOOKUP(Tabla2[[#This Row],[Artículo]],Tabla1[Artículos],Tabla1[Rubro]),"") -> Reventa | E95: Metalúrgica Santa Fe | F95: 500 | G95: unidad | H95: 217 | I95: =Tabla2[[#This Row],[Precio Unitario ARS]]/Tabla2[[#This Row],[TC BNA]] -> 0.14863014 | J95: 0.2875 | K95: ARS | L95: 0.21 | M95: =(Tabla2[[#This Row],[Precio Unitario ARS]]-(Tabla2[[#This Row],[Precio Unitario ARS]]*Tabla2[[#This Row],[DTO]]))*Tabla2[[#This Row],[Cantidad]] -> 77306.25 | N95: =Tabla2[[#This Row],[Subtotal ARS]]+(Tabla2[[#This Row],[Subtotal ARS]]*Tabla2[[#This Row],[IVA]]) -> 93540.562 | O95: =Tabla2[[#This Row],[TOTAL ARS]]/Tabla2[[#This Row],[TC BNA]] -> 64.068878 | P95: =_xlfn.XLOOKUP(A95,'TC_BNA xlsx'!A:A,'TC_BNA xlsx'!C:C,"No encontrado") -> 1460
A96: 46191 | B96: =MONTH(Tabla2[[#This Row],[Fecha]]) -> 6 | C96: Zapato Ombú prusiano | D96: =IFERROR(_xlfn.XLOOKUP(Tabla2[[#This Row],[Artículo]],Tabla1[Artículos],Tabla1[Rubro]),"") -> EPP | E96: Tech Safe | F96: 3 | G96: unidad | H96: 49509.2 | I96: =Tabla2[[#This Row],[Precio Unitario ARS]]/Tabla2[[#This Row],[TC BNA]] -> 33.679728 | J96: 0 | K96: ARS | L96: 0.21 | M96: =(Tabla2[[#This Row],[Precio Unitario ARS]]-(Tabla2[[#This Row],[Precio Unitario ARS]]*Tabla2[[#This Row],[DTO]]))*Tabla2[[#This Row],[Cantidad]] -> 148527.6 | N96: =Tabla2[[#This Row],[Subtotal ARS]]+(Tabla2[[#This Row],[Subtotal ARS]]*Tabla2[[#This Row],[IVA]]) -> 179718.4 | O96: =Tabla2[[#This Row],[TOTAL ARS]]/Tabla2[[#This Row],[TC BNA]] -> 122.25741 | P96: =_xlfn.XLOOKUP(A96,'TC_BNA xlsx'!A:A,'TC_BNA xlsx'!C:C,"No encontrado") -> 1470
... A145: 46203 | B145: =MONTH(Tabla2[[#This Row],[Fecha]]) -> 6 | C145: Cartón corrugado | D145: =IFERROR(_xlfn.XLOOKUP(Tabla2[[#This Row],[Artículo]],Tabla1[Artículos],Tabla1[Rubro]),"") -> Embalaje | E145: Embalsur | F145: 10 | G145: unidad | H145: 9148 | I145: =Tabla2[[#This Row],[Precio Unitario ARS]]/Tabla2[[#This Row],[TC BNA]] -> 6.0986667 | J145: 0 | K145: ARS | L145: 0.21 | M145: =(Tabla2[[#This Row],[Precio Unitario ARS]]-(Tabla2[[#This Row],[Precio Unitario ARS]]*Tabla2[[#This Row],[DTO]]))*Tabla2[[#This Row],[Cantidad]] -> 91480 | N145: =Tabla2[[#This Row],[Subtotal ARS]]+(Tabla2[[#This Row],[Subtotal ARS]]*Tabla2[[#This Row],[IVA]]) -> 110690.8 | O145: =Tabla2[[#This Row],[TOTAL ARS]]/Tabla2[[#This Row],[TC BNA]] -> 73.793867 | P145: =_xlfn.XLOOKUP(A145,'TC_BNA xlsx'!A:A,'TC_BNA xlsx'!C:C,"No encontrado") -> 1500
A146: 46203 | B146: =MONTH(Tabla2[[#This Row],[Fecha]]) -> 6 | C146: Lubricantes Aerosol | D146: =IFERROR(_xlfn.XLOOKUP(Tabla2[[#This Row],[Artículo]],Tabla1[Artículos],Tabla1[Rubro]),"") -> Lubricantes | E146: Fercol | F146: 2 | G146: pack | H146: 46620 | I146: =Tabla2[[#This Row],[Precio Unitario ARS]]/Tabla2[[#This Row],[TC BNA]] -> 31.08 | J146: 0 | K146: ARS | L146: 0.21 | M146: =(Tabla2[[#This Row],[Precio Unitario ARS]]-(Tabla2[[#This Row],[Precio Unitario ARS]]*Tabla2[[#This Row],[DTO]]))*Tabla2[[#This Row],[Cantidad]] -> 93240 | N146: =Tabla2[[#This Row],[Subtotal ARS]]+(Tabla2[[#This Row],[Subtotal ARS]]*Tabla2[[#This Row],[IVA]]) -> 112820.4 | O146: =Tabla2[[#This Row],[TOTAL ARS]]/Tabla2[[#This Row],[TC BNA]] -> 75.2136 | P146: =_xlfn.XLOOKUP(A146,'TC_BNA xlsx'!A:A,'TC_BNA xlsx'!C:C,"No encontrado") -> 1500 | Q146: bonif 37% (entender fac)
A147: 46203 | B147: =MONTH(Tabla2[[#This Row],[Fecha]]) -> 6 | C147: Tacos 2" x 2 1/2" x 640mm | D147: =IFERROR(_xlfn.XLOOKUP(Tabla2[[#This Row],[Artículo]],Tabla1[Artículos],Tabla1[Rubro]),"") -> Embalaje | E147: Aserradero Alonso | F147: 100 | G147: unidad | H147: 814.51901 | I147: =Tabla2[[#This Row],[Precio Unitario ARS]]/Tabla2[[#This Row],[TC BNA]] -> 0.54301267 | J147: 0.1 | K147: ARS | L147: 0.21 | M147: =(Tabla2[[#This Row],[Precio Unitario ARS]]-(Tabla2[[#This Row],[Precio Unitario ARS]]*Tabla2[[#This Row],[DTO]]))*Tabla2[[#This Row],[Cantidad]] -> 73306.711 | N147: =Tabla2[[#This Row],[Subtotal ARS]]+(Tabla2[[#This Row],[Subtotal ARS]]*Tabla2[[#This Row],[IVA]]) -> 88701.12 | O147: =Tabla2[[#This Row],[TOTAL ARS]]/Tabla2[[#This Row],[TC BNA]] -> 59.13408 | P147: =_xlfn.XLOOKUP(A147,'TC_BNA xlsx'!A:A,'TC_BNA xlsx'!C:C,"No encontrado") -> 1500
A148: 46203 | B148: =MONTH(Tabla2[[#This Row],[Fecha]]) -> 6 | C148: Tacos 1 1/2" x 3" x 300mm | D148: =IFERROR(_xlfn.XLOOKUP(Tabla2[[#This Row],[Artículo]],Tabla1[Artículos],Tabla1[Rubro]),"") -> Embalaje | E148: Aserradero Alonso | F148: 40 | G148: unidad | H148: 3818.0579 | I148: =Tabla2[[#This Row],[Precio Unitario ARS]]/Tabla2[[#This Row],[TC BNA]] -> 2.5453719 | J148: 0.1 | K148: ARS | L148: 0.21 | M148: =(Tabla2[[#This Row],[Precio Unitario ARS]]-(Tabla2[[#This Row],[Precio Unitario ARS]]*Tabla2[[#This Row],[DTO]]))*Tabla2[[#This Row],[Cantidad]] -> 137450.08 | N148: =Tabla2[[#This Row],[Subtotal ARS]]+(Tabla2[[#This Row],[Subtotal ARS]]*Tabla2[[#This Row],[IVA]]) -> 166314.6 | O148: =Tabla2[[#This Row],[TOTAL ARS]]/Tabla2[[#This Row],[TC BNA]] -> 110.8764 | P148: =_xlfn.XLOOKUP(A148,'TC_BNA xlsx'!A:A,'TC_BNA xlsx'!C:C,"No encontrado") -> 1500
A149: 46203 | B149: =MONTH(Tabla2[[#This Row],[Fecha]]) -> 6 | C149: Clavos 4" | D149: =IFERROR(_xlfn.XLOOKUP(Tabla2[[#This Row],[Artículo]],Tabla1[Artículos],Tabla1[Rubro]),"") -> Embalaje | E149: Aserradero Alonso | F149: 5 | G149: kg | H149: 5488.3719 | I149: =Tabla2[[#This Row],[Precio Unitario ARS]]/Tabla2[[#This Row],[TC BNA]] -> 3.6589146 | J149: 0.1 | K149: ARS | L149: 0.21 | M149: =(Tabla2[[#This Row],[Precio Unitario ARS]]-(Tabla2[[#This Row],[Precio Unitario ARS]]*Tabla2[[#This Row],[DTO]]))*Tabla2[[#This Row],[Cantidad]] -> 24697.674 | N149: =Tabla2[[#This Row],[Subtotal ARS]]+(Tabla2[[#This Row],[Subtotal ARS]]*Tabla2[[#This Row],[IVA]]) -> 29884.185 | O149: =Tabla2[[#This Row],[TOTAL ARS]]/Tabla2[[#This Row],[TC BNA]] -> 19.92279 | P149: =_xlfn.XLOOKUP(A149,'TC_BNA xlsx'!A:A,'TC_BNA xlsx'!C:C,"No encontrado") -> 1500
A150: 46203 | B150: =MONTH(Tabla2[[#This Row],[Fecha]]) -> 6 | C150: Tacos 1 1/2" x 3" x 1130mm | D150: =IFERROR(_xlfn.XLOOKUP(Tabla2[[#This Row],[Artículo]],Tabla1[Artículos],Tabla1[Rubro]),"") -> Embalaje | E150: Aserradero Alonso | F150: 300 | G150: unidad | H150: 1151.7875 | I150: =Tabla2[[#This Row],[Precio Unitario ARS]]/Tabla2[[#This Row],[TC BNA]] -> 0.76785835 | J150: 0.1 | K150: ARS | L150: 0.21 | M150: =(Tabla2[[#This Row],[Precio Unitario ARS]]-(Tabla2[[#This Row],[Precio Unitario ARS]]*Tabla2[[#This Row],[DTO]]))*Tabla2[[#This Row],[Cantidad]] -> 310982.63 | N150: =Tabla2[[#This Row],[Subtotal ARS]]+(Tabla2[[#This Row],[Subtotal ARS]]*Tabla2[[#This Row],[IVA]]) -> 376288.98 | O150: =Tabla2[[#This Row],[TOTAL ARS]]/Tabla2[[#This Row],[TC BNA]] -> 250.85932 | P150: =_xlfn.XLOOKUP(A150,'TC_BNA xlsx'!A:A,'TC_BNA xlsx'!C:C,"No encontrado") -> 1500
A151: 46203 | B151: =MONTH(Tabla2[[#This Row],[Fecha]]) -> 6 | C151: Tacos 2" x 2 1/2" x 640mm | D151: =IFERROR(_xlfn.XLOOKUP(Tabla2[[#This Row],[Artículo]],Tabla1[Artículos],Tabla1[Rubro]),"") -> Embalaje | E151: Aserradero Alonso | F151: 300 | G151: unidad | H151: 814.51901 | I151: =Tabla2[[#This Row],[Precio Unitario ARS]]/Tabla2[[#This Row],[TC BNA]] -> 0.54301267 | J151: 0.1 | K151: ARS | L151: 0.21 | M151: =(Tabla2[[#This Row],[Precio Unitario ARS]]-(Tabla2[[#This Row],[Precio Unitario ARS]]*Tabla2[[#This Row],[DTO]]))*Tabla2[[#This Row],[Cantidad]] -> 219920.13 | N151: =Tabla2[[#This Row],[Subtotal ARS]]+(Tabla2[[#This Row],[Subtotal ARS]]*Tabla2[[#This Row],[IVA]]) -> 266103.36 | O151: =Tabla2[[#This Row],[TOTAL ARS]]/Tabla2[[#This Row],[TC BNA]] -> 177.40224 | P151: =_xlfn.XLOOKUP(A151,'TC_BNA xlsx'!A:A,'TC_BNA xlsx'!C:C,"No encontrado") -> 1500
A152: 46204 | B152: =MONTH(Tabla2[[#This Row],[Fecha]]) -> 7 | C152: Guantes Poli (Tactil) 8# | D152: =IFERROR(_xlfn.XLOOKUP(Tabla2[[#This Row],[Artículo]],Tabla1[Artículos],Tabla1[Rubro]),"") -> EPP | E152: Tech Safe | F152: 24 | G152: par | H152: 651.22 | I152: =Tabla2[[#This Row],[Precio Unitario ARS]]/Tabla2[[#This Row],[TC BNA]] -> 0.43127152 | J152: 0 | K152: ARS | L152: 0.21 | M152: =(Tabla2[[#This Row],[Precio Unitario ARS]]-(Tabla2[[#This Row],[Precio Unitario ARS]]*Tabla2[[#This Row],[DTO]]))*Tabla2[[#This Row],[Cantidad]] -> 15629.28 | N152: =Tabla2[[#This Row],[Subtotal ARS]]+(Tabla2[[#This Row],[Subtotal ARS]]*Tabla2[[#This Row],[IVA]]) -> 18911.429 | O152: =Tabla2[[#This Row],[TOTAL ARS]]/Tabla2[[#This Row],[TC BNA]] -> 12.524125 | P152: =_xlfn.XLOOKUP(A152,'TC_BNA xlsx'!A:A,'TC_BNA xlsx'!C:C,"No encontrado") -> 1510
A153: 46204 | B153: =MONTH(Tabla2[[#This Row],[Fecha]]) -> 7 | C153: Guantes Poli (Tactil) 10# | D153: =IFERROR(_xlfn.XLOOKUP(Tabla2[[#This Row],[Artículo]],Tabla1[Artículos],Tabla1[Rubro]),"") -> EPP | E153: Tech Safe | F153: 24 | G153: par | H153: 651.22 | I153: =Tabla2[[#This Row],[Precio Unitario ARS]]/Tabla2[[#This Row],[TC BNA]] -> 0.43127152 | J153: 0 | K153: ARS | L153: 0.21 | M153: =(Tabla2[[#This Row],[Precio Unitario ARS]]-(Tabla2[[#This Row],[Precio Unitario ARS]]*Tabla2[[#This Row],[DTO]]))*Tabla2[[#This Row],[Cantidad]] -> 15629.28 | N153: =Tabla2[[#This Row],[Subtotal ARS]]+(Tabla2[[#This Row],[Subtotal ARS]]*Tabla2[[#This Row],[IVA]]) -> 18911.429 | O153: =Tabla2[[#This Row],[TOTAL ARS]]/Tabla2[[#This Row],[TC BNA]] -> 12.524125 | P153: =_xlfn.XLOOKUP(A153,'TC_BNA xlsx'!A:A,'TC_BNA xlsx'!C:C,"No encontrado") -> 1510
A154: 46204 | B154: =MONTH(Tabla2[[#This Row],[Fecha]]) -> 7 | C154: Guantes Dyne 5 | D154: =IFERROR(_xlfn.XLOOKUP(Tabla2[[#This Row],[Artículo]],Tabla1[Artículos],Tabla1[Rubro]),"") -> EPP | E154: Tech Safe | F154: 24 | G154: par | H154: 4795 | I154: =Tabla2[[#This Row],[Precio Unitario ARS]]/Tabla2[[#This Row],[TC BNA]] -> 3.1754967 | J154: 0 | K154: ARS | L154: 0.21 | M154: =(Tabla2[[#This Row],[Precio Unitario ARS]]-(Tabla2[[#This Row],[Precio Unitario ARS]]*Tabla2[[#This Row],[DTO]]))*Tabla2[[#This Row],[Cantidad]] -> 115080 | N154: =Tabla2[[#This Row],[Subtotal ARS]]+(Tabla2[[#This Row],[Subtotal ARS]]*Tabla2[[#This Row],[IVA]]) -> 139246.8 | O154: =Tabla2[[#This Row],[TOTAL ARS]]/Tabla2[[#This Row],[TC BNA]] -> 92.216424 | P154: =_xlfn.XLOOKUP(A154,'TC_BNA xlsx'!A:A,'TC_BNA xlsx'!C:C,"No encontrado") -> 1510
A155: 46204 | B155: =MONTH(Tabla2[[#This Row],[Fecha]]) -> 7 | C155: Arandela Plana Zinc. 1/4" | D155: =IFERROR(_xlfn.XLOOKUP(Tabla2[[#This Row],[Artículo]],Tabla1[Artículos],Tabla1[Rubro]),"") -> Reventa | E155: Disur | F155: 32 | G155: kg | H155: 4800 | I155: =Tabla2[[#This Row],[Precio Unitario ARS]]/Tabla2[[#This Row],[TC BNA]] -> 3.1788079 | J155: 0 | K155: ARS | L155: 0.21 | M155: =(Tabla2[[#This Row],[Precio Unitario ARS]]-(Tabla2[[#This Row],[Precio Unitario ARS]]*Tabla2[[#This Row],[DTO]]))*Tabla2[[#This Row],[Cantidad]] -> 153600 | N155: =Tabla2[[#This Row],[Subtotal ARS]]+(Tabla2[[#This Row],[Subtotal ARS]]*Tabla2[[#This Row],[IVA]]) -> 185856 | O155: =Tabla2[[#This Row],[TOTAL ARS]]/Tabla2[[#This Row],[TC BNA]] -> 123.08344 | P155: =_xlfn.XLOOKUP(A155,'TC_BNA xlsx'!A:A,'TC_BNA xlsx'!C:C,"No encontrado") -> 1510
A156: 46204 | B156: =MONTH(Tabla2[[#This Row],[Fecha]]) -> 7 | C156: Arandela Plana Zinc. 5/16" | D156: =IFERROR(_xlfn.XLOOKUP(Tabla2[[#This Row],[Artículo]],Tabla1[Artículos],Tabla1[Rubro]),"") -> Reventa | E156: Disur | F156: 20 | G156: kg | H156: 4890 | I156: =Tabla2[[#This Row],[Precio Unitario ARS]]/Tabla2[[#This Row],[TC BNA]] -> 3.2384106 | J156: 0 | K156: ARS | L156: 0.21 | M156: =(Tabla2[[#This Row],[Precio Unitario ARS]]-(Tabla2[[#This Row],[Precio Unitario ARS]]*Tabla2[[#This Row],[DTO]]))*Tabla2[[#This Row],[Cantidad]] -> 97800 | N156: =Tabla2[[#This Row],[Subtotal ARS]]+(Tabla2[[#This Row],[Subtotal ARS]]*Tabla2[[#This Row],[IVA]]) -> 118338 | O156: =Tabla2[[#This Row],[TOTAL ARS]]/Tabla2[[#This Row],[TC BNA]] -> 78.369536 | P156: =_xlfn.XLOOKUP(A156,'TC_BNA xlsx'!A:A,'TC_BNA xlsx'!C:C,"No encontrado") -> 1510
A157: 46204 | B157: =MONTH(Tabla2[[#This Row],[Fecha]]) -> 7 | C157: Tor. Cab. Re. 1/4" | D157: =IFERROR(_xlfn.XLOOKUP(Tabla2[[#This Row],[Artículo]],Tabla1[Artículos],Tabla1[Rubro]),"") -> Reventa | E157: Disur | F157: 5000 | G157: unidad | H157: 29.2 | I157: =Tabla2[[#This Row],[Precio Unitario ARS]]/Tabla2[[#This Row],[TC BNA]] -> 0.019337748 | J157: 0 | K157: ARS | L157: 0.21 | M157: =(Tabla2[[#This Row],[Precio Unitario ARS]]-(Tabla2[[#This Row],[Precio Unitario ARS]]*Tabla2[[#This Row],[DTO]]))*Tabla2[[#This Row],[Cantidad]] -> 146000 | N157: =Tabla2[[#This Row],[Subtotal ARS]]+(Tabla2[[#This Row],[Subtotal ARS]]*Tabla2[[#This Row],[IVA]]) -> 176660 | O157: =Tabla2[[#This Row],[TOTAL ARS]]/Tabla2[[#This Row],[TC BNA]] -> 116.99338 | P157: =_xlfn.XLOOKUP(A157,'TC_BNA xlsx'!A:A,'TC_BNA xlsx'!C:C,"No encontrado") -> 1510
A158: 46204 | B158: =MONTH(Tabla2[[#This Row],[Fecha]]) -> 7 | C158: Tuerca Cupla 1/4" | D158: =IFERROR(_xlfn.XLOOKUP(Tabla2[[#This Row],[Artículo]],Tabla1[Artículos],Tabla1[Rubro]),"") -> Reventa | E158: Disur | F158: 10000 | G158: unidad | H158: 235.44 | I158: =Tabla2[[#This Row],[Precio Unitario ARS]]/Tabla2[[#This Row],[TC BNA]] -> 0.15592053 | J158: 0 | K158: ARS | L158: 0.21 | M158: =(Tabla2[[#This Row],[Precio Unitario ARS]]-(Tabla2[[#This Row],[Precio Unitario ARS]]*Tabla2[[#This Row],[DTO]]))*Tabla2[[#This Row],[Cantidad]] -> 2354400 | N158: =Tabla2[[#This Row],[Subtotal ARS]]+(Tabla2[[#This Row],[Subtotal ARS]]*Tabla2[[#This Row],[IVA]]) -> 2848824 | O158: =Tabla2[[#This Row],[TOTAL ARS]]/Tabla2[[#This Row],[TC BNA]] -> 1886.6384 | P158: =_xlfn.XLOOKUP(A158,'TC_BNA xlsx'!A:A,'TC_BNA xlsx'!C:C,"No encontrado") -> 1510
...

Sheet Cotizaciones
A1: Fecha | B1: Artículo | C1: Cantidad | D1: Unidad | E1: Precio Cotizado | F1: Últ. Precio | G1: Último Proveedor | H1: Mejor Precio | I1: Mejor Proveedor | J1: Variación vs Últ. Precio | K1: Dif por Unidad | L1: Sobrecosto Total | M1: Estado | N1: Observaciones
A2: 46222 | B2: Zapato Ombú prusiano | C2: 2 | D2: unidad | E2: 59000 | F2: =IF(Tabla4[[#This Row],[Artículo]]="","",IFERROR(_xlfn.XLOOKUP(Tabla4[[#This Row],[Artículo]],Tabla2[Artículo],Tabla2[Precio Unitario ARS],"",0,-1),"")) -> 59000 | G2: =IF(Tabla4[[#This Row],[Artículo]]="","",IFERROR(_xlfn.XLOOKUP(Tabla4[[#This Row],[Artículo]],Tabla2[Artículo],Tabla2[Proveedor],"",0,-1),"")) -> Aníbal Roncoroni | H2: {=IF(Tabla4[[#This Row],[Artículo]]="","",IFERROR(MIN(_xlfn._xlws.FILTER(Tabla2[Precio Unitario ARS],Tabla2[Artículo]=Tabla4[[#This Row],[Artículo]])),""))} -> 49509.2 | I2: {=IF(Tabla4[[#This Row],[Artículo]]="","",IFERROR(_xlfn.XLOOKUP(1,(Tabla2[Artículo]=Tabla4[[#This Row],[Artículo]])*(Tabla2[Precio Unitario ARS]=Tabla4[[#This Row],[Mejor Precio]]),Tabla2[Proveedor]),""))} -> Tech Safe | J2: =IF(Tabla4[[#This Row],[Artículo]]="","",IFERROR((Tabla4[[#This Row],[Precio Cotizado]]-Tabla4[[#This Row],[Últ. Precio]])/Tabla4[[#This Row],[Últ. Precio]],"")) -> 0 | K2: =IF(Tabla4[[#This Row],[Artículo]]="","",IFERROR(Tabla4[[#This Row],[Precio Cotizado]]-Tabla4[[#This Row],[Mejor Precio]],"")) -> 9490.8 | L2: =IF(Tabla4[[#This Row],[Artículo]]="","",IFERROR(Tabla4[[#This Row],[Dif por Unidad]]*Tabla4[[#This Row],[Cantidad]],"")) -> 18981.6 | M2: =IF(B2="","",IF(J2<0,"Más barato",IF(J2<=5%,"Dentro del rango",IF(J2<=15%,"Revisar","Precio alto")))) -> Dentro del rango | N2: =IF(Tabla4[[#This Row],[Artículo]]="","",IF(Tabla4[[#This Row],[Estado]]="Más barato","✓ Conviene comprar. Ahorro respecto al mejor precio.",IF(Tabla4[[#This Row],[Estado]]="Dentro del rango","✓ Precio dentro del rango habitual.",IF(Tabla4[[#This Row],[Estado]]="Revisar","⚠ Solicitar otra cotización.","🚨 Precio elevado. Negociar o buscar alternativa.")))) -> ✓ Precio dentro del rango habitual.
A3: 46227 | B3: Varilla Roscada Zinc. 1/4" | C3: 2000 | D3: unidad | E3: 472.5 | F3: =IF(Tabla4[[#This Row],[Artículo]]="","",IFERROR(_xlfn.XLOOKUP(Tabla4[[#This Row],[Artículo]],Tabla2[Artículo],Tabla2[Precio Unitario ARS],"",0,-1),"")) -> 463.05 | G3: =IF(Tabla4[[#This Row],[Artículo]]="","",IFERROR(_xlfn.XLOOKUP(Tabla4[[#This Row],[Artículo]],Tabla2[Artículo],Tabla2[Proveedor],"",0,-1),"")) -> Dusvar | H3: {=IF(Tabla4[[#This Row],[Artículo]]="","",IFERROR(MIN(_xlfn._xlws.FILTER(Tabla2[Precio Unitario ARS],Tabla2[Artículo]=Tabla4[[#This Row],[Artículo]])),""))} -> 450 | I3: {=IF(Tabla4[[#This Row],[Artículo]]="","",IFERROR(_xlfn.XLOOKUP(1,(Tabla2[Artículo]=Tabla4[[#This Row],[Artículo]])*(Tabla2[Precio Unitario ARS]=Tabla4[[#This Row],[Mejor Precio]]),Tabla2[Proveedor]),""))} -> Dusvar | J3: =IF(Tabla4[[#This Row],[Artículo]]="","",IFERROR((Tabla4[[#This Row],[Precio Cotizado]]-Tabla4[[#This Row],[Últ. Precio]])/Tabla4[[#This Row],[Últ. Precio]],"")) -> 0.020408163 | K3: =IF(Tabla4[[#This Row],[Artículo]]="","",IFERROR(Tabla4[[#This Row],[Precio Cotizado]]-Tabla4[[#This Row],[Mejor Precio]],"")) -> 22.5 | L3: =IF(Tabla4[[#This Row],[Artículo]]="","",IFERROR(Tabla4[[#This Row],[Dif por Unidad]]*Tabla4[[#This Row],[Cantidad]],"")) -> 45000 | M3: =IF(B3="","",IF(J3<0,"Más barato",IF(J3<=5%,"Dentro del rango",IF(J3<=15%,"Revisar","Precio alto")))) -> Dentro del rango | N3: =IF(Tabla4[[#This Row],[Artículo]]="","",IF(Tabla4[[#This Row],[Estado]]="Más barato","✓ Conviene comprar. Ahorro respecto al mejor precio.",IF(Tabla4[[#This Row],[Estado]]="Dentro del rango","✓ Precio dentro del rango habitual.",IF(Tabla4[[#This Row],[Estado]]="Revisar","⚠ Solicitar otra cotización.","🚨 Precio elevado. Negociar o buscar alternativa.")))) -> ✓ Precio dentro del rango habitual.
A4: 46227 | B4: Varilla Roscada Zinc. 3/8" | C4: 700 | D4: unidad | E4: 1026.95 | F4: =IF(Tabla4[[#This Row],[Artículo]]="","",IFERROR(_xlfn.XLOOKUP(Tabla4[[#This Row],[Artículo]],Tabla2[Artículo],Tabla2[Precio Unitario ARS],"",0,-1),"")) -> 1026 | G4: =IF(Tabla4[[#This Row],[Artículo]]="","",IFERROR(_xlfn.XLOOKUP(Tabla4[[#This Row],[Artículo]],Tabla2[Artículo],Tabla2[Proveedor],"",0,-1),"")) -> Dusvar | H4: {=IF(Tabla4[[#This Row],[Artículo]]="","",IFERROR(MIN(_xlfn._xlws.FILTER(Tabla2[Precio Unitario ARS],Tabla2[Artículo]=Tabla4[[#This Row],[Artículo]])),""))} -> 998 | I4: {=IF(Tabla4[[#This Row],[Artículo]]="","",IFERROR(_xlfn.XLOOKUP(1,(Tabla2[Artículo]=Tabla4[[#This Row],[Artículo]])*(Tabla2[Precio Unitario ARS]=Tabla4[[#This Row],[Mejor Precio]]),Tabla2[Proveedor]),""))} -> Dusvar | J4: =IF(Tabla4[[#This Row],[Artículo]]="","",IFERROR((Tabla4[[#This Row],[Precio Cotizado]]-Tabla4[[#This Row],[Últ. Precio]])/Tabla4[[#This Row],[Últ. Precio]],"")) -> 0.00092592593 | K4: =IF(Tabla4[[#This Row],[Artículo]]="","",IFERROR(Tabla4[[#This Row],[Precio Cotizado]]-Tabla4[[#This Row],[Mejor Precio]],"")) -> 28.95 | L4: =IF(Tabla4[[#This Row],[Artículo]]="","",IFERROR(Tabla4[[#This Row],[Dif por Unidad]]*Tabla4[[#This Row],[Cantidad]],"")) -> 20265 | M4: =IF(B4="","",IF(J4<0,"Más barato",IF(J4<=5%,"Dentro del rango",IF(J4<=15%,"Revisar","Precio alto")))) -> Dentro del rango | N4: =IF(Tabla4[[#This Row],[Artículo]]="","",IF(Tabla4[[#This Row],[Estado]]="Más barato","✓ Conviene comprar. Ahorro respecto al mejor precio.",IF(Tabla4[[#This Row],[Estado]]="Dentro del rango","✓ Precio dentro del rango habitual.",IF(Tabla4[[#This Row],[Estado]]="Revisar","⚠ Solicitar otra cotización.","🚨 Precio elevado. Negociar o buscar alternativa.")))) -> ✓ Precio dentro del rango habitual.
A5: 46227 | B5: Varilla Roscada Zinc. 5/16" | C5: 1000 | D5: unidad | E5: 730.26 | F5: =IF(Tabla4[[#This Row],[Artículo]]="","",IFERROR(_xlfn.XLOOKUP(Tabla4[[#This Row],[Artículo]],Tabla2[Artículo],Tabla2[Precio Unitario ARS],"",0,-1),"")) -> 730.26 | G5: =IF(Tabla4[[#This Row],[Artículo]]="","",IFERROR(_xlfn.XLOOKUP(Tabla4[[#This Row],[Artículo]],Tabla2[Artículo],Tabla2[Proveedor],"",0,-1),"")) -> Dusvar | H5: {=IF(Tabla4[[#This Row],[Artículo]]="","",IFERROR(MIN(_xlfn._xlws.FILTER(Tabla2[Precio Unitario ARS],Tabla2[Artículo]=Tabla4[[#This Row],[Artículo]])),""))} -> 717 | I5: {=IF(Tabla4[[#This Row],[Artículo]]="","",IFERROR(_xlfn.XLOOKUP(1,(Tabla2[Artículo]=Tabla4[[#This Row],[Artículo]])*(Tabla2[Precio Unitario ARS]=Tabla4[[#This Row],[Mejor Precio]]),Tabla2[Proveedor]),""))} -> Dusvar | J5: =IF(Tabla4[[#This Row],[Artículo]]="","",IFERROR((Tabla4[[#This Row],[Precio Cotizado]]-Tabla4[[#This Row],[Últ. Precio]])/Tabla4[[#This Row],[Últ. Precio]],"")) -> 0 | K5: =IF(Tabla4[[#This Row],[Artículo]]="","",IFERROR(Tabla4[[#This Row],[Precio Cotizado]]-Tabla4[[#This Row],[Mejor Precio]],"")) -> 13.26 | L5: =IF(Tabla4[[#This Row],[Artículo]]="","",IFERROR(Tabla4[[#This Row],[Dif por Unidad]]*Tabla4[[#This Row],[Cantidad]],"")) -> 13260 | M5: =IF(B5="","",IF(J5<0,"Más barato",IF(J5<=5%,"Dentro del rango",IF(J5<=15%,"Revisar","Precio alto")))) -> Dentro del rango | N5: =IF(Tabla4[[#This Row],[Artículo]]="","",IF(Tabla4[[#This Row],[Estado]]="Más barato","✓ Conviene comprar. Ahorro respecto al mejor precio.",IF(Tabla4[[#This Row],[Estado]]="Dentro del rango","✓ Precio dentro del rango habitual.",IF(Tabla4[[#This Row],[Estado]]="Revisar","⚠ Solicitar otra cotización.","🚨 Precio elevado. Negociar o buscar alternativa.")))) -> ✓ Precio dentro del rango habitual.
A6: 46227 | B6: Lysoform | C6: 5 | E6: 3462.8 | F6: =IF(Tabla4[[#This Row],[Artículo]]="","",IFERROR(_xlfn.XLOOKUP(Tabla4[[#This Row],[Artículo]],Tabla2[Artículo],Tabla2[Precio Unitario ARS],"",0,-1),"")) -> 3462.8 | G6: =IF(Tabla4[[#This Row],[Artículo]]="","",IFERROR(_xlfn.XLOOKUP(Tabla4[[#This Row],[Artículo]],Tabla2[Artículo],Tabla2[Proveedor],"",0,-1),"")) -> Imperio de la Limpieza | H6: {=IF(Tabla4[[#This Row],[Artículo]]="","",IFERROR(MIN(_xlfn._xlws.FILTER(Tabla2[Precio Unitario ARS],Tabla2[Artículo]=Tabla4[[#This Row],[Artículo]])),""))} -> 3198.34 | I6: {=IF(Tabla4[[#This Row],[Artículo]]="","",IFERROR(_xlfn.XLOOKUP(1,(Tabla2[Artículo]=Tabla4[[#This Row],[Artículo]])*(Tabla2[Precio Unitario ARS]=Tabla4[[#This Row],[Mejor Precio]]),Tabla2[Proveedor]),""))} -> Imperio de la Limpieza | J6: =IF(Tabla4[[#This Row],[Artículo]]="","",IFERROR((Tabla4[[#This Row],[Precio Cotizado]]-Tabla4[[#This Row],[Últ. Precio]])/Tabla4[[#This Row],[Últ. Precio]],"")) -> 0 | K6: =IF(Tabla4[[#This Row],[Artículo]]="","",IFERROR(Tabla4[[#This Row],[Precio Cotizado]]-Tabla4[[#This Row],[Mejor Precio]],"")) -> 264.46 | L6: =IF(Tabla4[[#This Row],[Artículo]]="","",IFERROR(Tabla4[[#This Row],[Dif por Unidad]]*Tabla4[[#This Row],[Cantidad]],"")) -> 1322.3 | M6: =IF(B6="","",IF(J6<0,"Más barato",IF(J6<=5%,"Dentro del rango",IF(J6<=15%,"Revisar","Precio alto")))) -> Dentro del rango | N6: =IF(Tabla4[[#This Row],[Artículo]]="","",IF(Tabla4[[#This Row],[Estado]]="Más barato","✓ Conviene comprar. Ahorro respecto al mejor precio.",IF(Tabla4[[#This Row],[Estado]]="Dentro del rango","✓ Precio dentro del rango habitual.",IF(Tabla4[[#This Row],[Estado]]="Revisar","⚠ Solicitar otra cotización.","🚨 Precio elevado. Negociar o buscar alternativa.")))) -> ✓ Precio dentro del rango habitual.
A7: 46227 | B7: Bolsas 50x70 | C7: 15 | E7: =611.57/15 -> 40.771333 | F7: =IF(Tabla4[[#This Row],[Artículo]]="","",IFERROR(_xlfn.XLOOKUP(Tabla4[[#This Row],[Artículo]],Tabla2[Artículo],Tabla2[Precio Unitario ARS],"",0,-1),"")) -> 611.57 | G7: =IF(Tabla4[[#This Row],[Artículo]]="","",IFERROR(_xlfn.XLOOKUP(Tabla4[[#This Row],[Artículo]],Tabla2[Artículo],Tabla2[Proveedor],"",0,-1),"")) -> Imperio de la Limpieza | H7: {=IF(Tabla4[[#This Row],[Artículo]]="","",IFERROR(MIN(_xlfn._xlws.FILTER(Tabla2[Precio Unitario ARS],Tabla2[Artículo]=Tabla4[[#This Row],[Artículo]])),""))} -> 61.157 | I7: {=IF(Tabla4[[#This Row],[Artículo]]="","",IFERROR(_xlfn.XLOOKUP(1,(Tabla2[Artículo]=Tabla4[[#This Row],[Artículo]])*(Tabla2[Precio Unitario ARS]=Tabla4[[#This Row],[Mejor Precio]]),Tabla2[Proveedor]),""))} -> Imperio de la Limpieza | J7: =IF(Tabla4[[#This Row],[Artículo]]="","",IFERROR((Tabla4[[#This Row],[Precio Cotizado]]-Tabla4[[#This Row],[Últ. Precio]])/Tabla4[[#This Row],[Últ. Precio]],"")) -> -0.93333333 | K7: =IF(Tabla4[[#This Row],[Artículo]]="","",IFERROR(Tabla4[[#This Row],[Precio Cotizado]]-Tabla4[[#This Row],[Mejor Precio]],"")) -> -20.385667 | L7: =IF(Tabla4[[#This Row],[Artículo]]="","",IFERROR(Tabla4[[#This Row],[Dif por Unidad]]*Tabla4[[#This Row],[Cantidad]],"")) -> -305.785 | M7: =IF(B7="","",IF(J7<0,"Más barato",IF(J7<=5%,"Dentro del rango",IF(J7<=15%,"Revisar","Precio alto")))) -> Más barato | N7: =IF(Tabla4[[#This Row],[Artículo]]="","",IF(Tabla4[[#This Row],[Estado]]="Más barato","✓ Conviene comprar. Ahorro respecto al mejor precio.",IF(Tabla4[[#This Row],[Estado]]="Dentro del rango","✓ Precio dentro del rango habitual.",IF(Tabla4[[#This Row],[Estado]]="Revisar","⚠ Solicitar otra cotización.","🚨 Precio elevado. Negociar o buscar alternativa.")))) -> ✓ Conviene comprar. Ahorro respecto al mejor precio.
A8: 46227 | B8: Bolsas 80x110 | C8: 10 | E8: =1876.03/10 -> 187.603 | F8: =IF(Tabla4[[#This Row],[Artículo]]="","",IFERROR(_xlfn.XLOOKUP(Tabla4[[#This Row],[Artículo]],Tabla2[Artículo],Tabla2[Precio Unitario ARS],"",0,-1),"")) -> 1876.03 | G8: =IF(Tabla4[[#This Row],[Artículo]]="","",IFERROR(_xlfn.XLOOKUP(Tabla4[[#This Row],[Artículo]],Tabla2[Artículo],Tabla2[Proveedor],"",0,-1),"")) -> Imperio de la Limpieza | H8: {=IF(Tabla4[[#This Row],[Artículo]]="","",IFERROR(MIN(_xlfn._xlws.FILTER(Tabla2[Precio Unitario ARS],Tabla2[Artículo]=Tabla4[[#This Row],[Artículo]])),""))} -> 187.603 | I8: {=IF(Tabla4[[#This Row],[Artículo]]="","",IFERROR(_xlfn.XLOOKUP(1,(Tabla2[Artículo]=Tabla4[[#This Row],[Artículo]])*(Tabla2[Precio Unitario ARS]=Tabla4[[#This Row],[Mejor Precio]]),Tabla2[Proveedor]),""))} -> Imperio de la Limpieza | J8: =IF(Tabla4[[#This Row],[Artículo]]="","",IFERROR((Tabla4[[#This Row],[Precio Cotizado]]-Tabla4[[#This Row],[Últ. Precio]])/Tabla4[[#This Row],[Últ. Precio]],"")) -> -0.9 | K8: =IF(Tabla4[[#This Row],[Artículo]]="","",IFERROR(Tabla4[[#This Row],[Precio Cotizado]]-Tabla4[[#This Row],[Mejor Precio]],"")) -> 0 | L8: =IF(Tabla4[[#This Row],[Artículo]]="","",IFERROR(Tabla4[[#This Row],[Dif por Unidad]]*Tabla4[[#This Row],[Cantidad]],"")) -> 0 | M8: =IF(B8="","",IF(J8<0,"Más barato",IF(J8<=5%,"Dentro del rango",IF(J8<=15%,"Revisar","Precio alto")))) -> Más barato | N8: =IF(Tabla4[[#This Row],[Artículo]]="","",IF(Tabla4[[#This Row],[Estado]]="Más barato","✓ Conviene comprar. Ahorro respecto al mejor precio.",IF(Tabla4[[#This Row],[Estado]]="Dentro del rango","✓ Precio dentro del rango habitual.",IF(Tabla4[[#This Row],[Estado]]="Revisar","⚠ Solicitar otra cotización.","🚨 Precio elevado. Negociar o buscar alternativa.")))) -> ✓ Conviene comprar. Ahorro respecto al mejor precio.
A9: 46227 | B9: Esponjas | C9: 5 | E9: 553.71 | F9: =IF(Tabla4[[#This Row],[Artículo]]="","",IFERROR(_xlfn.XLOOKUP(Tabla4[[#This Row],[Artículo]],Tabla2[Artículo],Tabla2[Precio Unitario ARS],"",0,-1),"")) -> 553.71 | G9: =IF(Tabla4[[#This Row],[Artículo]]="","",IFERROR(_xlfn.XLOOKUP(Tabla4[[#This Row],[Artículo]],Tabla2[Artículo],Tabla2[Proveedor],"",0,-1),"")) -> Imperio de la Limpieza | H9: {=IF(Tabla4[[#This Row],[Artículo]]="","",IFERROR(MIN(_xlfn._xlws.FILTER(Tabla2[Precio Unitario ARS],Tabla2[Artículo]=Tabla4[[#This Row],[Artículo]])),""))} -> 504.13 | I9: {=IF(Tabla4[[#This Row],[Artículo]]="","",IFERROR(_xlfn.XLOOKUP(1,(Tabla2[Artículo]=Tabla4[[#This Row],[Artículo]])*(Tabla2[Precio Unitario ARS]=Tabla4[[#This Row],[Mejor Precio]]),Tabla2[Proveedor]),""))} -> Imperio de la Limpieza | J9: =IF(Tabla4[[#This Row],[Artículo]]="","",IFERROR((Tabla4[[#This Row],[Precio Cotizado]]-Tabla4[[#This Row],[Últ. Precio]])/Tabla4[[#This Row],[Últ. Precio]],"")) -> 0 | K9: =IF(Tabla4[[#This Row],[Artículo]]="","",IFERROR(Tabla4[[#This Row],[Precio Cotizado]]-Tabla4[[#This Row],[Mejor Precio]],"")) -> 49.58 | L9: =IF(Tabla4[[#This Row],[Artículo]]="","",IFERROR(Tabla4[[#This Row],[Dif por Unidad]]*Tabla4[[#This Row],[Cantidad]],"")) -> 247.9 | M9: =IF(B9="","",IF(J9<0,"Más barato",IF(J9<=5%,"Dentro del rango",IF(J9<=15%,"Revisar","Precio alto")))) -> Dentro del rango | N9: =IF(Tabla4[[#This Row],[Artículo]]="","",IF(Tabla4[[#This Row],[Estado]]="Más barato","✓ Conviene comprar. Ahorro respecto al mejor precio.",IF(Tabla4[[#This Row],[Estado]]="Dentro del rango","✓ Precio dentro del rango habitual.",IF(Tabla4[[#This Row],[Estado]]="Revisar","⚠ Solicitar otra cotización.","🚨 Precio elevado. Negociar o buscar alternativa.")))) -> ✓ Precio dentro del rango habitual.
A10: 46227 | B10: Desodorante p/piso Lavanda | C10: 5 | E10: 2933.88 | F10: =IF(Tabla4[[#This Row],[Artículo]]="","",IFERROR(_xlfn.XLOOKUP(Tabla4[[#This Row],[Artículo]],Tabla2[Artículo],Tabla2[Precio Unitario ARS],"",0,-1),"")) -> 2933.88 | G10: =IF(Tabla4[[#This Row],[Artículo]]="","",IFERROR(_xlfn.XLOOKUP(Tabla4[[#This Row],[Artículo]],Tabla2[Artículo],Tabla2[Proveedor],"",0,-1),"")) -> Imperio de la Limpieza | H10: {=IF(Tabla4[[#This Row],[Artículo]]="","",IFERROR(MIN(_xlfn._xlws.FILTER(Tabla2[Precio Unitario ARS],Tabla2[Artículo]=Tabla4[[#This Row],[Artículo]])),""))} -> 561.982 | I10: {=IF(Tabla4[[#This Row],[Artículo]]="","",IFERROR(_xlfn.XLOOKUP(1,(Tabla2[Artículo]=Tabla4[[#This Row],[Artículo]])*(Tabla2[Precio Unitario ARS]=Tabla4[[#This Row],[Mejor Precio]]),Tabla2[Proveedor]),""))} -> Imperio de la Limpieza | J10: =IF(Tabla4[[#This Row],[Artículo]]="","",IFERROR((Tabla4[[#This Row],[Precio Cotizado]]-Tabla4[[#This Row],[Últ. Precio]])/Tabla4[[#This Row],[Últ. Precio]],"")) -> 0 | K10: =IF(Tabla4[[#This Row],[Artículo]]="","",IFERROR(Tabla4[[#This Row],[Precio Cotizado]]-Tabla4[[#This Row],[Mejor Precio]],"")) -> 2371.898 | L10: =IF(Tabla4[[#This Row],[Artículo]]="","",IFERROR(Tabla4[[#This Row],[Dif por Unidad]]*Tabla4[[#This Row],[Cantidad]],"")) -> 11859.49 | M10: =IF(B10="","",IF(J10<0,"Más barato",IF(J10<=5%,"Dentro del rango",IF(J10<=15%,"Revisar","Precio alto")))) -> Dentro del rango | N10: =IF(Tabla4[[#This Row],[Artículo]]="","",IF(Tabla4[[#This Row],[Estado]]="Más barato","✓ Conviene comprar. Ahorro respecto al mejor precio.",IF(Tabla4[[#This Row],[Estado]]="Dentro del rango","✓ Precio dentro del rango habitual.",IF(Tabla4[[#This Row],[Estado]]="Revisar","⚠ Solicitar otra cotización.","🚨 Precio elevado. Negociar o buscar alternativa.")))) -> ✓ Precio dentro del rango habitual.
A11: 46227 | B11: Guantes de limpieza (Talle L) | C11: 1 | E11: 2917.35 | F11: =IF(Tabla4[[#This Row],[Artículo]]="","",IFERROR(_xlfn.XLOOKUP(Tabla4[[#This Row],[Artículo]],Tabla2[Artículo],Tabla2[Precio Unitario ARS],"",0,-1),"")) -> 2917.35 | G11: =IF(Tabla4[[#This Row],[Artículo]]="","",IFERROR(_xlfn.XLOOKUP(Tabla4[[#This Row],[Artículo]],Tabla2[Artículo],Tabla2[Proveedor],"",0,-1),"")) -> Imperio de la Limpieza | H11: {=IF(Tabla4[[#This Row],[Artículo]]="","",IFERROR(MIN(_xlfn._xlws.FILTER(Tabla2[Precio Unitario ARS],Tabla2[Artículo]=Tabla4[[#This Row],[Artículo]])),""))} -> 2628.09 | I11: {=IF(Tabla4[[#This Row],[Artículo]]="","",IFERROR(_xlfn.XLOOKUP(1,(Tabla2[Artículo]=Tabla4[[#This Row],[Artículo]])*(Tabla2[Precio Unitario ARS]=Tabla4[[#This Row],[Mejor Precio]]),Tabla2[Proveedor]),""))} -> Imperio de la Limpieza | J11: =IF(Tabla4[[#This Row],[Artículo]]="","",IFERROR((Tabla4[[#This Row],[Precio Cotizado]]-Tabla4[[#This Row],[Últ. Precio]])/Tabla4[[#This Row],[Últ. Precio]],"")) -> 0 | K11: =IF(Tabla4[[#This Row],[Artículo]]="","",IFERROR(Tabla4[[#This Row],[Precio Cotizado]]-Tabla4[[#This Row],[Mejor Precio]],"")) -> 289.26 | L11: =IF(Tabla4[[#This Row],[Artículo]]="","",IFERROR(Tabla4[[#This Row],[Dif por Unidad]]*Tabla4[[#This Row],[Cantidad]],"")) -> 289.26 | M11: =IF(B11="","",IF(J11<0,"Más barato",IF(J11<=5%,"Dentro del rango",IF(J11<=15%,"Revisar","Precio alto")))) -> Dentro del rango | N11: =IF(Tabla4[[#This Row],[Artículo]]="","",IF(Tabla4[[#This Row],[Estado]]="Más barato","✓ Conviene comprar. Ahorro respecto al mejor precio.",IF(Tabla4[[#This Row],[Estado]]="Dentro del rango","✓ Precio dentro del rango habitual.",IF(Tabla4[[#This Row],[Estado]]="Revisar","⚠ Solicitar otra cotización.","🚨 Precio elevado. Negociar o buscar alternativa.")))) -> ✓ Precio dentro del rango habitual.
A12: 46227 | B12: Jabón líquido | C12: 1 | E12: 9008.23 | F12: =IF(Tabla4[[#This Row],[Artículo]]="","",IFERROR(_xlfn.XLOOKUP(Tabla4[[#This Row],[Artículo]],Tabla2[Artículo],Tabla2[Precio Unitario ARS],"",0,-1),"")) -> 9008.26 | G12: =IF(Tabla4[[#This Row],[Artículo]]="","",IFERROR(_xlfn.XLOOKUP(Tabla4[[#This Row],[Artículo]],Tabla2[Artículo],Tabla2[Proveedor],"",0,-1),"")) -> Imperio de la Limpieza | H12: {=IF(Tabla4[[#This Row],[Artículo]]="","",IFERROR(MIN(_xlfn._xlws.FILTER(Tabla2[Precio Unitario ARS],Tabla2[Artículo]=Tabla4[[#This Row],[Artículo]])),""))} -> 1692.56 | I12: {=IF(Tabla4[[#This Row],[Artículo]]="","",IFERROR(_xlfn.XLOOKUP(1,(Tabla2[Artículo]=Tabla4[[#This Row],[Artículo]])*(Tabla2[Precio Unitario ARS]=Tabla4[[#This Row],[Mejor Precio]]),Tabla2[Proveedor]),""))} -> Imperio de la Limpieza | J12: =IF(Tabla4[[#This Row],[Artículo]]="","",IFERROR((Tabla4[[#This Row],[Precio Cotizado]]-Tabla4[[#This Row],[Últ. Precio]])/Tabla4[[#This Row],[Últ. Precio]],"")) -> -3.3302769e-06 | K12: =IF(Tabla4[[#This Row],[Artículo]]="","",IFERROR(Tabla4[[#This Row],[Precio Cotizado]]-Tabla4[[#This Row],[Mejor Precio]],"")) -> 7315.67 | L12: =IF(Tabla4[[#This Row],[Artículo]]="","",IFERROR(Tabla4[[#This Row],[Dif por Unidad]]*Tabla4[[#This Row],[Cantidad]],"")) -> 7315.67 | M12: =IF(B12="","",IF(J12<0,"Más barato",IF(J12<=5%,"Dentro del rango",IF(J12<=15%,"Revisar","Precio alto")))) -> Más barato | N12: =IF(Tabla4[[#This Row],[Artículo]]="","",IF(Tabla4[[#This Row],[Estado]]="Más barato","✓ Conviene comprar. Ahorro respecto al mejor precio.",IF(Tabla4[[#This Row],[Estado]]="Dentro del rango","✓ Precio dentro del rango habitual.",IF(Tabla4[[#This Row],[Estado]]="Revisar","⚠ Solicitar otra cotización.","🚨 Precio elevado. Negociar o buscar alternativa.")))) -> ✓ Conviene comprar. Ahorro respecto al mejor precio.
A13: 46227 | B13: Detergente | C13: 3 | F13: =IF(Tabla4[[#This Row],[Artículo]]="","",IFERROR(_xlfn.XLOOKUP(Tabla4[[#This Row],[Artículo]],Tabla2[Artículo],Tabla2[Precio Unitario ARS],"",0,-1),"")) -> 9000 | G13: =IF(Tabla4[[#This Row],[Artículo]]="","",IFERROR(_xlfn.XLOOKUP(Tabla4[[#This Row],[Artículo]],Tabla2[Artículo],Tabla2[Proveedor],"",0,-1),"")) -> Imperio de la Limpieza | H13: {=IF(Tabla4[[#This Row],[Artículo]]="","",IFERROR(MIN(_xlfn._xlws.FILTER(Tabla2[Precio Unitario ARS],Tabla2[Artículo]=Tabla4[[#This Row],[Artículo]])),""))} -> 1647.932 | I13: {=IF(Tabla4[[#This Row],[Artículo]]="","",IFERROR(_xlfn.XLOOKUP(1,(Tabla2[Artículo]=Tabla4[[#This Row],[Artículo]])*(Tabla2[Precio Unitario ARS]=Tabla4[[#This Row],[Mejor Precio]]),Tabla2[Proveedor]),""))} -> Imperio de la Limpieza | J13: =IF(Tabla4[[#This Row],[Artículo]]="","",IFERROR((Tabla4[[#This Row],[Precio Cotizado]]-Tabla4[[#This Row],[Últ. Precio]])/Tabla4[[#This Row],[Últ. Precio]],"")) -> -1 | K13: =IF(Tabla4[[#This Row],[Artículo]]="","",IFERROR(Tabla4[[#This Row],[Precio Cotizado]]-Tabla4[[#This Row],[Mejor Precio]],"")) -> -1647.932 | L13: =IF(Tabla4[[#This Row],[Artículo]]="","",IFERROR(Tabla4[[#This Row],[Dif por Unidad]]*Tabla4[[#This Row],[Cantidad]],"")) -> -4943.796 | M13: =IF(B13="","",IF(J13<0,"Más barato",IF(J13<=5%,"Dentro del rango",IF(J13<=15%,"Revisar","Precio alto")))) -> Más barato | N13: =IF(Tabla4[[#This Row],[Artículo]]="","",IF(Tabla4[[#This Row],[Estado]]="Más barato","✓ Conviene comprar. Ahorro respecto al mejor precio.",IF(Tabla4[[#This Row],[Estado]]="Dentro del rango","✓ Precio dentro del rango habitual.",IF(Tabla4[[#This Row],[Estado]]="Revisar","⚠ Solicitar otra cotización.","🚨 Precio elevado. Negociar o buscar alternativa.")))) -> ✓ Conviene comprar. Ahorro respecto al mejor precio.
A14: 46227 | B14: Lavandina Líquida | C14: 2 | F14: =IF(Tabla4[[#This Row],[Artículo]]="","",IFERROR(_xlfn.XLOOKUP(Tabla4[[#This Row],[Artículo]],Tabla2[Artículo],Tabla2[Precio Unitario ARS],"",0,-1),"")) -> 3801.65 | G14: =IF(Tabla4[[#This Row],[Artículo]]="","",IFERROR(_xlfn.XLOOKUP(Tabla4[[#This Row],[Artículo]],Tabla2[Artículo],Tabla2[Proveedor],"",0,-1),"")) -> Imperio de la Limpieza | H14: {=IF(Tabla4[[#This Row],[Artículo]]="","",IFERROR(MIN(_xlfn._xlws.FILTER(Tabla2[Precio Unitario ARS],Tabla2[Artículo]=Tabla4[[#This Row],[Artículo]])),""))} -> 3801.65 | I14: {=IF(Tabla4[[#This Row],[Artículo]]="","",IFERROR(_xlfn.XLOOKUP(1,(Tabla2[Artículo]=Tabla4[[#This Row],[Artículo]])*(Tabla2[Precio Unitario ARS]=Tabla4[[#This Row],[Mejor Precio]]),Tabla2[Proveedor]),""))} -> Imperio de la Limpieza | J14: =IF(Tabla4[[#This Row],[Artículo]]="","",IFERROR((Tabla4[[#This Row],[Precio Cotizado]]-Tabla4[[#This Row],[Últ. Precio]])/Tabla4[[#This Row],[Últ. Precio]],"")) -> -1 | K14: =IF(Tabla4[[#This Row],[Artículo]]="","",IFERROR(Tabla4[[#This Row],[Precio Cotizado]]-Tabla4[[#This Row],[Mejor Precio]],"")) -> -3801.65 | L14: =IF(Tabla4[[#This Row],[Artículo]]="","",IFERROR(Tabla4[[#This Row],[Dif por Unidad]]*Tabla4[[#This Row],[Cantidad]],"")) -> -7603.3 | M14: =IF(B14="","",IF(J14<0,"Más barato",IF(J14<=5%,"Dentro del rango",IF(J14<=15%,"Revisar","Precio alto")))) -> Más barato | N14: =IF(Tabla4[[#This Row],[Artículo]]="","",IF(Tabla4[[#This Row],[Estado]]="Más barato","✓ Conviene comprar. Ahorro respecto al mejor precio.",IF(Tabla4[[#This Row],[Estado]]="Dentro del rango","✓ Precio dentro del rango habitual.",IF(Tabla4[[#This Row],[Estado]]="Revisar","⚠ Solicitar otra cotización.","🚨 Precio elevado. Negociar o buscar alternativa.")))) -> ✓ Conviene comprar. Ahorro respecto al mejor precio.
A15: 46227 | B15: Alcohol 96% | C15: 1 | F15: =IF(Tabla4[[#This Row],[Artículo]]="","",IFERROR(_xlfn.XLOOKUP(Tabla4[[#This Row],[Artículo]],Tabla2[Artículo],Tabla2[Precio Unitario ARS],"",0,-1),"")) -> 14380.16 | G15: =IF(Tabla4[[#This Row],[Artículo]]="","",IFERROR(_xlfn.XLOOKUP(Tabla4[[#This Row],[Artículo]],Tabla2[Artículo],Tabla2[Proveedor],"",0,-1),"")) -> Imperio de la Limpieza | H15: {=IF(Tabla4[[#This Row],[Artículo]]="","",IFERROR(MIN(_xlfn._xlws.FILTER(Tabla2[Precio Unitario ARS],Tabla2[Artículo]=Tabla4[[#This Row],[Artículo]])),""))} -> 14008.26 | I15: {=IF(Tabla4[[#This Row],[Artículo]]="","",IFERROR(_xlfn.XLOOKUP(1,(Tabla2[Artículo]=Tabla4[[#This Row],[Artículo]])*(Tabla2[Precio Unitario ARS]=Tabla4[[#This Row],[Mejor Precio]]),Tabla2[Proveedor]),""))} -> Imperio de la Limpieza | J15: =IF(Tabla4[[#This Row],[Artículo]]="","",IFERROR((Tabla4[[#This Row],[Precio Cotizado]]-Tabla4[[#This Row],[Últ. Precio]])/Tabla4[[#This Row],[Últ. Precio]],"")) -> -1 | K15: =IF(Tabla4[[#This Row],[Artículo]]="","",IFERROR(Tabla4[[#This Row],[Precio Cotizado]]-Tabla4[[#This Row],[Mejor Precio]],"")) -> -14008.26 | L15: =IF(Tabla4[[#This Row],[Artículo]]="","",IFERROR(Tabla4[[#This Row],[Dif por Unidad]]*Tabla4[[#This Row],[Cantidad]],"")) -> -14008.26 | M15: =IF(B15="","",IF(J15<0,"Más barato",IF(J15<=5%,"Dentro del rango",IF(J15<=15%,"Revisar","Precio alto")))) -> Más barato | N15: =IF(Tabla4[[#This Row],[Artículo]]="","",IF(Tabla4[[#This Row],[Estado]]="Más barato","✓ Conviene comprar. Ahorro respecto al mejor precio.",IF(Tabla4[[#This Row],[Estado]]="Dentro del rango","✓ Precio dentro del rango habitual.",IF(Tabla4[[#This Row],[Estado]]="Revisar","⚠ Solicitar otra cotización.","🚨 Precio elevado. Negociar o buscar alternativa.")))) -> ✓ Conviene comprar. Ahorro respecto al mejor precio.
A16: 46227 | B16: Escobillones | C16: 2 | F16: =IF(Tabla4[[#This Row],[Artículo]]="","",IFERROR(_xlfn.XLOOKUP(Tabla4[[#This Row],[Artículo]],Tabla2[Artículo],Tabla2[Precio Unitario ARS],"",0,-1),"")) -> 12851.23 | G16: =IF(Tabla4[[#This Row],[Artículo]]="","",IFERROR(_xlfn.XLOOKUP(Tabla4[[#This Row],[Artículo]],Tabla2[Artículo],Tabla2[Proveedor],"",0,-1),"")) -> Imperio de la Limpieza | H16: {=IF(Tabla4[[#This Row],[Artículo]]="","",IFERROR(MIN(_xlfn._xlws.FILTER(Tabla2[Precio Unitario ARS],Tabla2[Artículo]=Tabla4[[#This Row],[Artículo]])),""))} -> 12851.23 | I16: {=IF(Tabla4[[#This Row],[Artículo]]="","",IFERROR(_xlfn.XLOOKUP(1,(Tabla2[Artículo]=Tabla4[[#This Row],[Artículo]])*(Tabla2[Precio Unitario ARS]=Tabla4[[#This Row],[Mejor Precio]]),Tabla2[Proveedor]),""))} -> Imperio de la Limpieza | J16: =IF(Tabla4[[#This Row],[Artículo]]="","",IFERROR((Tabla4[[#This Row],[Precio Cotizado]]-Tabla4[[#This Row],[Últ. Precio]])/Tabla4[[#This Row],[Últ. Precio]],"")) -> -1 | K16: =IF(Tabla4[[#This Row],[Artículo]]="","",IFERROR(Tabla4[[#This Row],[Precio Cotizado]]-Tabla4[[#This Row],[Mejor Precio]],"")) -> -12851.23 | L16: =IF(Tabla4[[#This Row],[Artículo]]="","",IFERROR(Tabla4[[#This Row],[Dif por Unidad]]*Tabla4[[#This Row],[Cantidad]],"")) -> -25702.46 | M16: =IF(B16="","",IF(J16<0,"Más barato",IF(J16<=5%,"Dentro del rango",IF(J16<=15%,"Revisar","Precio alto")))) -> Más barato | N16: =IF(Tabla4[[#This Row],[Artículo]]="","",IF(Tabla4[[#This Row],[Estado]]="Más barato","✓ Conviene comprar. Ahorro respecto al mejor precio.",IF(Tabla4[[#This Row],[Estado]]="Dentro del rango","✓ Precio dentro del rango habitual.",IF(Tabla4[[#This Row],[Estado]]="Revisar","⚠ Solicitar otra cotización.","🚨 Precio elevado. Negociar o buscar alternativa.")))) -> ✓ Conviene comprar. Ahorro respecto al mejor precio.
A17: 46227 | B17: Rejilla | C17: 1 | F17: =IF(Tabla4[[#This Row],[Artículo]]="","",IFERROR(_xlfn.XLOOKUP(Tabla4[[#This Row],[Artículo]],Tabla2[Artículo],Tabla2[Precio Unitario ARS],"",0,-1),"")) -> 743.8 | G17: =IF(Tabla4[[#This Row],[Artículo]]="","",IFERROR(_xlfn.XLOOKUP(Tabla4[[#This Row],[Artículo]],Tabla2[Artículo],Tabla2[Proveedor],"",0,-1),"")) -> Imperio de la Limpieza | H17: {=IF(Tabla4[[#This Row],[Artículo]]="","",IFERROR(MIN(_xlfn._xlws.FILTER(Tabla2[Precio Unitario ARS],Tabla2[Artículo]=Tabla4[[#This Row],[Artículo]])),""))} -> 710.74 | I17: {=IF(Tabla4[[#This Row],[Artículo]]="","",IFERROR(_xlfn.XLOOKUP(1,(Tabla2[Artículo]=Tabla4[[#This Row],[Artículo]])*(Tabla2[Precio Unitario ARS]=Tabla4[[#This Row],[Mejor Precio]]),Tabla2[Proveedor]),""))} -> Imperio de la Limpieza | J17: =IF(Tabla4[[#This Row],[Artículo]]="","",IFERROR((Tabla4[[#This Row],[Precio Cotizado]]-Tabla4[[#This Row],[Últ. Precio]])/Tabla4[[#This Row],[Últ. Precio]],"")) -> -1 | K17: =IF(Tabla4[[#This Row],[Artículo]]="","",IFERROR(Tabla4[[#This Row],[Precio Cotizado]]-Tabla4[[#This Row],[Mejor Precio]],"")) -> -710.74 | L17: =IF(Tabla4[[#This Row],[Artículo]]="","",IFERROR(Tabla4[[#This Row],[Dif por Unidad]]*Tabla4[[#This Row],[Cantidad]],"")) -> -710.74 | M17: =IF(B17="","",IF(J17<0,"Más barato",IF(J17<=5%,"Dentro del rango",IF(J17<=15%,"Revisar","Precio alto")))) -> Más barato | N17: =IF(Tabla4[[#This Row],[Artículo]]="","",IF(Tabla4[[#This Row],[Estado]]="Más barato","✓ Conviene comprar. Ahorro respecto al mejor precio.",IF(Tabla4[[#This Row],[Estado]]="Dentro del rango","✓ Precio dentro del rango habitual.",IF(Tabla4[[#This Row],[Estado]]="Revisar","⚠ Solicitar otra cotización.","🚨 Precio elevado. Negociar o buscar alternativa.")))) -> ✓ Conviene comprar. Ahorro respecto al mejor precio.
A18: 46227 | B18: Trapo de piso | C18: 1 | F18: =IF(Tabla4[[#This Row],[Artículo]]="","",IFERROR(_xlfn.XLOOKUP(Tabla4[[#This Row],[Artículo]],Tabla2[Artículo],Tabla2[Precio Unitario ARS],"",0,-1),"")) -> 1661.15 | G18: =IF(Tabla4[[#This Row],[Artículo]]="","",IFERROR(_xlfn.XLOOKUP(Tabla4[[#This Row],[Artículo]],Tabla2[Artículo],Tabla2[Proveedor],"",0,-1),"")) -> Imperio de la Limpieza | H18: {=IF(Tabla4[[#This Row],[Artículo]]="","",IFERROR(MIN(_xlfn._xlws.FILTER(Tabla2[Precio Unitario ARS],Tabla2[Artículo]=Tabla4[[#This Row],[Artículo]])),""))} -> 1661.15 | I18: {=IF(Tabla4[[#This Row],[Artículo]]="","",IFERROR(_xlfn.XLOOKUP(1,(Tabla2[Artículo]=Tabla4[[#This Row],[Artículo]])*(Tabla2[Precio Unitario ARS]=Tabla4[[#This Row],[Mejor Precio]]),Tabla2[Proveedor]),""))} -> Imperio de la Limpieza | J18: =IF(Tabla4[[#This Row],[Artículo]]="","",IFERROR((Tabla4[[#This Row],[Precio Cotizado]]-Tabla4[[#This Row],[Últ. Precio]])/Tabla4[[#This Row],[Últ. Precio]],"")) -> -1 | K18: =IF(Tabla4[[#This Row],[Artículo]]="","",IFERROR(Tabla4[[#This Row],[Precio Cotizado]]-Tabla4[[#This Row],[Mejor Precio]],"")) -> -1661.15 | L18: =IF(Tabla4[[#This Row],[Artículo]]="","",IFERROR(Tabla4[[#This Row],[Dif por Unidad]]*Tabla4[[#This Row],[Cantidad]],"")) -> -1661.15 | M18: =IF(B18="","",IF(J18<0,"Más barato",IF(J18<=5%,"Dentro del rango",IF(J18<=15%,"Revisar","Precio alto")))) -> Más barato | N18: =IF(Tabla4[[#This Row],[Artículo]]="","",IF(Tabla4[[#This Row],[Estado]]="Más barato","✓ Conviene comprar. Ahorro respecto al mejor precio.",IF(Tabla4[[#This Row],[Estado]]="Dentro del rango","✓ Precio dentro del rango habitual.",IF(Tabla4[[#This Row],[Estado]]="Revisar","⚠ Solicitar otra cotización.","🚨 Precio elevado. Negociar o buscar alternativa.")))) -> ✓ Conviene comprar. Ahorro respecto al mejor precio.
A19: 46231 | B19: Bolsas Tubos x 100 mic | C19: 60 | D19: kg | E19: 7620 | F19: =IF(Tabla4[[#This Row],[Artículo]]="","",IFERROR(_xlfn.XLOOKUP(Tabla4[[#This Row],[Artículo]],Tabla2[Artículo],Tabla2[Precio Unitario ARS],"",0,-1),"")) -> 7620 | G19: =IF(Tabla4[[#This Row],[Artículo]]="","",IFERROR(_xlfn.XLOOKUP(Tabla4[[#This Row],[Artículo]],Tabla2[Artículo],Tabla2[Proveedor],"",0,-1),"")) -> Plásticos Aloha | H19: {=IF(Tabla4[[#This Row],[Artículo]]="","",IFERROR(MIN(_xlfn._xlws.FILTER(Tabla2[Precio Unitario ARS],Tabla2[Artículo]=Tabla4[[#This Row],[Artículo]])),""))} -> 7620 | I19: {=IF(Tabla4[[#This Row],[Artículo]]="","",IFERROR(_xlfn.XLOOKUP(1,(Tabla2[Artículo]=Tabla4[[#This Row],[Artículo]])*(Tabla2[Precio Unitario ARS]=Tabla4[[#This Row],[Mejor Precio]]),Tabla2[Proveedor]),""))} -> Plásticos Aloha | J19: =IF(Tabla4[[#This Row],[Artículo]]="","",IFERROR((Tabla4[[#This Row],[Precio Cotizado]]-Tabla4[[#This Row],[Últ. Precio]])/Tabla4[[#This Row],[Últ. Precio]],"")) -> 0 | K19: =IF(Tabla4[[#This Row],[Artículo]]="","",IFERROR(Tabla4[[#This Row],[Precio Cotizado]]-Tabla4[[#This Row],[Mejor Precio]],"")) -> 0 | L19: =IF(Tabla4[[#This Row],[Artículo]]="","",IFERROR(Tabla4[[#This Row],[Dif por Unidad]]*Tabla4[[#This Row],[Cantidad]],"")) -> 0 | M19: =IF(B19="","",IF(J19<0,"Más barato",IF(J19<=5%,"Dentro del rango",IF(J19<=15%,"Revisar","Precio alto")))) -> Dentro del rango | N19: =IF(Tabla4[[#This Row],[Artículo]]="","",IF(Tabla4[[#This Row],[Estado]]="Más barato","✓ Conviene comprar. Ahorro respecto al mejor precio.",IF(Tabla4[[#This Row],[Estado]]="Dentro del rango","✓ Precio dentro del rango habitual.",IF(Tabla4[[#This Row],[Estado]]="Revisar","⚠ Solicitar otra cotización.","🚨 Precio elevado. Negociar o buscar alternativa.")))) -> ✓ Precio dentro del rango habitual.
A20: 46231 | B20: Casco S/Arnes Blanco | E20: =5.9*1520 -> 8968 | F20: =IF(Tabla4[[#This Row],[Artículo]]="","",IFERROR(_xlfn.XLOOKUP(Tabla4[[#This Row],[Artículo]],Tabla2[Artículo],Tabla2[Precio Unitario ARS],"",0,-1),"")) -> 3961.1 | G20: =IF(Tabla4[[#This Row],[Artículo]]="","",IFERROR(_xlfn.XLOOKUP(Tabla4[[#This Row],[Artículo]],Tabla2[Artículo],Tabla2[Proveedor],"",0,-1),"")) -> Roguant | H20: {=IF(Tabla4[[#This Row],[Artículo]]="","",IFERROR(MIN(_xlfn._xlws.FILTER(Tabla2[Precio Unitario ARS],Tabla2[Artículo]=Tabla4[[#This Row],[Artículo]])),""))} -> 3961.1 | I20: {=IF(Tabla4[[#This Row],[Artículo]]="","",IFERROR(_xlfn.XLOOKUP(1,(Tabla2[Artículo]=Tabla4[[#This Row],[Artículo]])*(Tabla2[Precio Unitario ARS]=Tabla4[[#This Row],[Mejor Precio]]),Tabla2[Proveedor]),""))} -> Roguant | J20: =IF(Tabla4[[#This Row],[Artículo]]="","",IFERROR((Tabla4[[#This Row],[Precio Cotizado]]-Tabla4[[#This Row],[Últ. Precio]])/Tabla4[[#This Row],[Últ. Precio]],"")) -> 1.2640176 | K20: =IF(Tabla4[[#This Row],[Artículo]]="","",IFERROR(Tabla4[[#This Row],[Precio Cotizado]]-Tabla4[[#This Row],[Mejor Precio]],"")) -> 5006.9 | L20: =IF(Tabla4[[#This Row],[Artículo]]="","",IFERROR(Tabla4[[#This Row],[Dif por Unidad]]*Tabla4[[#This Row],[Cantidad]],"")) -> 0 | M20: =IF(B20="","",IF(J20<0,"Más barato",IF(J20<=5%,"Dentro del rango",IF(J20<=15%,"Revisar","Precio alto")))) -> Precio alto | N20: =IF(Tabla4[[#This Row],[Artículo]]="","",IF(Tabla4[[#This Row],[Estado]]="Más barato","✓ Conviene comprar. Ahorro respecto al mejor precio.",IF(Tabla4[[#This Row],[Estado]]="Dentro del rango","✓ Precio dentro del rango habitual.",IF(Tabla4[[#This Row],[Estado]]="Revisar","⚠ Solicitar otra cotización.","🚨 Precio elevado. Negociar o buscar alternativa.")))) -> 🚨 Precio elevado. Negociar o buscar alternativa.
A21: 46231 | B21: Arnes P/Casco | E21: =8.7*1520 -> 13224 | F21: =IF(Tabla4[[#This Row],[Artículo]]="","",IFERROR(_xlfn.XLOOKUP(Tabla4[[#This Row],[Artículo]],Tabla2[Artículo],Tabla2[Precio Unitario ARS],"",0,-1),"")) -> 6306.3 | G21: =IF(Tabla4[[#This Row],[Artículo]]="","",IFERROR(_xlfn.XLOOKUP(Tabla4[[#This Row],[Artículo]],Tabla2[Artículo],Tabla2[Proveedor],"",0,-1),"")) -> Roguant | H21: {=IF(Tabla4[[#This Row],[Artículo]]="","",IFERROR(MIN(_xlfn._xlws.FILTER(Tabla2[Precio Unitario ARS],Tabla2[Artículo]=Tabla4[[#This Row],[Artículo]])),""))} -> 6306.3 | I21: {=IF(Tabla4[[#This Row],[Artículo]]="","",IFERROR(_xlfn.XLOOKUP(1,(Tabla2[Artículo]=Tabla4[[#This Row],[Artículo]])*(Tabla2[Precio Unitario ARS]=Tabla4[[#This Row],[Mejor Precio]]),Tabla2[Proveedor]),""))} -> Roguant | J21: =IF(Tabla4[[#This Row],[Artículo]]="","",IFERROR((Tabla4[[#This Row],[Precio Cotizado]]-Tabla4[[#This Row],[Últ. Precio]])/Tabla4[[#This Row],[Últ. Precio]],"")) -> 1.0969507 | K21: =IF(Tabla4[[#This Row],[Artículo]]="","",IFERROR(Tabla4[[#This Row],[Precio Cotizado]]-Tabla4[[#This Row],[Mejor Precio]],"")) -> 6917.7 | L21: =IF(Tabla4[[#This Row],[Artículo]]="","",IFERROR(Tabla4[[#This Row],[Dif por Unidad]]*Tabla4[[#This Row],[Cantidad]],"")) -> 0 | M21: =IF(B21="","",IF(J21<0,"Más barato",IF(J21<=5%,"Dentro del rango",IF(J21<=15%,"Revisar","Precio alto")))) -> Precio alto | N21: =IF(Tabla4[[#This Row],[Artículo]]="","",IF(Tabla4[[#This Row],[Estado]]="Más barato","✓ Conviene comprar. Ahorro respecto al mejor precio.",IF(Tabla4[[#This Row],[Estado]]="Dentro del rango","✓ Precio dentro del rango habitual.",IF(Tabla4[[#This Row],[Estado]]="Revisar","⚠ Solicitar otra cotización.","🚨 Precio elevado. Negociar o buscar alternativa.")))) -> 🚨 Precio elevado. Negociar o buscar alternativa.
A22: 46231 | B22: Protector Auditivo | E22: =33.7*1520 -> 51224 | F22: =IF(Tabla4[[#This Row],[Artículo]]="","",IFERROR(_xlfn.XLOOKUP(Tabla4[[#This Row],[Artículo]],Tabla2[Artículo],Tabla2[Precio Unitario ARS],"",0,-1),"")) | G22: =IF(Tabla4[[#This Row],[Artículo]]="","",IFERROR(_xlfn.XLOOKUP(Tabla4[[#This Row],[Artículo]],Tabla2[Artículo],Tabla2[Proveedor],"",0,-1),"")) | H22: {=IF(Tabla4[[#This Row],[Artículo]]="","",IFERROR(MIN(_xlfn._xlws.FILTER(Tabla2[Precio Unitario ARS],Tabla2[Artículo]=Tabla4[[#This Row],[Artículo]])),""))} | I22: {=IF(Tabla4[[#This Row],[Artículo]]="","",IFERROR(_xlfn.XLOOKUP(1,(Tabla2[Artículo]=Tabla4[[#This Row],[Artículo]])*(Tabla2[Precio Unitario ARS]=Tabla4[[#This Row],[Mejor Precio]]),Tabla2[Proveedor]),""))} | J22: =IF(Tabla4[[#This Row],[Artículo]]="","",IFERROR((Tabla4[[#This Row],[Precio Cotizado]]-Tabla4[[#This Row],[Últ. Precio]])/Tabla4[[#This Row],[Últ. Precio]],"")) | K22: =IF(Tabla4[[#This Row],[Artículo]]="","",IFERROR(Tabla4[[#This Row],[Precio Cotizado]]-Tabla4[[#This Row],[Mejor Precio]],"")) | L22: =IF(Tabla4[[#This Row],[Artículo]]="","",IFERROR(Tabla4[[#This Row],[Dif por Unidad]]*Tabla4[[#This Row],[Cantidad]],"")) | M22: =IF(B22="","",IF(J22<0,"Más barato",IF(J22<=5%,"Dentro del rango",IF(J22<=15%,"Revisar","Precio alto")))) -> Precio alto | N22: =IF(Tabla4[[#This Row],[Artículo]]="","",IF(Tabla4[[#This Row],[Estado]]="Más barato","✓ Conviene comprar. Ahorro respecto al mejor precio.",IF(Tabla4[[#This Row],[Estado]]="Dentro del rango","✓ Precio dentro del rango habitual.",IF(Tabla4[[#This Row],[Estado]]="Revisar","⚠ Solicitar otra cotización.","🚨 Precio elevado. Negociar o buscar alternativa.")))) -> 🚨 Precio elevado. Negociar o buscar alternativa.
A23: 46231 | B23: Protector Auditivo | E23: =28.8*1520 -> 43776 | F23: =IF(Tabla4[[#This Row],[Artículo]]="","",IFERROR(_xlfn.XLOOKUP(Tabla4[[#This Row],[Artículo]],Tabla2[Artículo],Tabla2[Precio Unitario ARS],"",0,-1),"")) | G23: =IF(Tabla4[[#This Row],[Artículo]]="","",IFERROR(_xlfn.XLOOKUP(Tabla4[[#This Row],[Artículo]],Tabla2[Artículo],Tabla2[Proveedor],"",0,-1),"")) | H23: {=IF(Tabla4[[#This Row],[Artículo]]="","",IFERROR(MIN(_xlfn._xlws.FILTER(Tabla2[Precio Unitario ARS],Tabla2[Artículo]=Tabla4[[#This Row],[Artículo]])),""))} | I23: {=IF(Tabla4[[#This Row],[Artículo]]="","",IFERROR(_xlfn.XLOOKUP(1,(Tabla2[Artículo]=Tabla4[[#This Row],[Artículo]])*(Tabla2[Precio Unitario ARS]=Tabla4[[#This Row],[Mejor Precio]]),Tabla2[Proveedor]),""))} | J23: =IF(Tabla4[[#This Row],[Artículo]]="","",IFERROR((Tabla4[[#This Row],[Precio Cotizado]]-Tabla4[[#This Row],[Últ. Precio]])/Tabla4[[#This Row],[Últ. Precio]],"")) | K23: =IF(Tabla4[[#This Row],[Artículo]]="","",IFERROR(Tabla4[[#This Row],[Precio Cotizado]]-Tabla4[[#This Row],[Mejor Precio]],"")) | L23: =IF(Tabla4[[#This Row],[Artículo]]="","",IFERROR(Tabla4[[#This Row],[Dif por Unidad]]*Tabla4[[#This Row],[Cantidad]],"")) | M23: =IF(B23="","",IF(J23<0,"Más barato",IF(J23<=5%,"Dentro del rango",IF(J23<=15%,"Revisar","Precio alto")))) -> Precio alto | N23: =IF(Tabla4[[#This Row],[Artículo]]="","",IF(Tabla4[[#This Row],[Estado]]="Más barato","✓ Conviene comprar. Ahorro respecto al mejor precio.",IF(Tabla4[[#This Row],[Estado]]="Dentro del rango","✓ Precio dentro del rango habitual.",IF(Tabla4[[#This Row],[Estado]]="Revisar","⚠ Solicitar otra cotización.","🚨 Precio elevado. Negociar o buscar alternativa.")))) -> 🚨 Precio elevado. Negociar o buscar alternativa.
A24: 46231 | B24: Guantes Poli (Tactil) 8# | E24: =0.5*1520 -> 760 | F24: =IF(Tabla4[[#This Row],[Artículo]]="","",IFERROR(_xlfn.XLOOKUP(Tabla4[[#This Row],[Artículo]],Tabla2[Artículo],Tabla2[Precio Unitario ARS],"",0,-1),"")) -> 651.15 | G24: =IF(Tabla4[[#This Row],[Artículo]]="","",IFERROR(_xlfn.XLOOKUP(Tabla4[[#This Row],[Artículo]],Tabla2[Artículo],Tabla2[Proveedor],"",0,-1),"")) -> Tech Safe | H24: {=IF(Tabla4[[#This Row],[Artículo]]="","",IFERROR(MIN(_xlfn._xlws.FILTER(Tabla2[Precio Unitario ARS],Tabla2[Artículo]=Tabla4[[#This Row],[Artículo]])),""))} -> 600 | I24: {=IF(Tabla4[[#This Row],[Artículo]]="","",IFERROR(_xlfn.XLOOKUP(1,(Tabla2[Artículo]=Tabla4[[#This Row],[Artículo]])*(Tabla2[Precio Unitario ARS]=Tabla4[[#This Row],[Mejor Precio]]),Tabla2[Proveedor]),""))} -> Tech Safe | J24: =IF(Tabla4[[#This Row],[Artículo]]="","",IFERROR((Tabla4[[#This Row],[Precio Cotizado]]-Tabla4[[#This Row],[Últ. Precio]])/Tabla4[[#This Row],[Últ. Precio]],"")) -> 0.16716578 | K24: =IF(Tabla4[[#This Row],[Artículo]]="","",IFERROR(Tabla4[[#This Row],[Precio Cotizado]]-Tabla4[[#This Row],[Mejor Precio]],"")) -> 160 | L24: =IF(Tabla4[[#This Row],[Artículo]]="","",IFERROR(Tabla4[[#This Row],[Dif por Unidad]]*Tabla4[[#This Row],[Cantidad]],"")) -> 0 | M24: =IF(B24="","",IF(J24<0,"Más barato",IF(J24<=5%,"Dentro del rango",IF(J24<=15%,"Revisar","Precio alto")))) -> Precio alto | N24: =IF(Tabla4[[#This Row],[Artículo]]="","",IF(Tabla4[[#This Row],[Estado]]="Más barato","✓ Conviene comprar. Ahorro respecto al mejor precio.",IF(Tabla4[[#This Row],[Estado]]="Dentro del rango","✓ Precio dentro del rango habitual.",IF(Tabla4[[#This Row],[Estado]]="Revisar","⚠ Solicitar otra cotización.","🚨 Precio elevado. Negociar o buscar alternativa.")))) -> 🚨 Precio elevado. Negociar o buscar alternativa.
A25: 46231 | B25: Guantes Poli (Tactil) 10# | E25: =0.5*1520 -> 760 | F25: =IF(Tabla4[[#This Row],[Artículo]]="","",IFERROR(_xlfn.XLOOKUP(Tabla4[[#This Row],[Artículo]],Tabla2[Artículo],Tabla2[Precio Unitario ARS],"",0,-1),"")) -> 651.15 | G25: =IF(Tabla4[[#This Row],[Artículo]]="","",IFERROR(_xlfn.XLOOKUP(Tabla4[[#This Row],[Artículo]],Tabla2[Artículo],Tabla2[Proveedor],"",0,-1),"")) -> Tech Safe | H25: {=IF(Tabla4[[#This Row],[Artículo]]="","",IFERROR(MIN(_xlfn._xlws.FILTER(Tabla2[Precio Unitario ARS],Tabla2[Artículo]=Tabla4[[#This Row],[Artículo]])),""))} -> 600 | I25: {=IF(Tabla4[[#This Row],[Artículo]]="","",IFERROR(_xlfn.XLOOKUP(1,(Tabla2[Artículo]=Tabla4[[#This Row],[Artículo]])*(Tabla2[Precio Unitario ARS]=Tabla4[[#This Row],[Mejor Precio]]),Tabla2[Proveedor]),""))} -> Tech Safe | J25: =IF(Tabla4[[#This Row],[Artículo]]="","",IFERROR((Tabla4[[#This Row],[Precio Cotizado]]-Tabla4[[#This Row],[Últ. Precio]])/Tabla4[[#This Row],[Últ. Precio]],"")) -> 0.16716578 | K25: =IF(Tabla4[[#This Row],[Artículo]]="","",IFERROR(Tabla4[[#This Row],[Precio Cotizado]]-Tabla4[[#This Row],[Mejor Precio]],"")) -> 160 | L25: =IF(Tabla4[[#This Row],[Artículo]]="","",IFERROR(Tabla4[[#This Row],[Dif por Unidad]]*Tabla4[[#This Row],[Cantidad]],"")) -> 0 | M25: =IF(B25="","",IF(J25<0,"Más barato",IF(J25<=5%,"Dentro del rango",IF(J25<=15%,"Revisar","Precio alto")))) -> Precio alto | N25: =IF(Tabla4[[#This Row],[Artículo]]="","",IF(Tabla4[[#This Row],[Estado]]="Más barato","✓ Conviene comprar. Ahorro respecto al mejor precio.",IF(Tabla4[[#This Row],[Estado]]="Dentro del rango","✓ Precio dentro del rango habitual.",IF(Tabla4[[#This Row],[Estado]]="Revisar","⚠ Solicitar otra cotización.","🚨 Precio elevado. Negociar o buscar alternativa.")))) -> 🚨 Precio elevado. Negociar o buscar alternativa.
A26: 46231 | B26: Guantes Dyne 5 | E26: =3.22*1520 -> 4894.4 | F26: =IF(Tabla4[[#This Row],[Artículo]]="","",IFERROR(_xlfn.XLOOKUP(Tabla4[[#This Row],[Artículo]],Tabla2[Artículo],Tabla2[Precio Unitario ARS],"",0,-1),"")) -> 4482 | G26: =IF(Tabla4[[#This Row],[Artículo]]="","",IFERROR(_xlfn.XLOOKUP(Tabla4[[#This Row],[Artículo]],Tabla2[Artículo],Tabla2[Proveedor],"",0,-1),"")) -> Tech Safe | H26: {=IF(Tabla4[[#This Row],[Artículo]]="","",IFERROR(MIN(_xlfn._xlws.FILTER(Tabla2[Precio Unitario ARS],Tabla2[Artículo]=Tabla4[[#This Row],[Artículo]])),""))} -> 4147 | I26: {=IF(Tabla4[[#This Row],[Artículo]]="","",IFERROR(_xlfn.XLOOKUP(1,(Tabla2[Artículo]=Tabla4[[#This Row],[Artículo]])*(Tabla2[Precio Unitario ARS]=Tabla4[[#This Row],[Mejor Precio]]),Tabla2[Proveedor]),""))} -> Roguant | J26: =IF(Tabla4[[#This Row],[Artículo]]="","",IFERROR((Tabla4[[#This Row],[Precio Cotizado]]-Tabla4[[#This Row],[Últ. Precio]])/Tabla4[[#This Row],[Últ. Precio]],"")) -> 0.092012494 | K26: =IF(Tabla4[[#This Row],[Artículo]]="","",IFERROR(Tabla4[[#This Row],[Precio Cotizado]]-Tabla4[[#This Row],[Mejor Precio]],"")) -> 747.4 | L26: =IF(Tabla4[[#This Row],[Artículo]]="","",IFERROR(Tabla4[[#This Row],[Dif por Unidad]]*Tabla4[[#This Row],[Cantidad]],"")) -> 0 | M26: =IF(B26="","",IF(J26<0,"Más barato",IF(J26<=5%,"Dentro del rango",IF(J26<=15%,"Revisar","Precio alto")))) -> Revisar | N26: =IF(Tabla4[[#This Row],[Artículo]]="","",IF(Tabla4[[#This Row],[Estado]]="Más barato","✓ Conviene comprar. Ahorro respecto al mejor precio.",IF(Tabla4[[#This Row],[Estado]]="Dentro del rango","✓ Precio dentro del rango habitual.",IF(Tabla4[[#This Row],[Estado]]="Revisar","⚠ Solicitar otra cotización.","🚨 Precio elevado. Negociar o buscar alternativa.")))) -> ⚠ Solicitar otra cotización.
B27: Arandela Plana Zinc. 1/2" | E27: 3840.7 | F27: =IF(Tabla4[[#This Row],[Artículo]]="","",IFERROR(_xlfn.XLOOKUP(Tabla4[[#This Row],[Artículo]],Tabla2[Artículo],Tabla2[Precio Unitario ARS],"",0,-1),"")) | G27: =IF(Tabla4[[#This Row],[Artículo]]="","",IFERROR(_xlfn.XLOOKUP(Tabla4[[#This Row],[Artículo]],Tabla2[Artículo],Tabla2[Proveedor],"",0,-1),"")) | H27: {=IF(Tabla4[[#This Row],[Artículo]]="","",IFERROR(MIN(_xlfn._xlws.FILTER(Tabla2[Precio Unitario ARS],Tabla2[Artículo]=Tabla4[[#This Row],[Artículo]])),""))} | I27: {=IF(Tabla4[[#This Row],[Artículo]]="","",IFERROR(_xlfn.XLOOKUP(1,(Tabla2[Artículo]=Tabla4[[#This Row],[Artículo]])*(Tabla2[Precio Unitario ARS]=Tabla4[[#This Row],[Mejor Precio]]),Tabla2[Proveedor]),""))} | J27: =IF(Tabla4[[#This Row],[Artículo]]="","",IFERROR((Tabla4[[#This Row],[Precio Cotizado]]-Tabla4[[#This Row],[Últ. Precio]])/Tabla4[[#This Row],[Últ. Precio]],"")) | K27: =IF(Tabla4[[#This Row],[Artículo]]="","",IFERROR(Tabla4[[#This Row],[Precio Cotizado]]-Tabla4[[#This Row],[Mejor Precio]],"")) | L27: =IF(Tabla4[[#This Row],[Artículo]]="","",IFERROR(Tabla4[[#This Row],[Dif por Unidad]]*Tabla4[[#This Row],[Cantidad]],"")) | M27: =IF(B27="","",IF(J27<0,"Más barato",IF(J27<=5%,"Dentro del rango",IF(J27<=15%,"Revisar","Precio alto")))) -> Precio alto | N27: =IF(Tabla4[[#This Row],[Artículo]]="","",IF(Tabla4[[#This Row],[Estado]]="Más barato","✓ Conviene comprar. Ahorro respecto al mejor precio.",IF(Tabla4[[#This Row],[Estado]]="Dentro del rango","✓ Precio dentro del rango habitual.",IF(Tabla4[[#This Row],[Estado]]="Revisar","⚠ Solicitar otra cotización.","🚨 Precio elevado. Negociar o buscar alternativa.")))) -> 🚨 Precio elevado. Negociar o buscar alternativa.
B28: Arandela Plana Zinc. 1/4" | E28: 4450 | F28: =IF(Tabla4[[#This Row],[Artículo]]="","",IFERROR(_xlfn.XLOOKUP(Tabla4[[#This Row],[Artículo]],Tabla2[Artículo],Tabla2[Precio Unitario ARS],"",0,-1),"")) -> 4800 | G28: =IF(Tabla4[[#This Row],[Artículo]]="","",IFERROR(_xlfn.XLOOKUP(Tabla4[[#This Row],[Artículo]],Tabla2[Artículo],Tabla2[Proveedor],"",0,-1),"")) -> Disur | H28: {=IF(Tabla4[[#This Row],[Artículo]]="","",IFERROR(MIN(_xlfn._xlws.FILTER(Tabla2[Precio Unitario ARS],Tabla2[Artículo]=Tabla4[[#This Row],[Artículo]])),""))} -> 4800 | I28: {=IF(Tabla4[[#This Row],[Artículo]]="","",IFERROR(_xlfn.XLOOKUP(1,(Tabla2[Artículo]=Tabla4[[#This Row],[Artículo]])*(Tabla2[Precio Unitario ARS]=Tabla4[[#This Row],[Mejor Precio]]),Tabla2[Proveedor]),""))} -> Disur | J28: =IF(Tabla4[[#This Row],[Artículo]]="","",IFERROR((Tabla4[[#This Row],[Precio Cotizado]]-Tabla4[[#This Row],[Últ. Precio]])/Tabla4[[#This Row],[Últ. Precio]],"")) -> -0.072916667 | K28: =IF(Tabla4[[#This Row],[Artículo]]="","",IFERROR(Tabla4[[#This Row],[Precio Cotizado]]-Tabla4[[#This Row],[Mejor Precio]],"")) -> -350 | L28: =IF(Tabla4[[#This Row],[Artículo]]="","",IFERROR(Tabla4[[#This Row],[Dif por Unidad]]*Tabla4[[#This Row],[Cantidad]],"")) -> 0 | M28: =IF(B28="","",IF(J28<0,"Más barato",IF(J28<=5%,"Dentro del rango",IF(J28<=15%,"Revisar","Precio alto")))) -> Más barato | N28: =IF(Tabla4[[#This Row],[Artículo]]="","",IF(Tabla4[[#This Row],[Estado]]="Más barato","✓ Conviene comprar. Ahorro respecto al mejor precio.",IF(Tabla4[[#This Row],[Estado]]="Dentro del rango","✓ Precio dentro del rango habitual.",IF(Tabla4[[#This Row],[Estado]]="Revisar","⚠ Solicitar otra cotización.","🚨 Precio elevado. Negociar o buscar alternativa.")))) -> ✓ Conviene comprar. Ahorro respecto al mejor precio.
B29: Arandela Plana Zinc. 3/8" | E29: 4020 | F29: =IF(Tabla4[[#This Row],[Artículo]]="","",IFERROR(_xlfn.XLOOKUP(Tabla4[[#This Row],[Artículo]],Tabla2[Artículo],Tabla2[Precio Unitario ARS],"",0,-1),"")) -> 4185 | G29: =IF(Tabla4[[#This Row],[Artículo]]="","",IFERROR(_xlfn.XLOOKUP(Tabla4[[#This Row],[Artículo]],Tabla2[Artículo],Tabla2[Proveedor],"",0,-1),"")) -> Disur | H29: {=IF(Tabla4[[#This Row],[Artículo]]="","",IFERROR(MIN(_xlfn._xlws.FILTER(Tabla2[Precio Unitario ARS],Tabla2[Artículo]=Tabla4[[#This Row],[Artículo]])),""))} -> 4185 | I29: {=IF(Tabla4[[#This Row],[Artículo]]="","",IFERROR(_xlfn.XLOOKUP(1,(Tabla2[Artículo]=Tabla4[[#This Row],[Artículo]])*(Tabla2[Precio Unitario ARS]=Tabla4[[#This Row],[Mejor Precio]]),Tabla2[Proveedor]),""))} -> Disur | J29: =IF(Tabla4[[#This Row],[Artículo]]="","",IFERROR((Tabla4[[#This Row],[Precio Cotizado]]-Tabla4[[#This Row],[Últ. Precio]])/Tabla4[[#This Row],[Últ. Precio]],"")) -> -0.039426523 | K29: =IF(Tabla4[[#This Row],[Artículo]]="","",IFERROR(Tabla4[[#This Row],[Precio Cotizado]]-Tabla4[[#This Row],[Mejor Precio]],"")) -> -165 | L29: =IF(Tabla4[[#This Row],[Artículo]]="","",IFERROR(Tabla4[[#This Row],[Dif por Unidad]]*Tabla4[[#This Row],[Cantidad]],"")) -> 0 | M29: =IF(B29="","",IF(J29<0,"Más barato",IF(J29<=5%,"Dentro del rango",IF(J29<=15%,"Revisar","Precio alto")))) -> Más barato | N29: =IF(Tabla4[[#This Row],[Artículo]]="","",IF(Tabla4[[#This Row],[Estado]]="Más barato","✓ Conviene comprar. Ahorro respecto al mejor precio.",IF(Tabla4[[#This Row],[Estado]]="Dentro del rango","✓ Precio dentro del rango habitual.",IF(Tabla4[[#This Row],[Estado]]="Revisar","⚠ Solicitar otra cotización.","🚨 Precio elevado. Negociar o buscar alternativa.")))) -> ✓ Conviene comprar. Ahorro respecto al mejor precio.
B30: Arandela Plana Zinc. 5/16" | E30: 4550.9 | F30: =IF(Tabla4[[#This Row],[Artículo]]="","",IFERROR(_xlfn.XLOOKUP(Tabla4[[#This Row],[Artículo]],Tabla2[Artículo],Tabla2[Precio Unitario ARS],"",0,-1),"")) -> 4890 | G30: =IF(Tabla4[[#This Row],[Artículo]]="","",IFERROR(_xlfn.XLOOKUP(Tabla4[[#This Row],[Artículo]],Tabla2[Artículo],Tabla2[Proveedor],"",0,-1),"")) -> Disur | H30: {=IF(Tabla4[[#This Row],[Artículo]]="","",IFERROR(MIN(_xlfn._xlws.FILTER(Tabla2[Precio Unitario ARS],Tabla2[Artículo]=Tabla4[[#This Row],[Artículo]])),""))} -> 4890 | I30: {=IF(Tabla4[[#This Row],[Artículo]]="","",IFERROR(_xlfn.XLOOKUP(1,(Tabla2[Artículo]=Tabla4[[#This Row],[Artículo]])*(Tabla2[Precio Unitario ARS]=Tabla4[[#This Row],[Mejor Precio]]),Tabla2[Proveedor]),""))} -> Disur | J30: =IF(Tabla4[[#This Row],[Artículo]]="","",IFERROR((Tabla4[[#This Row],[Precio Cotizado]]-Tabla4[[#This Row],[Últ. Precio]])/Tabla4[[#This Row],[Últ. Precio]],"")) -> -0.069345603 | K30: =IF(Tabla4[[#This Row],[Artículo]]="","",IFERROR(Tabla4[[#This Row],[Precio Cotizado]]-Tabla4[[#This Row],[Mejor Precio]],"")) -> -339.1 | L30: =IF(Tabla4[[#This Row],[Artículo]]="","",IFERROR(Tabla4[[#This Row],[Dif por Unidad]]*Tabla4[[#This Row],[Cantidad]],"")) -> 0 | M30: =IF(B30="","",IF(J30<0,"Más barato",IF(J30<=5%,"Dentro del rango",IF(J30<=15%,"Revisar","Precio alto")))) -> Más barato | N30: =IF(Tabla4[[#This Row],[Artículo]]="","",IF(Tabla4[[#This Row],[Estado]]="Más barato","✓ Conviene comprar. Ahorro respecto al mejor precio.",IF(Tabla4[[#This Row],[Estado]]="Dentro del rango","✓ Precio dentro del rango habitual.",IF(Tabla4[[#This Row],[Estado]]="Revisar","⚠ Solicitar otra cotización.","🚨 Precio elevado. Negociar o buscar alternativa.")))) -> ✓ Conviene comprar. Ahorro respecto al mejor precio.
B31: Tor. Punta Mecha 8 x 9/16 | E31: 17 | F31: =IF(Tabla4[[#This Row],[Artículo]]="","",IFERROR(_xlfn.XLOOKUP(Tabla4[[#This Row],[Artículo]],Tabla2[Artículo],Tabla2[Precio Unitario ARS],"",0,-1),"")) | G31: =IF(Tabla4[[#This Row],[Artículo]]="","",IFERROR(_xlfn.XLOOKUP(Tabla4[[#This Row],[Artículo]],Tabla2[Artículo],Tabla2[Proveedor],"",0,-1),"")) | H31: {=IF(Tabla4[[#This Row],[Artículo]]="","",IFERROR(MIN(_xlfn._xlws.FILTER(Tabla2[Precio Unitario ARS],Tabla2[Artículo]=Tabla4[[#This Row],[Artículo]])),""))} | I31: {=IF(Tabla4[[#This Row],[Artículo]]="","",IFERROR(_xlfn.XLOOKUP(1,(Tabla2[Artículo]=Tabla4[[#This Row],[Artículo]])*(Tabla2[Precio Unitario ARS]=Tabla4[[#This Row],[Mejor Precio]]),Tabla2[Proveedor]),""))} | J31: =IF(Tabla4[[#This Row],[Artículo]]="","",IFERROR((Tabla4[[#This Row],[Precio Cotizado]]-Tabla4[[#This Row],[Últ. Precio]])/Tabla4[[#This Row],[Últ. Precio]],"")) | K31: =IF(Tabla4[[#This Row],[Artículo]]="","",IFERROR(Tabla4[[#This Row],[Precio Cotizado]]-Tabla4[[#This Row],[Mejor Precio]],"")) | L31: =IF(Tabla4[[#This Row],[Artículo]]="","",IFERROR(Tabla4[[#This Row],[Dif por Unidad]]*Tabla4[[#This Row],[Cantidad]],"")) | M31: =IF(B31="","",IF(J31<0,"Más barato",IF(J31<=5%,"Dentro del rango",IF(J31<=15%,"Revisar","Precio alto")))) -> Precio alto | N31: =IF(Tabla4[[#This Row],[Artículo]]="","",IF(Tabla4[[#This Row],[Estado]]="Más barato","✓ Conviene comprar. Ahorro respecto al mejor precio.",IF(Tabla4[[#This Row],[Estado]]="Dentro del rango","✓ Precio dentro del rango habitual.",IF(Tabla4[[#This Row],[Estado]]="Revisar","⚠ Solicitar otra cotización.","🚨 Precio elevado. Negociar o buscar alternativa.")))) -> 🚨 Precio elevado. Negociar o buscar alternativa.
B32: Tuerca Zinc. 1/2" | E32: 60 | F32: =IF(Tabla4[[#This Row],[Artículo]]="","",IFERROR(_xlfn.XLOOKUP(Tabla4[[#This Row],[Artículo]],Tabla2[Artículo],Tabla2[Precio Unitario ARS],"",0,-1),"")) | G32: =IF(Tabla4[[#This Row],[Artículo]]="","",IFERROR(_xlfn.XLOOKUP(Tabla4[[#This Row],[Artículo]],Tabla2[Artículo],Tabla2[Proveedor],"",0,-1),"")) | H32: {=IF(Tabla4[[#This Row],[Artículo]]="","",IFERROR(MIN(_xlfn._xlws.FILTER(Tabla2[Precio Unitario ARS],Tabla2[Artículo]=Tabla4[[#This Row],[Artículo]])),""))} | I32: {=IF(Tabla4[[#This Row],[Artículo]]="","",IFERROR(_xlfn.XLOOKUP(1,(Tabla2[Artículo]=Tabla4[[#This Row],[Artículo]])*(Tabla2[Precio Unitario ARS]=Tabla4[[#This Row],[Mejor Precio]]),Tabla2[Proveedor]),""))} | J32: =IF(Tabla4[[#This Row],[Artículo]]="","",IFERROR((Tabla4[[#This Row],[Precio Cotizado]]-Tabla4[[#This Row],[Últ. Precio]])/Tabla4[[#This Row],[Últ. Precio]],"")) | K32: =IF(Tabla4[[#This Row],[Artículo]]="","",IFERROR(Tabla4[[#This Row],[Precio Cotizado]]-Tabla4[[#This Row],[Mejor Precio]],"")) | L32: =IF(Tabla4[[#This Row],[Artículo]]="","",IFERROR(Tabla4[[#This Row],[Dif por Unidad]]*Tabla4[[#This Row],[Cantidad]],"")) | M32: =IF(B32="","",IF(J32<0,"Más barato",IF(J32<=5%,"Dentro del rango",IF(J32<=15%,"Revisar","Precio alto")))) -> Precio alto | N32: =IF(Tabla4[[#This Row],[Artículo]]="","",IF(Tabla4[[#This Row],[Estado]]="Más barato","✓ Conviene comprar. Ahorro respecto al mejor precio.",IF(Tabla4[[#This Row],[Estado]]="Dentro del rango","✓ Precio dentro del rango habitual.",IF(Tabla4[[#This Row],[Estado]]="Revisar","⚠ Solicitar otra cotización.","🚨 Precio elevado. Negociar o buscar alternativa.")))) -> 🚨 Precio elevado. Negociar o buscar alternativa.
B33: Tuerca Zinc. 1/4" | E33: 11.7 | F33: =IF(Tabla4[[#This Row],[Artículo]]="","",IFERROR(_xlfn.XLOOKUP(Tabla4[[#This Row],[Artículo]],Tabla2[Artículo],Tabla2[Precio Unitario ARS],"",0,-1),"")) -> 12.5 | G33: =IF(Tabla4[[#This Row],[Artículo]]="","",IFERROR(_xlfn.XLOOKUP(Tabla4[[#This Row],[Artículo]],Tabla2[Artículo],Tabla2[Proveedor],"",0,-1),"")) -> Disur | H33: {=IF(Tabla4[[#This Row],[Artículo]]="","",IFERROR(MIN(_xlfn._xlws.FILTER(Tabla2[Precio Unitario ARS],Tabla2[Artículo]=Tabla4[[#This Row],[Artículo]])),""))} -> 12.5 | I33: {=IF(Tabla4[[#This Row],[Artículo]]="","",IFERROR(_xlfn.XLOOKUP(1,(Tabla2[Artículo]=Tabla4[[#This Row],[Artículo]])*(Tabla2[Precio Unitario ARS]=Tabla4[[#This Row],[Mejor Precio]]),Tabla2[Proveedor]),""))} -> Disur | J33: =IF(Tabla4[[#This Row],[Artículo]]="","",IFERROR((Tabla4[[#This Row],[Precio Cotizado]]-Tabla4[[#This Row],[Últ. Precio]])/Tabla4[[#This Row],[Últ. Precio]],"")) -> -0.064 | K33: =IF(Tabla4[[#This Row],[Artículo]]="","",IFERROR(Tabla4[[#This Row],[Precio Cotizado]]-Tabla4[[#This Row],[Mejor Precio]],"")) -> -0.8 | L33: =IF(Tabla4[[#This Row],[Artículo]]="","",IFERROR(Tabla4[[#This Row],[Dif por Unidad]]*Tabla4[[#This Row],[Cantidad]],"")) -> 0 | M33: =IF(B33="","",IF(J33<0,"Más barato",IF(J33<=5%,"Dentro del rango",IF(J33<=15%,"Revisar","Precio alto")))) -> Más barato | N33: =IF(Tabla4[[#This Row],[Artículo]]="","",IF(Tabla4[[#This Row],[Estado]]="Más barato","✓ Conviene comprar. Ahorro respecto al mejor precio.",IF(Tabla4[[#This Row],[Estado]]="Dentro del rango","✓ Precio dentro del rango habitual.",IF(Tabla4[[#This Row],[Estado]]="Revisar","⚠ Solicitar otra cotización.","🚨 Precio elevado. Negociar o buscar alternativa.")))) -> ✓ Conviene comprar. Ahorro respecto al mejor precio.
B34: Tuerca Zinc. 3/8" | E34: 24.7 | F34: =IF(Tabla4[[#This Row],[Artículo]]="","",IFERROR(_xlfn.XLOOKUP(Tabla4[[#This Row],[Artículo]],Tabla2[Artículo],Tabla2[Precio Unitario ARS],"",0,-1),"")) -> 26 | G34: =IF(Tabla4[[#This Row],[Artículo]]="","",IFERROR(_xlfn.XLOOKUP(Tabla4[[#This Row],[Artículo]],Tabla2[Artículo],Tabla2[Proveedor],"",0,-1),"")) -> Disur | H34: {=IF(Tabla4[[#This Row],[Artículo]]="","",IFERROR(MIN(_xlfn._xlws.FILTER(Tabla2[Precio Unitario ARS],Tabla2[Artículo]=Tabla4[[#This Row],[Artículo]])),""))} -> 26 | I34: {=IF(Tabla4[[#This Row],[Artículo]]="","",IFERROR(_xlfn.XLOOKUP(1,(Tabla2[Artículo]=Tabla4[[#This Row],[Artículo]])*(Tabla2[Precio Unitario ARS]=Tabla4[[#This Row],[Mejor Precio]]),Tabla2[Proveedor]),""))} -> Disur | J34: =IF(Tabla4[[#This Row],[Artículo]]="","",IFERROR((Tabla4[[#This Row],[Precio Cotizado]]-Tabla4[[#This Row],[Últ. Precio]])/Tabla4[[#This Row],[Últ. Precio]],"")) -> -0.05 | K34: =IF(Tabla4[[#This Row],[Artículo]]="","",IFERROR(Tabla4[[#This Row],[Precio Cotizado]]-Tabla4[[#This Row],[Mejor Precio]],"")) -> -1.3 | L34: =IF(Tabla4[[#This Row],[Artículo]]="","",IFERROR(Tabla4[[#This Row],[Dif por Unidad]]*Tabla4[[#This Row],[Cantidad]],"")) -> 0 | M34: =IF(B34="","",IF(J34<0,"Más barato",IF(J34<=5%,"Dentro del rango",IF(J34<=15%,"Revisar","Precio alto")))) -> Más barato | N34: =IF(Tabla4[[#This Row],[Artículo]]="","",IF(Tabla4[[#This Row],[Estado]]="Más barato","✓ Conviene comprar. Ahorro respecto al mejor precio.",IF(Tabla4[[#This Row],[Estado]]="Dentro del rango","✓ Precio dentro del rango habitual.",IF(Tabla4[[#This Row],[Estado]]="Revisar","⚠ Solicitar otra cotización.","🚨 Precio elevado. Negociar o buscar alternativa.")))) -> ✓ Conviene comprar. Ahorro respecto al mejor precio.
B35: Tuerca Zinc. 5/16" | E35: 17.18 | F35: =IF(Tabla4[[#This Row],[Artículo]]="","",IFERROR(_xlfn.XLOOKUP(Tabla4[[#This Row],[Artículo]],Tabla2[Artículo],Tabla2[Precio Unitario ARS],"",0,-1),"")) -> 18.6 | G35: =IF(Tabla4[[#This Row],[Artículo]]="","",IFERROR(_xlfn.XLOOKUP(Tabla4[[#This Row],[Artículo]],Tabla2[Artículo],Tabla2[Proveedor],"",0,-1),"")) -> Disur | H35: {=IF(Tabla4[[#This Row],[Artículo]]="","",IFERROR(MIN(_xlfn._xlws.FILTER(Tabla2[Precio Unitario ARS],Tabla2[Artículo]=Tabla4[[#This Row],[Artículo]])),""))} -> 18.6 | I35: {=IF(Tabla4[[#This Row],[Artículo]]="","",IFERROR(_xlfn.XLOOKUP(1,(Tabla2[Artículo]=Tabla4[[#This Row],[Artículo]])*(Tabla2[Precio Unitario ARS]=Tabla4[[#This Row],[Mejor Precio]]),Tabla2[Proveedor]),""))} -> Disur | J35: =IF(Tabla4[[#This Row],[Artículo]]="","",IFERROR((Tabla4[[#This Row],[Precio Cotizado]]-Tabla4[[#This Row],[Últ. Precio]])/Tabla4[[#This Row],[Últ. Precio]],"")) -> -0.076344086 | K35: =IF(Tabla4[[#This Row],[Artículo]]="","",IFERROR(Tabla4[[#This Row],[Precio Cotizado]]-Tabla4[[#This Row],[Mejor Precio]],"")) -> -1.42 | L35: =IF(Tabla4[[#This Row],[Artículo]]="","",IFERROR(Tabla4[[#This Row],[Dif por Unidad]]*Tabla4[[#This Row],[Cantidad]],"")) -> 0 | M35: =IF(B35="","",IF(J35<0,"Más barato",IF(J35<=5%,"Dentro del rango",IF(J35<=15%,"Revisar","Precio alto")))) -> Más barato | N35: =IF(Tabla4[[#This Row],[Artículo]]="","",IF(Tabla4[[#This Row],[Estado]]="Más barato","✓ Conviene comprar. Ahorro respecto al mejor precio.",IF(Tabla4[[#This Row],[Estado]]="Dentro del rango","✓ Precio dentro del rango habitual.",IF(Tabla4[[#This Row],[Estado]]="Revisar","⚠ Solicitar otra cotización.","🚨 Precio elevado. Negociar o buscar alternativa.")))) -> ✓ Conviene comprar. Ahorro respecto al mejor precio.
B36: Varilla Roscada Zinc. 1/4" | E36: 449 | F36: =IF(Tabla4[[#This Row],[Artículo]]="","",IFERROR(_xlfn.XLOOKUP(Tabla4[[#This Row],[Artículo]],Tabla2[Artículo],Tabla2[Precio Unitario ARS],"",0,-1),"")) -> 463.05 | G36: =IF(Tabla4[[#This Row],[Artículo]]="","",IFERROR(_xlfn.XLOOKUP(Tabla4[[#This Row],[Artículo]],Tabla2[Artículo],Tabla2[Proveedor],"",0,-1),"")) -> Dusvar | H36: {=IF(Tabla4[[#This Row],[Artículo]]="","",IFERROR(MIN(_xlfn._xlws.FILTER(Tabla2[Precio Unitario ARS],Tabla2[Artículo]=Tabla4[[#This Row],[Artículo]])),""))} -> 450 | I36: {=IF(Tabla4[[#This Row],[Artículo]]="","",IFERROR(_xlfn.XLOOKUP(1,(Tabla2[Artículo]=Tabla4[[#This Row],[Artículo]])*(Tabla2[Precio Unitario ARS]=Tabla4[[#This Row],[Mejor Precio]]),Tabla2[Proveedor]),""))} -> Dusvar | J36: =IF(Tabla4[[#This Row],[Artículo]]="","",IFERROR((Tabla4[[#This Row],[Precio Cotizado]]-Tabla4[[#This Row],[Últ. Precio]])/Tabla4[[#This Row],[Últ. Precio]],"")) -> -0.030342296 | K36: =IF(Tabla4[[#This Row],[Artículo]]="","",IFERROR(Tabla4[[#This Row],[Precio Cotizado]]-Tabla4[[#This Row],[Mejor Precio]],"")) -> -1 | L36: =IF(Tabla4[[#This Row],[Artículo]]="","",IFERROR(Tabla4[[#This Row],[Dif por Unidad]]*Tabla4[[#This Row],[Cantidad]],"")) -> 0 | M36: =IF(B36="","",IF(J36<0,"Más barato",IF(J36<=5%,"Dentro del rango",IF(J36<=15%,"Revisar","Precio alto")))) -> Más barato | N36: =IF(Tabla4[[#This Row],[Artículo]]="","",IF(Tabla4[[#This Row],[Estado]]="Más barato","✓ Conviene comprar. Ahorro respecto al mejor precio.",IF(Tabla4[[#This Row],[Estado]]="Dentro del rango","✓ Precio dentro del rango habitual.",IF(Tabla4[[#This Row],[Estado]]="Revisar","⚠ Solicitar otra cotización.","🚨 Precio elevado. Negociar o buscar alternativa.")))) -> ✓ Conviene comprar. Ahorro respecto al mejor precio.
F37: =IF(Tabla4[[#This Row],[Artículo]]="","",IFERROR(_xlfn.XLOOKUP(Tabla4[[#This Row],[Artículo]],Tabla2[Artículo],Tabla2[Precio Unitario ARS],"",0,-1),"")) | G37: =IF(Tabla4[[#This Row],[Artículo]]="","",IFERROR(_xlfn.XLOOKUP(Tabla4[[#This Row],[Artículo]],Tabla2[Artículo],Tabla2[Proveedor],"",0,-1),"")) | H37: {=IF(Tabla4[[#This Row],[Artículo]]="","",IFERROR(MIN(_xlfn._xlws.FILTER(Tabla2[Precio Unitario ARS],Tabla2[Artículo]=Tabla4[[#This Row],[Artículo]])),""))} | I37: {=IF(Tabla4[[#This Row],[Artículo]]="","",IFERROR(_xlfn.XLOOKUP(1,(Tabla2[Artículo]=Tabla4[[#This Row],[Artículo]])*(Tabla2[Precio Unitario ARS]=Tabla4[[#This Row],[Mejor Precio]]),Tabla2[Proveedor]),""))} | J37: =IF(Tabla4[[#This Row],[Artículo]]="","",IFERROR((Tabla4[[#This Row],[Precio Cotizado]]-Tabla4[[#This Row],[Últ. Precio]])/Tabla4[[#This Row],[Últ. Precio]],"")) | K37: =IF(Tabla4[[#This Row],[Artículo]]="","",IFERROR(Tabla4[[#This Row],[Precio Cotizado]]-Tabla4[[#This Row],[Mejor Precio]],"")) | L37: =IF(Tabla4[[#This Row],[Artículo]]="","",IFERROR(Tabla4[[#This Row],[Dif por Unidad]]*Tabla4[[#This Row],[Cantidad]],"")) | M37: =IF(B37="","",IF(J37<0,"Más barato",IF(J37<=5%,"Dentro del rango",IF(J37<=15%,"Revisar","Precio alto")))) | N37: =IF(Tabla4[[#This Row],[Artículo]]="","",IF(Tabla4[[#This Row],[Estado]]="Más barato","✓ Conviene comprar. Ahorro respecto al mejor precio.",IF(Tabla4[[#This Row],[Estado]]="Dentro del rango","✓ Precio dentro del rango habitual.",IF(Tabla4[[#This Row],[Estado]]="Revisar","⚠ Solicitar otra cotización.","🚨 Precio elevado. Negociar o buscar alternativa."))))
F38: =IF(Tabla4[[#This Row],[Artículo]]="","",IFERROR(_xlfn.XLOOKUP(Tabla4[[#This Row],[Artículo]],Tabla2[Artículo],Tabla2[Precio Unitario ARS],"",0,-1),"")) | G38: =IF(Tabla4[[#This Row],[Artículo]]="","",IFERROR(_xlfn.XLOOKUP(Tabla4[[#This Row],[Artículo]],Tabla2[Artículo],Tabla2[Proveedor],"",0,-1),"")) | H38: {=IF(Tabla4[[#This Row],[Artículo]]="","",IFERROR(MIN(_xlfn._xlws.FILTER(Tabla2[Precio Unitario ARS],Tabla2[Artículo]=Tabla4[[#This Row],[Artículo]])),""))} | I38: {=IF(Tabla4[[#This Row],[Artículo]]="","",IFERROR(_xlfn.XLOOKUP(1,(Tabla2[Artículo]=Tabla4[[#This Row],[Artículo]])*(Tabla2[Precio Unitario ARS]=Tabla4[[#This Row],[Mejor Precio]]),Tabla2[Proveedor]),""))} | J38: =IF(Tabla4[[#This Row],[Artículo]]="","",IFERROR((Tabla4[[#This Row],[Precio Cotizado]]-Tabla4[[#This Row],[Últ. Precio]])/Tabla4[[#This Row],[Últ. Precio]],"")) | K38: =IF(Tabla4[[#This Row],[Artículo]]="","",IFERROR(Tabla4[[#This Row],[Precio Cotizado]]-Tabla4[[#This Row],[Mejor Precio]],"")) | L38: =IF(Tabla4[[#This Row],[Artículo]]="","",IFERROR(Tabla4[[#This Row],[Dif por Unidad]]*Tabla4[[#This Row],[Cantidad]],"")) | M38: =IF(B38="","",IF(J38<0,"Más barato",IF(J38<=5%,"Dentro del rango",IF(J38<=15%,"Revisar","Precio alto")))) | N38: =IF(Tabla4[[#This Row],[Artículo]]="","",IF(Tabla4[[#This Row],[Estado]]="Más barato","✓ Conviene comprar. Ahorro respecto al mejor precio.",IF(Tabla4[[#This Row],[Estado]]="Dentro del rango","✓ Precio dentro del rango habitual.",IF(Tabla4[[#This Row],[Estado]]="Revisar","⚠ Solicitar otra cotización.","🚨 Precio elevado. Negociar o buscar alternativa."))))
F39: =IF(Tabla4[[#This Row],[Artículo]]="","",IFERROR(_xlfn.XLOOKUP(Tabla4[[#This Row],[Artículo]],Tabla2[Artículo],Tabla2[Precio Unitario ARS],"",0,-1),"")) | G39: =IF(Tabla4[[#This Row],[Artículo]]="","",IFERROR(_xlfn.XLOOKUP(Tabla4[[#This Row],[Artículo]],Tabla2[Artículo],Tabla2[Proveedor],"",0,-1),"")) | H39: {=IF(Tabla4[[#This Row],[Artículo]]="","",IFERROR(MIN(_xlfn._xlws.FILTER(Tabla2[Precio Unitario ARS],Tabla2[Artículo]=Tabla4[[#This Row],[Artículo]])),""))} | I39: {=IF(Tabla4[[#This Row],[Artículo]]="","",IFERROR(_xlfn.XLOOKUP(1,(Tabla2[Artículo]=Tabla4[[#This Row],[Artículo]])*(Tabla2[Precio Unitario ARS]=Tabla4[[#This Row],[Mejor Precio]]),Tabla2[Proveedor]),""))} | J39: =IF(Tabla4[[#This Row],[Artículo]]="","",IFERROR((Tabla4[[#This Row],[Precio Cotizado]]-Tabla4[[#This Row],[Últ. Precio]])/Tabla4[[#This Row],[Últ. Precio]],"")) | K39: =IF(Tabla4[[#This Row],[Artículo]]="","",IFERROR(Tabla4[[#This Row],[Precio Cotizado]]-Tabla4[[#This Row],[Mejor Precio]],"")) | L39: =IF(Tabla4[[#This Row],[Artículo]]="","",IFERROR(Tabla4[[#This Row],[Dif por Unidad]]*Tabla4[[#This Row],[Cantidad]],"")) | M39: =IF(B39="","",IF(J39<0,"Más barato",IF(J39<=5%,"Dentro del rango",IF(J39<=15%,"Revisar","Precio alto")))) | N39: =IF(Tabla4[[#This Row],[Artículo]]="","",IF(Tabla4[[#This Row],[Estado]]="Más barato","✓ Conviene comprar. Ahorro respecto al mejor precio.",IF(Tabla4[[#This Row],[Estado]]="Dentro del rango","✓ Precio dentro del rango habitual.",IF(Tabla4[[#This Row],[Estado]]="Revisar","⚠ Solicitar otra cotización.","🚨 Precio elevado. Negociar o buscar alternativa."))))
F40: =IF(Tabla4[[#This Row],[Artículo]]="","",IFERROR(_xlfn.XLOOKUP(Tabla4[[#This Row],[Artículo]],Tabla2[Artículo],Tabla2[Precio Unitario ARS],"",0,-1),"")) | G40: =IF(Tabla4[[#This Row],[Artículo]]="","",IFERROR(_xlfn.XLOOKUP(Tabla4[[#This Row],[Artículo]],Tabla2[Artículo],Tabla2[Proveedor],"",0,-1),"")) | H40: {=IF(Tabla4[[#This Row],[Artículo]]="","",IFERROR(MIN(_xlfn._xlws.FILTER(Tabla2[Precio Unitario ARS],Tabla2[Artículo]=Tabla4[[#This Row],[Artículo]])),""))} | I40: {=IF(Tabla4[[#This Row],[Artículo]]="","",IFERROR(_xlfn.XLOOKUP(1,(Tabla2[Artículo]=Tabla4[[#This Row],[Artículo]])*(Tabla2[Precio Unitario ARS]=Tabla4[[#This Row],[Mejor Precio]]),Tabla2[Proveedor]),""))} | J40: =IF(Tabla4[[#This Row],[Artículo]]="","",IFERROR((Tabla4[[#This Row],[Precio Cotizado]]-Tabla4[[#This Row],[Últ. Precio]])/Tabla4[[#This Row],[Últ. Precio]],"")) | K40: =IF(Tabla4[[#This Row],[Artículo]]="","",IFERROR(Tabla4[[#This Row],[Precio Cotizado]]-Tabla4[[#This Row],[Mejor Precio]],"")) | L40: =IF(Tabla4[[#This Row],[Artículo]]="","",IFERROR(Tabla4[[#This Row],[Dif por Unidad]]*Tabla4[[#This Row],[Cantidad]],"")) | M40: =IF(B40="","",IF(J40<0,"Más barato",IF(J40<=5%,"Dentro del rango",IF(J40<=15%,"Revisar","Precio alto")))) | N40: =IF(Tabla4[[#This Row],[Artículo]]="","",IF(Tabla4[[#This Row],[Estado]]="Más barato","✓ Conviene comprar. Ahorro respecto al mejor precio.",IF(Tabla4[[#This Row],[Estado]]="Dentro del rango","✓ Precio dentro del rango habitual.",IF(Tabla4[[#This Row],[Estado]]="Revisar","⚠ Solicitar otra cotización.","🚨 Precio elevado. Negociar o buscar alternativa."))))
F41: =IF(Tabla4[[#This Row],[Artículo]]="","",IFERROR(_xlfn.XLOOKUP(Tabla4[[#This Row],[Artículo]],Tabla2[Artículo],Tabla2[Precio Unitario ARS],"",0,-1),"")) | G41: =IF(Tabla4[[#This Row],[Artículo]]="","",IFERROR(_xlfn.XLOOKUP(Tabla4[[#This Row],[Artículo]],Tabla2[Artículo],Tabla2[Proveedor],"",0,-1),"")) | H41: {=IF(Tabla4[[#This Row],[Artículo]]="","",IFERROR(MIN(_xlfn._xlws.FILTER(Tabla2[Precio Unitario ARS],Tabla2[Artículo]=Tabla4[[#This Row],[Artículo]])),""))} | I41: {=IF(Tabla4[[#This Row],[Artículo]]="","",IFERROR(_xlfn.XLOOKUP(1,(Tabla2[Artículo]=Tabla4[[#This Row],[Artículo]])*(Tabla2[Precio Unitario ARS]=Tabla4[[#This Row],[Mejor Precio]]),Tabla2[Proveedor]),""))} | J41: =IF(Tabla4[[#This Row],[Artículo]]="","",IFERROR((Tabla4[[#This Row],[Precio Cotizado]]-Tabla4[[#This Row],[Últ. Precio]])/Tabla4[[#This Row],[Últ. Precio]],"")) | K41: =IF(Tabla4[[#This Row],[Artículo]]="","",IFERROR(Tabla4[[#This Row],[Precio Cotizado]]-Tabla4[[#This Row],[Mejor Precio]],"")) | L41: =IF(Tabla4[[#This Row],[Artículo]]="","",IFERROR(Tabla4[[#This Row],[Dif por Unidad]]*Tabla4[[#This Row],[Cantidad]],"")) | M41: =IF(B41="","",IF(J41<0,"Más barato",IF(J41<=5%,"Dentro del rango",IF(J41<=15%,"Revisar","Precio alto")))) | N41: =IF(Tabla4[[#This Row],[Artículo]]="","",IF(Tabla4[[#This Row],[Estado]]="Más barato","✓ Conviene comprar. Ahorro respecto al mejor precio.",IF(Tabla4[[#This Row],[Estado]]="Dentro del rango","✓ Precio dentro del rango habitual.",IF(Tabla4[[#This Row],[Estado]]="Revisar","⚠ Solicitar otra cotización.","🚨 Precio elevado. Negociar o buscar alternativa."))))
F42: =IF(Tabla4[[#This Row],[Artículo]]="","",IFERROR(_xlfn.XLOOKUP(Tabla4[[#This Row],[Artículo]],Tabla2[Artículo],Tabla2[Precio Unitario ARS],"",0,-1),"")) | G42: =IF(Tabla4[[#This Row],[Artículo]]="","",IFERROR(_xlfn.XLOOKUP(Tabla4[[#This Row],[Artículo]],Tabla2[Artículo],Tabla2[Proveedor],"",0,-1),"")) | H42: {=IF(Tabla4[[#This Row],[Artículo]]="","",IFERROR(MIN(_xlfn._xlws.FILTER(Tabla2[Precio Unitario ARS],Tabla2[Artículo]=Tabla4[[#This Row],[Artículo]])),""))} | I42: {=IF(Tabla4[[#This Row],[Artículo]]="","",IFERROR(_xlfn.XLOOKUP(1,(Tabla2[Artículo]=Tabla4[[#This Row],[Artículo]])*(Tabla2[Precio Unitario ARS]=Tabla4[[#This Row],[Mejor Precio]]),Tabla2[Proveedor]),""))} | J42: =IF(Tabla4[[#This Row],[Artículo]]="","",IFERROR((Tabla4[[#This Row],[Precio Cotizado]]-Tabla4[[#This Row],[Últ. Precio]])/Tabla4[[#This Row],[Últ. Precio]],"")) | K42: =IF(Tabla4[[#This Row],[Artículo]]="","",IFERROR(Tabla4[[#This Row],[Precio Cotizado]]-Tabla4[[#This Row],[Mejor Precio]],"")) | L42: =IF(Tabla4[[#This Row],[Artículo]]="","",IFERROR(Tabla4[[#This Row],[Dif por Unidad]]*Tabla4[[#This Row],[Cantidad]],"")) | M42: =IF(B42="","",IF(J42<0,"Más barato",IF(J42<=5%,"Dentro del rango",IF(J42<=15%,"Revisar","Precio alto")))) | N42: =IF(Tabla4[[#This Row],[Artículo]]="","",IF(Tabla4[[#This Row],[Estado]]="Más barato","✓ Conviene comprar. Ahorro respecto al mejor precio.",IF(Tabla4[[#This Row],[Estado]]="Dentro del rango","✓ Precio dentro del rango habitual.",IF(Tabla4[[#This Row],[Estado]]="Revisar","⚠ Solicitar otra cotización.","🚨 Precio elevado. Negociar o buscar alternativa."))))
F43: =IF(Tabla4[[#This Row],[Artículo]]="","",IFERROR(_xlfn.XLOOKUP(Tabla4[[#This Row],[Artículo]],Tabla2[Artículo],Tabla2[Precio Unitario ARS],"",0,-1),"")) | G43: =IF(Tabla4[[#This Row],[Artículo]]="","",IFERROR(_xlfn.XLOOKUP(Tabla4[[#This Row],[Artículo]],Tabla2[Artículo],Tabla2[Proveedor],"",0,-1),"")) | H43: {=IF(Tabla4[[#This Row],[Artículo]]="","",IFERROR(MIN(_xlfn._xlws.FILTER(Tabla2[Precio Unitario ARS],Tabla2[Artículo]=Tabla4[[#This Row],[Artículo]])),""))} | I43: {=IF(Tabla4[[#This Row],[Artículo]]="","",IFERROR(_xlfn.XLOOKUP(1,(Tabla2[Artículo]=Tabla4[[#This Row],[Artículo]])*(Tabla2[Precio Unitario ARS]=Tabla4[[#This Row],[Mejor Precio]]),Tabla2[Proveedor]),""))} | J43: =IF(Tabla4[[#This Row],[Artículo]]="","",IFERROR((Tabla4[[#This Row],[Precio Cotizado]]-Tabla4[[#This Row],[Últ. Precio]])/Tabla4[[#This Row],[Últ. Precio]],"")) | K43: =IF(Tabla4[[#This Row],[Artículo]]="","",IFERROR(Tabla4[[#This Row],[Precio Cotizado]]-Tabla4[[#This Row],[Mejor Precio]],"")) | L43: =IF(Tabla4[[#This Row],[Artículo]]="","",IFERROR(Tabla4[[#This Row],[Dif por Unidad]]*Tabla4[[#This Row],[Cantidad]],"")) | M43: =IF(B43="","",IF(J43<0,"Más barato",IF(J43<=5%,"Dentro del rango",IF(J43<=15%,"Revisar","Precio alto")))) | N43: =IF(Tabla4[[#This Row],[Artículo]]="","",IF(Tabla4[[#This Row],[Estado]]="Más barato","✓ Conviene comprar. Ahorro respecto al mejor precio.",IF(Tabla4[[#This Row],[Estado]]="Dentro del rango","✓ Precio dentro del rango habitual.",IF(Tabla4[[#This Row],[Estado]]="Revisar","⚠ Solicitar otra cotización.","🚨 Precio elevado. Negociar o buscar alternativa."))))
F44: =IF(Tabla4[[#This Row],[Artículo]]="","",IFERROR(_xlfn.XLOOKUP(Tabla4[[#This Row],[Artículo]],Tabla2[Artículo],Tabla2[Precio Unitario ARS],"",0,-1),"")) | G44: =IF(Tabla4[[#This Row],[Artículo]]="","",IFERROR(_xlfn.XLOOKUP(Tabla4[[#This Row],[Artículo]],Tabla2[Artículo],Tabla2[Proveedor],"",0,-1),"")) | H44: {=IF(Tabla4[[#This Row],[Artículo]]="","",IFERROR(MIN(_xlfn._xlws.FILTER(Tabla2[Precio Unitario ARS],Tabla2[Artículo]=Tabla4[[#This Row],[Artículo]])),""))} | I44: {=IF(Tabla4[[#This Row],[Artículo]]="","",IFERROR(_xlfn.XLOOKUP(1,(Tabla2[Artículo]=Tabla4[[#This Row],[Artículo]])*(Tabla2[Precio Unitario ARS]=Tabla4[[#This Row],[Mejor Precio]]),Tabla2[Proveedor]),""))} | J44: =IF(Tabla4[[#This Row],[Artículo]]="","",IFERROR((Tabla4[[#This Row],[Precio Cotizado]]-Tabla4[[#This Row],[Últ. Precio]])/Tabla4[[#This Row],[Últ. Precio]],"")) | K44: =IF(Tabla4[[#This Row],[Artículo]]="","",IFERROR(Tabla4[[#This Row],[Precio Cotizado]]-Tabla4[[#This Row],[Mejor Precio]],"")) | L44: =IF(Tabla4[[#This Row],[Artículo]]="","",IFERROR(Tabla4[[#This Row],[Dif por Unidad]]*Tabla4[[#This Row],[Cantidad]],"")) | M44: =IF(B44="","",IF(J44<0,"Más barato",IF(J44<=5%,"Dentro del rango",IF(J44<=15%,"Revisar","Precio alto")))) | N44: =IF(Tabla4[[#This Row],[Artículo]]="","",IF(Tabla4[[#This Row],[Estado]]="Más barato","✓ Conviene comprar. Ahorro respecto al mejor precio.",IF(Tabla4[[#This Row],[Estado]]="Dentro del rango","✓ Precio dentro del rango habitual.",IF(Tabla4[[#This Row],[Estado]]="Revisar","⚠ Solicitar otra cotización.","🚨 Precio elevado. Negociar o buscar alternativa."))))
F45: =IF(Tabla4[[#This Row],[Artículo]]="","",IFERROR(_xlfn.XLOOKUP(Tabla4[[#This Row],[Artículo]],Tabla2[Artículo],Tabla2[Precio Unitario ARS],"",0,-1),"")) | G45: =IF(Tabla4[[#This Row],[Artículo]]="","",IFERROR(_xlfn.XLOOKUP(Tabla4[[#This Row],[Artículo]],Tabla2[Artículo],Tabla2[Proveedor],"",0,-1),"")) | H45: {=IF(Tabla4[[#This Row],[Artículo]]="","",IFERROR(MIN(_xlfn._xlws.FILTER(Tabla2[Precio Unitario ARS],Tabla2[Artículo]=Tabla4[[#This Row],[Artículo]])),""))} | I45: {=IF(Tabla4[[#This Row],[Artículo]]="","",IFERROR(_xlfn.XLOOKUP(1,(Tabla2[Artículo]=Tabla4[[#This Row],[Artículo]])*(Tabla2[Precio Unitario ARS]=Tabla4[[#This Row],[Mejor Precio]]),Tabla2[Proveedor]),""))} | J45: =IF(Tabla4[[#This Row],[Artículo]]="","",IFERROR((Tabla4[[#This Row],[Precio Cotizado]]-Tabla4[[#This Row],[Últ. Precio]])/Tabla4[[#This Row],[Últ. Precio]],"")) | K45: =IF(Tabla4[[#This Row],[Artículo]]="","",IFERROR(Tabla4[[#This Row],[Precio Cotizado]]-Tabla4[[#This Row],[Mejor Precio]],"")) | L45: =IF(Tabla4[[#This Row],[Artículo]]="","",IFERROR(Tabla4[[#This Row],[Dif por Unidad]]*Tabla4[[#This Row],[Cantidad]],"")) | M45: =IF(B45="","",IF(J45<0,"Más barato",IF(J45<=5%,"Dentro del rango",IF(J45<=15%,"Revisar","Precio alto")))) | N45: =IF(Tabla4[[#This Row],[Artículo]]="","",IF(Tabla4[[#This Row],[Estado]]="Más barato","✓ Conviene comprar. Ahorro respecto al mejor precio.",IF(Tabla4[[#This Row],[Estado]]="Dentro del rango","✓ Precio dentro del rango habitual.",IF(Tabla4[[#This Row],[Estado]]="Revisar","⚠ Solicitar otra cotización.","🚨 Precio elevado. Negociar o buscar alternativa."))))
F46: =IF(Tabla4[[#This Row],[Artículo]]="","",IFERROR(_xlfn.XLOOKUP(Tabla4[[#This Row],[Artículo]],Tabla2[Artículo],Tabla2[Precio Unitario ARS],"",0,-1),"")) | G46: =IF(Tabla4[[#This Row],[Artículo]]="","",IFERROR(_xlfn.XLOOKUP(Tabla4[[#This Row],[Artículo]],Tabla2[Artículo],Tabla2[Proveedor],"",0,-1),"")) | H46: {=IF(Tabla4[[#This Row],[Artículo]]="","",IFERROR(MIN(_xlfn._xlws.FILTER(Tabla2[Precio Unitario ARS],Tabla2[Artículo]=Tabla4[[#This Row],[Artículo]])),""))} | I46: {=IF(Tabla4[[#This Row],[Artículo]]="","",IFERROR(_xlfn.XLOOKUP(1,(Tabla2[Artículo]=Tabla4[[#This Row],[Artículo]])*(Tabla2[Precio Unitario ARS]=Tabla4[[#This Row],[Mejor Precio]]),Tabla2[Proveedor]),""))} | J46: =IF(Tabla4[[#This Row],[Artículo]]="","",IFERROR((Tabla4[[#This Row],[Precio Cotizado]]-Tabla4[[#This Row],[Últ. Precio]])/Tabla4[[#This Row],[Últ. Precio]],"")) | K46: =IF(Tabla4[[#This Row],[Artículo]]="","",IFERROR(Tabla4[[#This Row],[Precio Cotizado]]-Tabla4[[#This Row],[Mejor Precio]],"")) | L46: =IF(Tabla4[[#This Row],[Artículo]]="","",IFERROR(Tabla4[[#This Row],[Dif por Unidad]]*Tabla4[[#This Row],[Cantidad]],"")) | M46: =IF(B46="","",IF(J46<0,"Más barato",IF(J46<=5%,"Dentro del rango",IF(J46<=15%,"Revisar","Precio alto")))) | N46: =IF(Tabla4[[#This Row],[Artículo]]="","",IF(Tabla4[[#This Row],[Estado]]="Más barato","✓ Conviene comprar. Ahorro respecto al mejor precio.",IF(Tabla4[[#This Row],[Estado]]="Dentro del rango","✓ Precio dentro del rango habitual.",IF(Tabla4[[#This Row],[Estado]]="Revisar","⚠ Solicitar otra cotización.","🚨 Precio elevado. Negociar o buscar alternativa."))))
F47: =IF(Tabla4[[#This Row],[Artículo]]="","",IFERROR(_xlfn.XLOOKUP(Tabla4[[#This Row],[Artículo]],Tabla2[Artículo],Tabla2[Precio Unitario ARS],"",0,-1),"")) | G47: =IF(Tabla4[[#This Row],[Artículo]]="","",IFERROR(_xlfn.XLOOKUP(Tabla4[[#This Row],[Artículo]],Tabla2[Artículo],Tabla2[Proveedor],"",0,-1),"")) | H47: {=IF(Tabla4[[#This Row],[Artículo]]="","",IFERROR(MIN(_xlfn._xlws.FILTER(Tabla2[Precio Unitario ARS],Tabla2[Artículo]=Tabla4[[#This Row],[Artículo]])),""))} | I47: {=IF(Tabla4[[#This Row],[Artículo]]="","",IFERROR(_xlfn.XLOOKUP(1,(Tabla2[Artículo]=Tabla4[[#This Row],[Artículo]])*(Tabla2[Precio Unitario ARS]=Tabla4[[#This Row],[Mejor Precio]]),Tabla2[Proveedor]),""))} | J47: =IF(Tabla4[[#This Row],[Artículo]]="","",IFERROR((Tabla4[[#This Row],[Precio Cotizado]]-Tabla4[[#This Row],[Últ. Precio]])/Tabla4[[#This Row],[Últ. Precio]],"")) | K47: =IF(Tabla4[[#This Row],[Artículo]]="","",IFERROR(Tabla4[[#This Row],[Precio Cotizado]]-Tabla4[[#This Row],[Mejor Precio]],"")) | L47: =IF(Tabla4[[#This Row],[Artículo]]="","",IFERROR(Tabla4[[#This Row],[Dif por Unidad]]*Tabla4[[#This Row],[Cantidad]],"")) | M47: =IF(B47="","",IF(J47<0,"Más barato",IF(J47<=5%,"Dentro del rango",IF(J47<=15%,"Revisar","Precio alto")))) | N47: =IF(Tabla4[[#This Row],[Artículo]]="","",IF(Tabla4[[#This Row],[Estado]]="Más barato","✓ Conviene comprar. Ahorro respecto al mejor precio.",IF(Tabla4[[#This Row],[Estado]]="Dentro del rango","✓ Precio dentro del rango habitual.",IF(Tabla4[[#This Row],[Estado]]="Revisar","⚠ Solicitar otra cotización.","🚨 Precio elevado. Negociar o buscar alternativa."))))
F48: =IF(Tabla4[[#This Row],[Artículo]]="","",IFERROR(_xlfn.XLOOKUP(Tabla4[[#This Row],[Artículo]],Tabla2[Artículo],Tabla2[Precio Unitario ARS],"",0,-1),"")) | G48: =IF(Tabla4[[#This Row],[Artículo]]="","",IFERROR(_xlfn.XLOOKUP(Tabla4[[#This Row],[Artículo]],Tabla2[Artículo],Tabla2[Proveedor],"",0,-1),"")) | H48: {=IF(Tabla4[[#This Row],[Artículo]]="","",IFERROR(MIN(_xlfn._xlws.FILTER(Tabla2[Precio Unitario ARS],Tabla2[Artículo]=Tabla4[[#This Row],[Artículo]])),""))} | I48: {=IF(Tabla4[[#This Row],[Artículo]]="","",IFERROR(_xlfn.XLOOKUP(1,(Tabla2[Artículo]=Tabla4[[#This Row],[Artículo]])*(Tabla2[Precio Unitario ARS]=Tabla4[[#This Row],[Mejor Precio]]),Tabla2[Proveedor]),""))} | J48: =IF(Tabla4[[#This Row],[Artículo]]="","",IFERROR((Tabla4[[#This Row],[Precio Cotizado]]-Tabla4[[#This Row],[Últ. Precio]])/Tabla4[[#This Row],[Últ. Precio]],"")) | K48: =IF(Tabla4[[#This Row],[Artículo]]="","",IFERROR(Tabla4[[#This Row],[Precio Cotizado]]-Tabla4[[#This Row],[Mejor Precio]],"")) | L48: =IF(Tabla4[[#This Row],[Artículo]]="","",IFERROR(Tabla4[[#This Row],[Dif por Unidad]]*Tabla4[[#This Row],[Cantidad]],"")) | M48: =IF(B48="","",IF(J48<0,"Más barato",IF(J48<=5%,"Dentro del rango",IF(J48<=15%,"Revisar","Precio alto")))) | N48: =IF(Tabla4[[#This Row],[Artículo]]="","",IF(Tabla4[[#This Row],[Estado]]="Más barato","✓ Conviene comprar. Ahorro respecto al mejor precio.",IF(Tabla4[[#This Row],[Estado]]="Dentro del rango","✓ Precio dentro del rango habitual.",IF(Tabla4[[#This Row],[Estado]]="Revisar","⚠ Solicitar otra cotización.","🚨 Precio elevado. Negociar o buscar alternativa."))))
... F161: =IF(Tabla4[[#This Row],[Artículo]]="","",IFERROR(_xlfn.XLOOKUP(Tabla4[[#This Row],[Artículo]],Tabla2[Artículo],Tabla2[Precio Unitario ARS],"",0,-1),"")) | G161: =IF(Tabla4[[#This Row],[Artículo]]="","",IFERROR(_xlfn.XLOOKUP(Tabla4[[#This Row],[Artículo]],Tabla2[Artículo],Tabla2[Proveedor],"",0,-1),"")) | H161: {=IF(Tabla4[[#This Row],[Artículo]]="","",IFERROR(MIN(_xlfn._xlws.FILTER(Tabla2[Precio Unitario ARS],Tabla2[Artículo]=Tabla4[[#This Row],[Artículo]])),""))} | I161: {=IF(Tabla4[[#This Row],[Artículo]]="","",IFERROR(_xlfn.XLOOKUP(1,(Tabla2[Artículo]=Tabla4[[#This Row],[Artículo]])*(Tabla2[Precio Unitario ARS]=Tabla4[[#This Row],[Mejor Precio]]),Tabla2[Proveedor]),""))} | J161: =IF(Tabla4[[#This Row],[Artículo]]="","",IFERROR((Tabla4[[#This Row],[Precio Cotizado]]-Tabla4[[#This Row],[Últ. Precio]])/Tabla4[[#This Row],[Últ. Precio]],"")) | K161: =IF(Tabla4[[#This Row],[Artículo]]="","",IFERROR(Tabla4[[#This Row],[Precio Cotizado]]-Tabla4[[#This Row],[Mejor Precio]],"")) | L161: =IF(Tabla4[[#This Row],[Artículo]]="","",IFERROR(Tabla4[[#This Row],[Dif por Unidad]]*Tabla4[[#This Row],[Cantidad]],"")) | M161: =IF(B161="","",IF(J161<0,"Más barato",IF(J161<=5%,"Dentro del rango",IF(J161<=15%,"Revisar","Precio alto")))) | N161: =IF(Tabla4[[#This Row],[Artículo]]="","",IF(Tabla4[[#This Row],[Estado]]="Más barato","✓ Conviene comprar. Ahorro respecto al mejor precio.",IF(Tabla4[[#This Row],[Estado]]="Dentro del rango","✓ Precio dentro del rango habitual.",IF(Tabla4[[#This Row],[Estado]]="Revisar","⚠ Solicitar otra cotización.","🚨 Precio elevado. Negociar o buscar alternativa."))))

Sheet TC_BNA xlsx
A1: Fecha cotizacion | B1: Compra | C1: Venta
A2: 46146 | B2: 1375 | C2: 1425
A3: 46147 | B3: 1365 | C3: 1415
A4: 46148 | B4: 1360 | C4: 1410
A5: 46149 | B5: 1370 | C5: 1420
A6: 46150 | B6: 1370 | C6: 1420
A7: 46153 | B7: 1365 | C7: 1415
A8: 46154 | B8: 1355 | C8: 1405
A9: 46155 | B9: 1365 | C9: 1415
A10: 46156 | B10: 1365 | C10: 1415
A11: 46157 | B11: 1370 | C11: 1420
A12: 46160 | B12: 1370 | C12: 1420
A13: 46161 | B13: 1370 | C13: 1420
... A64: 46234 | B64: 1460 | C64: 1510

Sheet TD - Insumos
A1: Mes | B1: (Todas) | F1: Mes | G1: (Todas) | I1: Mes | J1: (Todas)
A2: Fecha | B2: (Todas) | F2: Fecha | G2: (Todas) | I2: Fecha | J2: (Todas)
A4: Etiquetas de fila | B4: Suma de Subtotal ARS | F4: Etiquetas de fila | G4: Suma de Subtotal ARS | I4: Etiquetas de fila | J4: Suma de Subtotal ARS
A5: GALVA 1220 X 2440 3,2 | B5: 9722624.3 | F5: Disur | G5: 16388855 | I5: Reventa | J5: 39970530
A6: Tuerca Flange Zinc. 1/4" | B6: 8162282.8 | F6: Dusvar | G6: 12120500 | I6: Materia Prima | J6: 17507082
A7: Varilla Roscada Zinc. 3/8" | B7: 6207200 | F7: Pacheco Chapas | G7: 9722624.3 | I7: Embalaje | J7: 16383135
A8: Stretch 10 cm | B8: 6039138 | F8: Distribuidora Tubulón | G8: 7512488.5 | I8: Soldadura | J8: 2810216.2
A9: Tor. Traba 1/4" | B9: 5873700 | F9: Mad Packaging | G9: 6655217.5 | I9: Servicio | J9: 2805600
A10: Varilla Roscada Zinc. 1/4" | B10: 4301100 | F10: Casanova | G10: 5871448.4 | I10: EPP | J10: 1612406.8
A11: Varilla Roscada Zinc. 5/16" | B11: 3986760 | F11: Aserradero Alonso | G11: 3462996.3 | I11: Limpieza | J11: 1154168.7
A12: Tuerca Cupla 1/4" | B12: 3531600 | F12: MTZ | G12: 2805600 | I12: Herramientas | J12: 947354.42
A13: HIERRO T 1" 1/4 X 1/8 | B13: 2390018.3 | F13: Roberto Gustavo Q. | G13: 2760000 | I13: Librería | J13: 455487.12
A14: Tacos 1 1/2" x 3" x 1130mm | B14: 1896995.8 | F14: Adamat | G14: 1942282.9 | I14: Lubricantes | J14: 93240
A15: PLANCHUELA 1 X 1/2 X 3/16 | B15: 1754146.7 | F15: Metalúrgica Santa Fe | G15: 1574126.2 | I15: Pintura | J15: 21309.08
A16: ANGULO 1" 1/4 X 1/8 x kg | B16: 1727283.4 | F16: Tech Safe | G16: 1148783.5 | I16: Envío | J16: 12596.18
A17: Precintos 450 x 10 | B17: 1654270.5 | F17: Mix-57 | G17: 1086115.6 | I17: 0 | J17: 0
A18: Tor. Traba 3/8" | B18: 1612650 | F18: Prive | G18: 1045009.2 | I18: (en blanco)
A19: Tubo de Gas (Atal) | B19: 1255000 | F19: Metrochain | G19: 868000 | I19: Total general | J19: 83773125
A20: EU-300 | B20: 1116000 | F20: Franco Damario | G20: 765000
A21: Cerrojo 210 | B21: 1045009.2 | F21: Imperio de la Limpieza | G21: 711668.68
A22: Tuerca Flange Zinc. 3/8" | B22: 1014205.7 | F22: Alpamet | G22: 680800
A23: Bolsas Tubos x 100 mic | B23: 885380 | F23: Greenfilm | G23: 512000
A24: Etiquetas Dobles 50x29 (embalaje) | B24: 870247.8 | F24: Esdevi - Valeria | G24: 442500
A25: Cadena Calibrada | B25: 868000 | F25: Plásticos Aloha | G25: 373380
A26: Tubo de Oxígeno | B26: 865000 | F26: Formaco | G26: 372643.7
A27: Tacos 2" x 2 1/2" x 640mm | B27: 806373.82 | F27: Frío Acero | G27: 320568.6
A28: Grampa Olmar 19 | B28: 787668.75 | F28: Zicari Mariana Elena | G28: 319837
A29: Bolsas de Arpillera 100 x 60 | B29: 765000 | F29: Pallets Buenos Aires | G29: 260000
A30: Zuncho Verde 19mm | B30: 754093.78 | F30: Embalsur | G30: 251480
A31: EU-250 | B31: 750684 | F31: Roguant | G31: 246623.3
... A41: Arandela Plana Zinc. 5/16" | B41: 366750 | F41: Total general | G41: 81017115
A42: EU-150 | B42: 315216
A43: Arandela Plana Zinc. 3/8" | B43: 313875
A44: Pantalón cargo ombú | B44: 292779
A45: Broca 5/16" | B45: 280000
A46: Grampa Omega 3/4" | B46: 277875
A47: Stretch 50 cm C/Mango | B47: 276780.4
A48: Dispénser de rollo de cocina | B48: 267300
A49: Rollo pluribol | B49: 263845
A50: Pallets | B50: 260000
A51: Zapato Ombú prusiano | B51: 257036.8
A52: Grampa Chaveta 19 (3/4") | B52: 252937.5
A53: Precintos 500 x 10 | B53: 250992.72
... A123: Total general | B123: 83773125
